Workbook

Sheet PF
Q1: PF | R1: PF | S1: PF
G2: PF
J4: GERAL
A6: 0.27222222 | B6: Du's 8 | C6: CAPACITY | D6: TEMPO DISP | E6: DISCAGEM | F6: ATENDIDA | G6: CPC | H6: CPCA | I6: PROPOSTA | J6: PAGAMENTO | K6: ($) CASH | L6: ($) TKT CASH | M6: ($) CONTABIL | N6: ($) TKT CONTABIL | O6: (%) CONVERSÃO | P6: =AUX!B11 -> (%) CPC | Q6: (%) EFETIVIDADE
C7: 9 | D7: =C7*A6 -> 2.45 | E7: 16539 | F7: 308 | G7: =AUX!C2 -> 17 | H7: =AUX!C3 -> 11 | I7: =AUX!C4 -> 2 | J7: =AUX!C5 -> 1 | K7: =AUX!C6 -> 12516.182 | L7: =AUX!C7 -> 5973.63 | M7: =AUX!C8 -> 210239.32 | N7: =AUX!C9 -> 105119.66 | O7: =AUX!C10 -> 0.19 | P7: =AUX!C11 -> 0.56 | Q7: =AUX!C12 -> 0.7
A9: 8 | B9: META GERAL | C9: 7 | D9: =D7*A9 -> 19.6 | E9: =E7*A9 -> 132312 | F9: =F7*A9 -> 2464 | G9: =G7*A9 -> 136 | H9: =H7*A9 -> 88 | I9: =I7*A9 -> 16 | J9: =J7*A9 -> 8 | K9: 357000 | L9: 14236.15 | M9: 5000000 | N9: 103800.73 | O9: =O7 -> 0.19 | P9: =P7 -> 0.56 | Q9: =Q7 -> 0.7
B10: REALIZADO | C10: =AVERAGE(C17:C24) -> 5.774423 | D10: =SUM(D17:D37) -> 12.57541 | E10: =SUM(E17:E37) -> 499351 | F10: =SUM(F17:F37) -> 5455 | G10: =SUM(G17:G37) -> 304 | H10: =SUM(H17:H37) -> 112 | I10: =SUM(I17:I36) -> 20 | J10: =SUM(J17:J36) -> 7 | K10: =SUM(K17:K37) -> 88313.9 | L10: =IFERROR(K10/J10,0) -> 12616.271 | M10: =SUM(M17:M36) -> 283641.89 | N10: =IFERROR(M10/J10,0) -> 40520.27 | O10: =AVERAGE(O17:O36) -> 0.078132481 | P10: =AVERAGE(P17:P24) -> 0.3790389 | Q10: =IFERROR(AVERAGE(Q17:Q36),0) -> 0.58333333
B11: META RELOGIO | C11: - | D11: =D7*(COUNTIFS(D17:D36,">="&0)) -> 49 | E11: =E7*(COUNTIFS(E17:E34,">="&1)) -> 132312 | F11: =F7*(COUNTIFS(F17:F34,">="&1)) -> 2464 | G11: =G7*(COUNTIFS(G17:G37,">="&1)) -> 136 | H11: =H7*(COUNTIFS(H17:H34,">="&1)) -> 88 | I11: =I7*(COUNTIFS(I17:I34,">="&1)) -> 14 | J11: =J7*(COUNTIFS(J17:J34,">="&1)) -> 5 | K11: =K7*(COUNTIFS(G17:G34,">="&1)) -> 100129.46 | L11: =L9 -> 14236.15 | M11: =M7*(COUNTIFS(G17:G29,">="&1)) -> 1681914.6 | N11: =N9 -> 103800.73 | O11: =O9 -> 0.19 | P11: =P9 -> 0.56 | Q11: =Q9 -> 0.7
B13: (%) META REALIZADO | C13: =C10/C9 -> 0.82491757 | D13: =D10/D9 -> 0.64160255 | E13: =E10/E9 -> 3.7740417 | F13: =F10/F9 -> 2.2138799 | G13: =G10/G9 -> 2.2352941 | H13: =H10/H9 -> 1.2727273 | I13: =I10/I9 -> 1.25 | J13: =J10/J9 -> 0.875 | ... P13: =P10/P9 -> 0.67685518 | Q13: =IFERROR(Q10/Q9,0) -> 0.83333333
B14: (%) META RELOGIO | C14: - | D14: =D10/D11 -> 0.25664102 | E14: =E10/E11 -> 3.7740417 | F14: =F10/F11 -> 2.2138799 | G14: =G10/G11 -> 2.2352941 | H14: =H10/H11 -> 1.2727273 | I14: =I10/I11 -> 1.4285714 | J14: =IFERROR(J10/J11,0) -> 1.4 | K14: =K10/K11 -> 0.88199717 | L14: =L10/L11 -> 0.88621372 | M14: =M10/M11 -> 0.16864227 | N14: =N10/N11 -> 0.39036594 | O14: =O10/O11 -> 0.41122358 | P14: =P10/P9 -> 0.67685518 | Q14: =IFERROR(Q10/Q9,0) -> 0.83333333
B16: DATA | C16: REALIZADO | D16: TEMPO REALIZADO | E16: DISCAGEM | F16: ATENDIDA | G16: CPC | H16: CPCA | I16: PROPOSTA | J16: PAGAMENTO | K16: ($) CASH | L16: ($) TKT CASH | M16: ($) CONTABIL | N16: ($) TKT CONTABIL | O16: (%) CONVERSÃO | P16: (%) CPC | Q16: (%) EFETIVIDADE
B17: 46266 | C17: =D17/$A$6 -> 5.3086776 | D17: =SUMIFS(TEMPOS!AL:AL,TEMPOS!X:X,PF!$Q$1,TEMPOS!Y:Y,B17) -> 1.44514 | E17: =SUMIFS('HORA HORA'!G:G,'HORA HORA'!C:C,PF!$S$1,'HORA HORA'!B:B,PF!B17) -> 49688 | F17: =SUMIFS('HORA HORA'!H:H,'HORA HORA'!B:B,PF!B17,'HORA HORA'!C:C,PF!$S$1) -> 631 | G17: =SUMIFS('HORA HORA'!J:J,'HORA HORA'!C:C,PF!$G$2,'HORA HORA'!B:B,B17,'HORA HORA'!C:C,PF!$G$2) -> 44 | H17: =SUMIFS('HORA HORA'!K:K,'HORA HORA'!C:C,PF!$G$2,'HORA HORA'!B:B,B17,'HORA HORA'!C:C,PF!$G$2) -> 14 | I17: =SUMIFS('HORA HORA'!L:L,'HORA HORA'!C:C,PF!$G$2,'HORA HORA'!B:B,B17,'HORA HORA'!C:C,PF!$G$2) -> 1 | J17: =COUNTIFS(ACOMPANHAMENTO!S:S,"ACORDO IMPLANTADO",ACOMPANHAMENTO!BC:BC,B17,ACOMPANHAMENTO!H:H,PF!$G$2) -> 0 | K17: =SUMIFS(ACOMPANHAMENTO!O:O,ACOMPANHAMENTO!H:H,PF!$G$2,ACOMPANHAMENTO!BC:BC,B17) -> 0 | L17: =K17/I17 -> 0 | M17: =SUMIFS(ACOMPANHAMENTO!R:R,ACOMPANHAMENTO!H:H,PF!$G$2,ACOMPANHAMENTO!BC:BC,PF!B17) -> 0 | N17: =M17/I17 -> 0 | O17: =IFERROR(IF(I17/G17=0,"-",I17/G17),"-") -> 0.022727273 | P17: =SUMIFS('HORA HORA'!$K:$K,'HORA HORA'!$B:$B,$B17,'HORA HORA'!$C:$C,"="&"PF")/SUMIFS('HORA HORA'!$J:$J,'HORA HORA'!$B:$B,PF!$B17,'HORA HORA'!$C:$C,$G$2) -> 0.31818182 | Q17: =IFERROR(IF(J17/I17=0,"-",J17/I17),"-") -> -
B18: 46267 | C18: =D18/$A$6 -> 7.1256784 | D18: =SUMIFS(TEMPOS!AL:AL,TEMPOS!X:X,PF!$Q$1,TEMPOS!Y:Y,B18) -> 1.939768 | E18: =SUMIFS('HORA HORA'!G:G,'HORA HORA'!C:C,PF!$S$1,'HORA HORA'!B:B,PF!B18) -> 66752 | F18: =SUMIFS('HORA HORA'!H:H,'HORA HORA'!B:B,PF!B18,'HORA HORA'!C:C,PF!$S$1) -> 699 | G18: =SUMIFS('HORA HORA'!J:J,'HORA HORA'!C:C,PF!$G$2,'HORA HORA'!B:B,B18,'HORA HORA'!C:C,PF!$G$2) -> 49 | H18: =SUMIFS('HORA HORA'!K:K,'HORA HORA'!C:C,PF!$G$2,'HORA HORA'!B:B,B18,'HORA HORA'!C:C,PF!$G$2) -> 14 | I18: =SUMIFS('HORA HORA'!L:L,'HORA HORA'!C:C,PF!$G$2,'HORA HORA'!B:B,B18,'HORA HORA'!C:C,PF!$G$2) -> 4 | J18: =COUNTIFS(ACOMPANHAMENTO!S:S,"ACORDO IMPLANTADO",ACOMPANHAMENTO!BC:BC,B18,ACOMPANHAMENTO!H:H,PF!$G$2) -> 0 | K18: =SUMIFS(ACOMPANHAMENTO!O:O,ACOMPANHAMENTO!H:H,PF!$G$2,ACOMPANHAMENTO!BC:BC,B18) -> 0 | L18: =IFERROR(K18/I18,0) -> 0 | M18: =SUMIFS(ACOMPANHAMENTO!R:R,ACOMPANHAMENTO!H:H,PF!$G$2,ACOMPANHAMENTO!BC:BC,PF!B18) -> 0 | N18: =IFERROR(M18/I18,0) -> 0 | O18: =IFERROR(IF(I18/G18=0,"-",I18/G18),"-") -> 0.081632653 | P18: =IFERROR(SUMIFS('HORA HORA'!$K:$K,'HORA HORA'!$B:$B,$B18,'HORA HORA'!$C:$C,"="&"PF")/SUMIFS('HORA HORA'!$J:$J,'HORA HORA'!$B:$B,PF!$B18,'HORA HORA'!$C:$C,$G$2),0) -> 0.28571429 | Q18: =IFERROR(IF(J18/I18=0,"-",J18/I18),"-") -> -
B19: 46268 | C19: =D19/$A$6 -> 6.1508094 | D19: =SUMIFS(TEMPOS!AL:AL,TEMPOS!X:X,PF!$Q$1,TEMPOS!Y:Y,B19) -> 1.674387 | E19: =SUMIFS('HORA HORA'!G:G,'HORA HORA'!C:C,PF!$S$1,'HORA HORA'!B:B,PF!B19) -> 65425 | F19: =SUMIFS('HORA HORA'!H:H,'HORA HORA'!B:B,PF!B19,'HORA HORA'!C:C,PF!$S$1) -> 644 | G19: =SUMIFS('HORA HORA'!J:J,'HORA HORA'!C:C,PF!$G$2,'HORA HORA'!B:B,B19,'HORA HORA'!C:C,PF!$G$2) -> 40 | H19: =SUMIFS('HORA HORA'!K:K,'HORA HORA'!C:C,PF!$G$2,'HORA HORA'!B:B,B19,'HORA HORA'!C:C,PF!$G$2) -> 10 | I19: =SUMIFS('HORA HORA'!L:L,'HORA HORA'!C:C,PF!$G$2,'HORA HORA'!B:B,B19,'HORA HORA'!C:C,PF!$G$2) -> 2 | J19: =COUNTIFS(ACOMPANHAMENTO!S:S,"ACORDO IMPLANTADO",ACOMPANHAMENTO!BC:BC,B19,ACOMPANHAMENTO!H:H,PF!$G$2) -> 0 | K19: =SUMIFS(ACOMPANHAMENTO!O:O,ACOMPANHAMENTO!H:H,PF!$G$2,ACOMPANHAMENTO!BC:BC,B19) -> 0 | L19: =IFERROR(K19/I19,0) -> 0 | M19: =SUMIFS(ACOMPANHAMENTO!R:R,ACOMPANHAMENTO!H:H,PF!$G$2,ACOMPANHAMENTO!BC:BC,PF!B19) -> 0 | N19: =IFERROR(M19/I19,0) -> 0 | O19: =IFERROR(IF(I19/G19=0,"-",I19/G19),"-") -> 0.05 | P19: =IFERROR(SUMIFS('HORA HORA'!$K:$K,'HORA HORA'!$B:$B,$B19,'HORA HORA'!$C:$C,"="&"PF")/SUMIFS('HORA HORA'!$J:$J,'HORA HORA'!$B:$B,PF!$B19,'HORA HORA'!$C:$C,$G$2),0) -> 0.25 | Q19: =IFERROR(IF(J19/I19=0,"-",J19/I19),"-") -> -
B20: 46269 | C20: =D20/$A$6 -> 6.9091457 | D20: =SUMIFS(TEMPOS!AL:AL,TEMPOS!X:X,PF!$Q$1,TEMPOS!Y:Y,B20) -> 1.880823 | E20: =SUMIFS('HORA HORA'!G:G,'HORA HORA'!C:C,PF!$S$1,'HORA HORA'!B:B,PF!B20) -> 67901 | F20: =SUMIFS('HORA HORA'!H:H,'HORA HORA'!B:B,PF!B20,'HORA HORA'!C:C,PF!$S$1) -> 659 | G20: =SUMIFS('HORA HORA'!J:J,'HORA HORA'!C:C,PF!$G$2,'HORA HORA'!B:B,B20,'HORA HORA'!C:C,PF!$G$2) -> 31 | H20: =SUMIFS('HORA HORA'!K:K,'HORA HORA'!C:C,PF!$G$2,'HORA HORA'!B:B,B20,'HORA HORA'!C:C,PF!$G$2) -> 12 | I20: =SUMIFS('HORA HORA'!L:L,'HORA HORA'!C:C,PF!$G$2,'HORA HORA'!B:B,B20,'HORA HORA'!C:C,PF!$G$2) -> 4 | J20: =COUNTIFS(ACOMPANHAMENTO!S:S,"ACORDO IMPLANTADO",ACOMPANHAMENTO!BC:BC,B20,ACOMPANHAMENTO!H:H,PF!$G$2) -> 1 | K20: =SUMIFS(ACOMPANHAMENTO!O:O,ACOMPANHAMENTO!H:H,PF!$G$2,ACOMPANHAMENTO!BC:BC,B20) -> 5000 | L20: =IFERROR(K20/I20,0) -> 1250 | M20: =SUMIFS(ACOMPANHAMENTO!R:R,ACOMPANHAMENTO!H:H,PF!$G$2,ACOMPANHAMENTO!BC:BC,PF!B20) -> 0 | N20: =IFERROR(M20/I20,0) -> 0 | O20: =IFERROR(IF(I20/G20=0,"-",I20/G20),"-") -> 0.12903226 | P20: =IFERROR(SUMIFS('HORA HORA'!$K:$K,'HORA HORA'!$B:$B,$B20,'HORA HORA'!$C:$C,"="&"PF")/SUMIFS('HORA HORA'!$J:$J,'HORA HORA'!$B:$B,PF!$B20,'HORA HORA'!$C:$C,$G$2),0) -> 0.38709677 | Q20: =IFERROR(IF(J20/I20=0,"-",J20/I20),"-") -> 0.25
B21: 46273 | C21: =D21/$A$6 -> 6.5947776 | D21: =SUMIFS(TEMPOS!AL:AL,TEMPOS!X:X,PF!$Q$1,TEMPOS!Y:Y,B21) -> 1.795245 | E21: =SUMIFS('HORA HORA'!G:G,'HORA HORA'!C:C,PF!$S$1,'HORA HORA'!B:B,PF!B21) -> 59736 | F21: =SUMIFS('HORA HORA'!H:H,'HORA HORA'!B:B,PF!B21,'HORA HORA'!C:C,PF!$S$1) -> 640 | G21: =SUMIFS('HORA HORA'!J:J,'HORA HORA'!C:C,PF!$G$2,'HORA HORA'!B:B,B21,'HORA HORA'!C:C,PF!$G$2) -> 31 | H21: =SUMIFS('HORA HORA'!K:K,'HORA HORA'!C:C,PF!$G$2,'HORA HORA'!B:B,B21,'HORA HORA'!C:C,PF!$G$2) -> 20 | I21: =SUMIFS('HORA HORA'!L:L,'HORA HORA'!C:C,PF!$G$2,'HORA HORA'!B:B,B21,'HORA HORA'!C:C,PF!$G$2) -> 4 | J21: =COUNTIFS(ACOMPANHAMENTO!S:S,"ACORDO IMPLANTADO",ACOMPANHAMENTO!BC:BC,B21,ACOMPANHAMENTO!H:H,PF!$G$2) -> 1 | K21: =SUMIFS(ACOMPANHAMENTO!O:O,ACOMPANHAMENTO!H:H,PF!$G$2,ACOMPANHAMENTO!BC:BC,B21) -> 7735.51 | L21: =IFERROR(K21/I21,0) -> 1933.8775 | M21: =SUMIFS(ACOMPANHAMENTO!R:R,ACOMPANHAMENTO!H:H,PF!$G$2,ACOMPANHAMENTO!BC:BC,PF!B21) -> 69713.73 | N21: =IFERROR(M21/I21,0) -> 17428.432 | O21: =IFERROR(IF(I21/G21=0,"-",I21/G21),"-") -> 0.12903226 | P21: =IFERROR(SUMIFS('HORA HORA'!$K:$K,'HORA HORA'!$B:$B,$B21,'HORA HORA'!$C:$C,"="&"PF")/SUMIFS('HORA HORA'!$J:$J,'HORA HORA'!$B:$B,PF!$B21,'HORA HORA'!$C:$C,$G$2),0) -> 0.64516129 | Q21: =IFERROR(IF(J21/I21=0,"-",J21/I21),"-") -> 0.25
B22: 46274 | C22: =D22/$A$6 -> 6.9705808 | D22: =SUMIFS(TEMPOS!AL:AL,TEMPOS!X:X,PF!$Q$1,TEMPOS!Y:Y,B22) -> 1.897547 | E22: =SUMIFS('HORA HORA'!G:G,'HORA HORA'!C:C,PF!$S$1,'HORA HORA'!B:B,PF!B22) -> 61385 | F22: =SUMIFS('HORA HORA'!H:H,'HORA HORA'!B:B,PF!B22,'HORA HORA'!C:C,PF!$S$1) -> 810 | G22: =SUMIFS('HORA HORA'!J:J,'HORA HORA'!C:C,PF!$G$2,'HORA HORA'!B:B,B22,'HORA HORA'!C:C,PF!$G$2) -> 36 | H22: =SUMIFS('HORA HORA'!K:K,'HORA HORA'!C:C,PF!$G$2,'HORA HORA'!B:B,B22,'HORA HORA'!C:C,PF!$G$2) -> 11 | I22: =SUMIFS('HORA HORA'!L:L,'HORA HORA'!C:C,PF!$G$2,'HORA HORA'!B:B,B22,'HORA HORA'!C:C,PF!$G$2) -> 2 | J22: =COUNTIFS(ACOMPANHAMENTO!S:S,"ACORDO IMPLANTADO",ACOMPANHAMENTO!BC:BC,B22,ACOMPANHAMENTO!H:H,PF!$G$2) -> 3 | K22: =SUMIFS(ACOMPANHAMENTO!O:O,ACOMPANHAMENTO!H:H,PF!$G$2,ACOMPANHAMENTO!BC:BC,B22) -> 50446.06 | L22: =IFERROR(K22/I22,0) -> 25223.03 | M22: =SUMIFS(ACOMPANHAMENTO!R:R,ACOMPANHAMENTO!H:H,PF!$G$2,ACOMPANHAMENTO!BC:BC,PF!B22) -> 91192.87 | N22: =IFERROR(M22/I22,0) -> 45596.435 | O22: =IFERROR(IF(I22/G22=0,"-",I22/G22),"-") -> 0.055555556 | P22: =IFERROR(SUMIFS('HORA HORA'!$K:$K,'HORA HORA'!$B:$B,$B22,'HORA HORA'!$C:$C,"="&"PF")/SUMIFS('HORA HORA'!$J:$J,'HORA HORA'!$B:$B,PF!$B22,'HORA HORA'!$C:$C,$G$2),0) -> 0.30555556 | Q22: =IFERROR(IF(J22/I22=0,"-",J22/I22),"-") -> 1.5
B23: 46275 | C23: =D23/$A$6 -> 7.1357143 | D23: =SUMIFS(TEMPOS!AL:AL,TEMPOS!X:X,PF!$Q$1,TEMPOS!Y:Y,B23) -> 1.9425 | E23: =SUMIFS('HORA HORA'!G:G,'HORA HORA'!C:C,PF!$S$1,'HORA HORA'!B:B,PF!B23) -> 60597 | F23: =SUMIFS('HORA HORA'!H:H,'HORA HORA'!B:B,PF!B23,'HORA HORA'!C:C,PF!$S$1) -> 656 | G23: =SUMIFS('HORA HORA'!J:J,'HORA HORA'!C:C,PF!$G$2,'HORA HORA'!B:B,B23,'HORA HORA'!C:C,PF!$G$2) -> 35 | H23: =SUMIFS('HORA HORA'!K:K,'HORA HORA'!C:C,PF!$G$2,'HORA HORA'!B:B,B23,'HORA HORA'!C:C,PF!$G$2) -> 11 | I23: =SUMIFS('HORA HORA'!L:L,'HORA HORA'!C:C,PF!$G$2,'HORA HORA'!B:B,B23,'HORA HORA'!C:C,PF!$G$2) -> 0 | J23: =COUNTIFS(ACOMPANHAMENTO!S:S,"ACORDO IMPLANTADO",ACOMPANHAMENTO!BC:BC,B23,ACOMPANHAMENTO!H:H,PF!$G$2) -> 1 | K23: =SUMIFS(ACOMPANHAMENTO!O:O,ACOMPANHAMENTO!H:H,PF!$G$2,ACOMPANHAMENTO!BC:BC,B23) -> 132.32 | L23: =IFERROR(K23/I23,0) -> 0 | M23: =SUMIFS(ACOMPANHAMENTO!R:R,ACOMPANHAMENTO!H:H,PF!$G$2,ACOMPANHAMENTO!BC:BC,PF!B23) -> 5970.05 | N23: =IFERROR(M23/I23,0) -> 0 | O23: =IFERROR(IF(I23/G23=0,"-",I23/G23),"-") -> - | P23: =IFERROR(SUMIFS('HORA HORA'!$K:$K,'HORA HORA'!$B:$B,$B23,'HORA HORA'!$C:$C,"="&"PF")/SUMIFS('HORA HORA'!$J:$J,'HORA HORA'!$B:$B,PF!$B23,'HORA HORA'!$C:$C,$G$2),0) -> 0.31428571 | Q23: =IFERROR(IF(J23/I23=0,"-",J23/I23),"-") -> -
B24: 46276 | C24: =D24/$A$6 -> 0 | D24: =SUMIFS(TEMPOS!AL:AL,TEMPOS!X:X,PF!$Q$1,TEMPOS!Y:Y,B24) -> 0 | E24: =SUMIFS('HORA HORA'!G:G,'HORA HORA'!C:C,PF!$S$1,'HORA HORA'!B:B,PF!B24) -> 67867 | F24: =SUMIFS('HORA HORA'!H:H,'HORA HORA'!B:B,PF!B24,'HORA HORA'!C:C,PF!$S$1) -> 716 | G24: =SUMIFS('HORA HORA'!J:J,'HORA HORA'!C:C,PF!$G$2,'HORA HORA'!B:B,B24,'HORA HORA'!C:C,PF!$G$2) -> 38 | H24: =SUMIFS('HORA HORA'!K:K,'HORA HORA'!C:C,PF!$G$2,'HORA HORA'!B:B,B24,'HORA HORA'!C:C,PF!$G$2) -> 20 | I24: =SUMIFS('HORA HORA'!L:L,'HORA HORA'!C:C,PF!$G$2,'HORA HORA'!B:B,B24,'HORA HORA'!C:C,PF!$G$2) -> 3 | J24: =COUNTIFS(ACOMPANHAMENTO!S:S,"ACORDO IMPLANTADO",ACOMPANHAMENTO!BC:BC,B24,ACOMPANHAMENTO!H:H,PF!$G$2) -> 1 | K24: =SUMIFS(ACOMPANHAMENTO!O:O,ACOMPANHAMENTO!H:H,PF!$G$2,ACOMPANHAMENTO!BC:BC,B24) -> 25000.01 | L24: =IFERROR(K24/I24,0) -> 8333.3367 | M24: =SUMIFS(ACOMPANHAMENTO!R:R,ACOMPANHAMENTO!H:H,PF!$G$2,ACOMPANHAMENTO!BC:BC,PF!B24) -> 116765.24 | N24: =IFERROR(M24/I24,0) -> 38921.747 | O24: =IFERROR(IF(I24/G24=0,"-",I24/G24),"-") -> 0.078947368 | P24: =IFERROR(SUMIFS('HORA HORA'!$K:$K,'HORA HORA'!$B:$B,$B24,'HORA HORA'!$C:$C,"="&"PF")/SUMIFS('HORA HORA'!$J:$J,'HORA HORA'!$B:$B,PF!$B24,'HORA HORA'!$C:$C,$G$2),0) -> 0.52631579 | Q24: =IFERROR(IF(J24/I24=0,"-",J24/I24),"-") -> 0.33333333
B25: 46279 | C25: =D25/$A$6 -> 0 | D25: =SUMIFS(TEMPOS!AL:AL,TEMPOS!X:X,PF!$Q$1,TEMPOS!Y:Y,B25) -> 0 | E25: =SUMIFS('HORA HORA'!G:G,'HORA HORA'!C:C,PF!$S$1,'HORA HORA'!B:B,PF!B25) -> 0 | F25: =SUMIFS('HORA HORA'!H:H,'HORA HORA'!B:B,PF!B25,'HORA HORA'!C:C,PF!$S$1) -> 0 | G25: =SUMIFS('HORA HORA'!J:J,'HORA HORA'!C:C,PF!$G$2,'HORA HORA'!B:B,B25,'HORA HORA'!C:C,PF!$G$2) -> 0 | H25: =SUMIFS('HORA HORA'!K:K,'HORA HORA'!C:C,PF!$G$2,'HORA HORA'!B:B,B25,'HORA HORA'!C:C,PF!$G$2) -> 0 | I25: =SUMIFS('HORA HORA'!L:L,'HORA HORA'!C:C,PF!$G$2,'HORA HORA'!B:B,B25,'HORA HORA'!C:C,PF!$G$2) -> 0 | J25: =COUNTIFS(ACOMPANHAMENTO!S:S,"ACORDO IMPLANTADO",ACOMPANHAMENTO!BC:BC,B25,ACOMPANHAMENTO!H:H,PF!$G$2) -> 0 | K25: =SUMIFS(ACOMPANHAMENTO!O:O,ACOMPANHAMENTO!H:H,PF!$G$2,ACOMPANHAMENTO!BC:BC,B25) -> 0 | L25: =IFERROR(K25/I25,0) -> 0 | M25: =SUMIFS(ACOMPANHAMENTO!R:R,ACOMPANHAMENTO!H:H,PF!$G$2,ACOMPANHAMENTO!BC:BC,PF!B25) -> 0 | N25: =IFERROR(M25/I25,0) -> 0 | O25: =IFERROR(IF(I25/G25=0,"-",I25/G25),"-") -> - | P25: =IFERROR(SUMIFS('HORA HORA'!$K:$K,'HORA HORA'!$B:$B,$B25,'HORA HORA'!$C:$C,"="&"PF")/SUMIFS('HORA HORA'!$J:$J,'HORA HORA'!$B:$B,PF!$B25,'HORA HORA'!$C:$C,$G$2),0) -> 0 | Q25: =IFERROR(IF(J25/I25=0,"-",J25/I25),"-") -> -
B26: 46280 | C26: =D26/$A$6 -> 0 | D26: =SUMIFS(TEMPOS!AL:AL,TEMPOS!X:X,PF!$Q$1,TEMPOS!Y:Y,B26) -> 0 | E26: =SUMIFS('HORA HORA'!G:G,'HORA HORA'!C:C,PF!$S$1,'HORA HORA'!B:B,PF!B26) -> 0 | F26: =SUMIFS('HORA HORA'!H:H,'HORA HORA'!B:B,PF!B26,'HORA HORA'!C:C,PF!$S$1) -> 0 | G26: =SUMIFS('HORA HORA'!J:J,'HORA HORA'!C:C,PF!$G$2,'HORA HORA'!B:B,B26,'HORA HORA'!C:C,PF!$G$2) -> 0 | H26: =SUMIFS('HORA HORA'!K:K,'HORA HORA'!C:C,PF!$G$2,'HORA HORA'!B:B,B26,'HORA HORA'!C:C,PF!$G$2) -> 0 | I26: =SUMIFS('HORA HORA'!L:L,'HORA HORA'!C:C,PF!$G$2,'HORA HORA'!B:B,B26,'HORA HORA'!C:C,PF!$G$2) -> 0 | J26: =COUNTIFS(ACOMPANHAMENTO!S:S,"ACORDO IMPLANTADO",ACOMPANHAMENTO!BC:BC,B26,ACOMPANHAMENTO!H:H,PF!$G$2) -> 0 | K26: =SUMIFS(ACOMPANHAMENTO!O:O,ACOMPANHAMENTO!H:H,PF!$G$2,ACOMPANHAMENTO!BC:BC,B26) -> 0 | L26: =IFERROR(K26/I26,0) -> 0 | M26: =SUMIFS(ACOMPANHAMENTO!R:R,ACOMPANHAMENTO!H:H,PF!$G$2,ACOMPANHAMENTO!BC:BC,PF!B26) -> 0 | N26: =IFERROR(M26/I26,0) -> 0 | O26: =IFERROR(IF(I26/G26=0,"-",I26/G26),"-") -> - | P26: =IFERROR(SUMIFS('HORA HORA'!$K:$K,'HORA HORA'!$B:$B,$B26,'HORA HORA'!$C:$C,"="&"PF")/SUMIFS('HORA HORA'!$J:$J,'HORA HORA'!$B:$B,PF!$B26,'HORA HORA'!$C:$C,$G$2),0) -> 0 | Q26: =IFERROR(IF(J26/I26=0,"-",J26/I26),"-") -> -
B27: 46281 | C27: =D27/$A$6 -> 0 | D27: =SUMIFS(TEMPOS!AL:AL,TEMPOS!X:X,PF!$Q$1,TEMPOS!Y:Y,B27) -> 0 | E27: =SUMIFS('HORA HORA'!G:G,'HORA HORA'!C:C,PF!$S$1,'HORA HORA'!B:B,PF!B27) -> 0 | F27: =SUMIFS('HORA HORA'!H:H,'HORA HORA'!B:B,PF!B27,'HORA HORA'!C:C,PF!$S$1) -> 0 | G27: =SUMIFS('HORA HORA'!J:J,'HORA HORA'!C:C,PF!$G$2,'HORA HORA'!B:B,B27,'HORA HORA'!C:C,PF!$G$2) -> 0 | H27: =SUMIFS('HORA HORA'!K:K,'HORA HORA'!C:C,PF!$G$2,'HORA HORA'!B:B,B27,'HORA HORA'!C:C,PF!$G$2) -> 0 | I27: =SUMIFS('HORA HORA'!L:L,'HORA HORA'!C:C,PF!$G$2,'HORA HORA'!B:B,B27,'HORA HORA'!C:C,PF!$G$2) -> 0 | J27: =COUNTIFS(ACOMPANHAMENTO!S:S,"ACORDO IMPLANTADO",ACOMPANHAMENTO!BC:BC,B27,ACOMPANHAMENTO!H:H,PF!$G$2) -> 0 | K27: =SUMIFS(ACOMPANHAMENTO!O:O,ACOMPANHAMENTO!H:H,PF!$G$2,ACOMPANHAMENTO!BC:BC,B27) -> 0 | L27: =IFERROR(K27/I27,0) -> 0 | M27: =SUMIFS(ACOMPANHAMENTO!R:R,ACOMPANHAMENTO!H:H,PF!$G$2,ACOMPANHAMENTO!BC:BC,PF!B27) -> 0 | N27: =IFERROR(M27/I27,0) -> 0 | O27: =IFERROR(IF(I27/G27=0,"-",I27/G27),"-") -> - | P27: =IFERROR(SUMIFS('HORA HORA'!$K:$K,'HORA HORA'!$B:$B,$B27,'HORA HORA'!$C:$C,"="&"PF")/SUMIFS('HORA HORA'!$J:$J,'HORA HORA'!$B:$B,PF!$B27,'HORA HORA'!$C:$C,$G$2),0) -> 0 | Q27: =IFERROR(IF(J27/I27=0,"-",J27/I27),"-") -> -
B28: 46282 | C28: =D28/$A$6 -> 0 | D28: =SUMIFS(TEMPOS!AL:AL,TEMPOS!X:X,PF!$Q$1,TEMPOS!Y:Y,B28) -> 0 | E28: =SUMIFS('HORA HORA'!G:G,'HORA HORA'!C:C,PF!$S$1,'HORA HORA'!B:B,PF!B28) -> 0 | F28: =SUMIFS('HORA HORA'!H:H,'HORA HORA'!B:B,PF!B28,'HORA HORA'!C:C,PF!$S$1) -> 0 | G28: =SUMIFS('HORA HORA'!J:J,'HORA HORA'!C:C,PF!$G$2,'HORA HORA'!B:B,B28,'HORA HORA'!C:C,PF!$G$2) -> 0 | H28: =SUMIFS('HORA HORA'!K:K,'HORA HORA'!C:C,PF!$G$2,'HORA HORA'!B:B,B28,'HORA HORA'!C:C,PF!$G$2) -> 0 | I28: =SUMIFS('HORA HORA'!L:L,'HORA HORA'!C:C,PF!$G$2,'HORA HORA'!B:B,B28,'HORA HORA'!C:C,PF!$G$2) -> 0 | J28: =COUNTIFS(ACOMPANHAMENTO!S:S,"ACORDO IMPLANTADO",ACOMPANHAMENTO!BC:BC,B28,ACOMPANHAMENTO!H:H,PF!$G$2) -> 0 | K28: =SUMIFS(ACOMPANHAMENTO!O:O,ACOMPANHAMENTO!H:H,PF!$G$2,ACOMPANHAMENTO!BC:BC,B28) -> 0 | L28: =IFERROR(K28/I28,0) -> 0 | M28: =SUMIFS(ACOMPANHAMENTO!R:R,ACOMPANHAMENTO!H:H,PF!$G$2,ACOMPANHAMENTO!BC:BC,PF!B28) -> 0 | N28: =IFERROR(M28/I28,0) -> 0 | O28: =IFERROR(IF(I28/G28=0,"-",I28/G28),"-") -> - | P28: =IFERROR(SUMIFS('HORA HORA'!$K:$K,'HORA HORA'!$B:$B,$B28,'HORA HORA'!$C:$C,"="&"PF")/SUMIFS('HORA HORA'!$J:$J,'HORA HORA'!$B:$B,PF!$B28,'HORA HORA'!$C:$C,$G$2),0) -> 0 | Q28: =IFERROR(IF(J28/I28=0,"-",J28/I28),"-") -> -
B29: 46283 | C29: =D29/$A$6 -> 0 | D29: =SUMIFS(TEMPOS!AL:AL,TEMPOS!X:X,PF!$Q$1,TEMPOS!Y:Y,B29) -> 0 | E29: =SUMIFS('HORA HORA'!G:G,'HORA HORA'!C:C,PF!$S$1,'HORA HORA'!B:B,PF!B29) -> 0 | F29: =SUMIFS('HORA HORA'!H:H,'HORA HORA'!B:B,PF!B29,'HORA HORA'!C:C,PF!$S$1) -> 0 | G29: =SUMIFS('HORA HORA'!J:J,'HORA HORA'!C:C,PF!$G$2,'HORA HORA'!B:B,B29,'HORA HORA'!C:C,PF!$G$2) -> 0 | H29: =SUMIFS('HORA HORA'!K:K,'HORA HORA'!C:C,PF!$G$2,'HORA HORA'!B:B,B29,'HORA HORA'!C:C,PF!$G$2) -> 0 | I29: =SUMIFS('HORA HORA'!L:L,'HORA HORA'!C:C,PF!$G$2,'HORA HORA'!B:B,B29,'HORA HORA'!C:C,PF!$G$2) -> 0 | J29: =COUNTIFS(ACOMPANHAMENTO!S:S,"ACORDO IMPLANTADO",ACOMPANHAMENTO!BC:BC,B29,ACOMPANHAMENTO!H:H,PF!$G$2) -> 0 | K29: =SUMIFS(ACOMPANHAMENTO!O:O,ACOMPANHAMENTO!H:H,PF!$G$2,ACOMPANHAMENTO!BC:BC,B29) -> 0 | L29: =IFERROR(K29/I29,0) -> 0 | M29: =SUMIFS(ACOMPANHAMENTO!R:R,ACOMPANHAMENTO!H:H,PF!$G$2,ACOMPANHAMENTO!BC:BC,PF!B29) -> 0 | N29: =IFERROR(M29/I29,0) -> 0 | O29: =IFERROR(IF(I29/G29=0,"-",I29/G29),"-") -> - | P29: =IFERROR(SUMIFS('HORA HORA'!$K:$K,'HORA HORA'!$B:$B,$B29,'HORA HORA'!$C:$C,"="&"PF")/SUMIFS('HORA HORA'!$J:$J,'HORA HORA'!$B:$B,PF!$B29,'HORA HORA'!$C:$C,$G$2),0) -> 0 | Q29: =IFERROR(IF(J29/I29=0,"-",J29/I29),"-") -> -
... B37: 46295 | C37: =D37/$A$6 -> 0 | D37: =SUMIFS(TEMPOS!AL:AL,TEMPOS!X:X,PF!$Q$1,TEMPOS!Y:Y,B37) -> 0 | E37: =SUMIFS('HORA HORA'!G:G,'HORA HORA'!C:C,PF!$S$1,'HORA HORA'!B:B,PF!B37) -> 0 | F37: =SUMIFS('HORA HORA'!H:H,'HORA HORA'!B:B,PF!B37,'HORA HORA'!C:C,PF!$S$1) -> 0 | G37: =SUMIFS('HORA HORA'!J:J,'HORA HORA'!C:C,PF!$G$2,'HORA HORA'!B:B,B37,'HORA HORA'!C:C,PF!$G$2) -> 0 | H37: =SUMIFS('HORA HORA'!K:K,'HORA HORA'!C:C,PF!$G$2,'HORA HORA'!B:B,B37,'HORA HORA'!C:C,PF!$G$2) -> 0 | I37: =SUMIFS('HORA HORA'!L:L,'HORA HORA'!C:C,PF!$G$2,'HORA HORA'!B:B,B37,'HORA HORA'!C:C,PF!$G$2) -> 0 | J37: =COUNTIFS(ACOMPANHAMENTO!S:S,"ACORDO IMPLANTADO",ACOMPANHAMENTO!BC:BC,B37,ACOMPANHAMENTO!H:H,PF!$G$2) -> 0 | K37: =SUMIFS(ACOMPANHAMENTO!O:O,ACOMPANHAMENTO!H:H,PF!$G$2,ACOMPANHAMENTO!BC:BC,B37) -> 0 | L37: =IFERROR(K37/I37,0) -> 0 | M37: =SUMIFS(ACOMPANHAMENTO!R:R,ACOMPANHAMENTO!H:H,PF!$G$2,ACOMPANHAMENTO!BC:BC,PF!B37) -> 0 | N37: =IFERROR(M37/I37,0) -> 0 | O37: =IFERROR(IF(I37/G37=0,"-",I37/G37),"-") -> - | P37: =IFERROR(SUMIFS('HORA HORA'!$K:$K,'HORA HORA'!$B:$B,$B37,'HORA HORA'!$C:$C,"="&"PF")/SUMIFS('HORA HORA'!$J:$J,'HORA HORA'!$B:$B,PF!$B37,'HORA HORA'!$C:$C,$G$2),0) -> 0 | Q37: =IFERROR(IF(J37/I37=0,"-",J37/I37),"-") -> -

Sheet PJ_B1
R1: PJ
I2: Business Banking 1 | R2: B1
A6: 0.27222222 | B6: DIA | C6: CAPACITY | D6: TEMPO DISP | E6: DISCAGEM | F6: ATENDIDA | G6: CPC | H6: CPCA | I6: PROPOSTA | J6: PAGAMENTO | K6: ($) CASH | L6: ($) TKT CASH | M6: ($) CONTABIL | N6: ($) TKT CONTABIL | O6: (%) CONVERSÃO | P6: =AUX!B11 -> (%) CPC | Q6: (%) EFETIVIDADE
A7: 0.27222222 | C7: 10 | D7: =A7*7 -> 1.9055556 | E7: 55737 | F7: 1165 | G7: =AUX!C15 -> 70 | H7: =AUX!C16 -> 46 | I7: =AUX!C17 -> 12 | J7: =AUX!C18 -> 5 | K7: =AUX!C19 -> 75686.94 | L7: =AUX!C20 -> 6307.245 | M7: =AUX!C21 -> 976768.68 | N7: =AUX!C22 -> 81397.39 | O7: =AUX!C35 -> 0.43 | P7: =AUX!C36 -> 0.58 | Q7: =AUX!C37 -> 0.46
A9: 8 | B9: META GERAL | C9: 13 | D9: =D7*A9 -> 15.244444 | E9: =E7*A9 -> 445896 | F9: =F7*A9 -> 9320 | G9: =G7*A9 -> 560 | H9: =H7*A9 -> 368 | I9: =I7*A9 -> 96 | J9: =J7*A9 -> 40 | K9: 1245000 | L9: =L7 -> 6307.245 | M9: 10200000 | N9: =N7 -> 81397.39 | O9: =O7 -> 0.43 | P9: =P7 -> 0.58 | Q9: =Q7 -> 0.46
B10: REALIZADO | C10: =AVERAGE(C17:C23) -> 5.2065268 | D10: =SUM(D17:D37) -> 9.921326 | E10: =SUM(E17:E37) -> 494185 | F10: =SUM(F17:F37) -> 8528 | G10: =SUM(G17:G37) -> 414 | H10: =SUM(H17:H32) -> 245 | I10: =SUM(I17:I32) -> 61 | J10: =SUM(J17:J32) -> 31 | K10: =SUM(K17:K32) -> 565753.49 | L10: =IFERROR(K10/J10,0) -> 18250.113 | M10: =SUM(M17:M28) -> 1772364.6 | N10: =IFERROR(M10/J10,0) -> 57173.05 | O10: =AVERAGE(O17:O37) -> 0.14719954 | P10: =AVERAGE(P17:P24) -> 0.59106594 | Q10: =AVERAGE(Q17:Q37) -> 0.70699405
B11: META RELOGIO | C11: - | D11: =D7*(COUNTIFS(D17:D33,">="&0)) -> 32.394444 | E11: =E7*(COUNTIFS(E17:E33,">="&1)) -> 445896 | F11: =F7*(COUNTIFS(F17:F33,">="&1)) -> 9320 | G11: =G7*(COUNTIFS(G16:G33,">="&1)) -> 560 | H11: =H7*(COUNTIFS(H16:H29,">="&1)) -> 368 | I11: =I7*(COUNTIFS(I16:I29,">="&1)) -> 96 | J11: =J7*(COUNTIFS(J16:J29,">="&1)) -> 35 | K11: =K7*(COUNTIFS(K16:K29,">="&1)) -> 529808.58 | L11: =L9 -> 6307.245 | M11: =M7*(COUNTIFS(M16:M29,">="&1)) -> 6837380.8 | N11: =N9 -> 81397.39 | O11: =O9 -> 0.43 | P11: =P9 -> 0.58 | Q11: =Q9 -> 0.46
B13: (%) META REALIZADO | C13: =C10/C9 -> 0.40050206 | D13: =D10/D9 -> 0.65081585 | E13: =E10/E9 -> 1.1082966 | F13: =F10/F9 -> 0.91502146 | G13: =G10/G9 -> 0.73928571 | H13: =H10/H9 -> 0.66576087 | I13: =I10/I9 -> 0.63541667 | J13: =J10/J9 -> 0.775 | ... Q13: =Q10/Q9 -> 1.5369436
B14: (%) META RELOGIO | C14: - | D14: =D10/D11 -> 0.30626628 | E14: =E10/E11 -> 1.1082966 | F14: =F10/F11 -> 0.91502146 | G14: =G10/G11 -> 0.73928571 | H14: =H10/H11 -> 0.66576087 | I14: =I10/I11 -> 0.63541667 | J14: =IFERROR(J10/J11,0) -> 0.88571429 | K14: =IFERROR(K10/K11,0) -> 1.0678451 | L14: =L10/L11 -> 2.8935157 | M14: =IFERROR(M10/M11,0) -> 0.25921689 | N14: =N10/N11 -> 0.70239415 | O14: =O10/O11 -> 0.34232452 | P14: =P10/P11 -> 1.0190792 | Q14: =Q10/Q11 -> 1.5369436
B16: DATA | C16: REALIZADO | D16: TEMPO REALIZADO | E16: DISCAGEM | F16: ATENDIDA | G16: CPC | H16: CPCA | I16: PROPOSTA | J16: PAGAMENTO | K16: ($) CASH | L16: ($) TKT CASH | M16: ($) CONTABIL | N16: ($) TKT CONTABIL | O16: (%) CONVERSÃO | P16: (%) CPC | Q16: (%) EFETIVIDADE
B17: 46266 | C17: =D17/$A$7 -> 6.3419327 | D17: =SUMIFS(TEMPOS!AL:AL,TEMPOS!X:X,$R$2,TEMPOS!Y:Y,B17) -> 1.726415 | E17: =SUMIFS('HORA HORA'!G:G,'HORA HORA'!C:C,PJ_B1!$R$1,'HORA HORA'!B:B,PJ_B1!B17,'HORA HORA'!Y:Y,"<>"&"EMPRESAS_2") -> 48484 | F17: =SUMIFS('HORA HORA'!H:H,'HORA HORA'!C:C,PJ_B1!$R$1,'HORA HORA'!B:B,PJ_B1!B17,'HORA HORA'!Y:Y,"<>"&"EMPRESAS_2") -> 1186 | G17: =SUMIFS('HORA HORA'!J:J,'HORA HORA'!C:C,PJ_B1!$R$1,'HORA HORA'!B:B,PJ_B1!B17,'HORA HORA'!Y:Y,"<>"&"EMPRESAS_2") -> 72 | H17: =SUMIFS('HORA HORA'!K:K,'HORA HORA'!C:C,PJ_B1!$R$1,'HORA HORA'!B:B,PJ_B1!B17,'HORA HORA'!Y:Y,"<>"&"EMPRESAS_2") -> 45 | I17: =SUMIFS('HORA HORA'!L:L,'HORA HORA'!C:C,PJ_B1!$R$1,'HORA HORA'!B:B,PJ_B1!B17,'HORA HORA'!Y:Y,"<>"&"EMPRESAS_2") -> 10 | J17: =COUNTIFS(ACOMPANHAMENTO!S:S,"ACORDO IMPLANTADO",ACOMPANHAMENTO!BC:BC,B17,ACOMPANHAMENTO!H:H,PJ_B1!$R$1,ACOMPANHAMENTO!I:I,"="&"Business Banking 1") -> 2 | K17: =SUMIFS(ACOMPANHAMENTO!O:O,ACOMPANHAMENTO!H:H,PJ_B1!$R$1,ACOMPANHAMENTO!BC:BC,PJ_B1!B17,ACOMPANHAMENTO!I:I,"="&"Business Banking 1") -> 72000 | L17: =K17/I17 -> 7200 | M17: =SUMIFS(ACOMPANHAMENTO!R:R,ACOMPANHAMENTO!H:H,PJ_B1!$R$1,ACOMPANHAMENTO!BC:BC,PJ_B1!B17,ACOMPANHAMENTO!I:I,"="&"Business Banking 1") -> 41195.64 | N17: =M17/I17 -> 4119.564 | O17: =IFERROR(IF(I17/G17=0,"-",I17/G17),"-") -> 0.13888889 | P17: =SUMIFS('HORA HORA'!$K:$K,'HORA HORA'!$B:$B,PJ_B1!$B17,'HORA HORA'!$C:$C,"="&"PJ",'HORA HORA'!$Y:$Y,"<>"&"EMPRESAS_2")/SUMIFS('HORA HORA'!$J:$J,'HORA HORA'!$B:$B,PJ_B1!$B17,'HORA HORA'!$C:$C,"="&"PJ",'HORA HORA'!$Y:$Y,"<>"&"EMPRESAS_2") -> 0.625 | Q17: =IFERROR(J17/I17,"-") -> 0.2
B18: 46267 | C18: =D18/$A$7 -> 5.9954069 | D18: =SUMIFS(TEMPOS!AL:AL,TEMPOS!X:X,$R$2,TEMPOS!Y:Y,B18) -> 1.632083 | E18: =SUMIFS('HORA HORA'!G:G,'HORA HORA'!C:C,PJ_B1!$R$1,'HORA HORA'!B:B,PJ_B1!B18,'HORA HORA'!Y:Y,"<>"&"EMPRESAS_2") -> 48063 | F18: =SUMIFS('HORA HORA'!H:H,'HORA HORA'!C:C,PJ_B1!$R$1,'HORA HORA'!B:B,PJ_B1!B18,'HORA HORA'!Y:Y,"<>"&"EMPRESAS_2") -> 1206 | G18: =SUMIFS('HORA HORA'!J:J,'HORA HORA'!C:C,PJ_B1!$R$1,'HORA HORA'!B:B,PJ_B1!B18,'HORA HORA'!Y:Y,"<>"&"EMPRESAS_2") -> 42 | H18: =SUMIFS('HORA HORA'!K:K,'HORA HORA'!C:C,PJ_B1!$R$1,'HORA HORA'!B:B,PJ_B1!B18,'HORA HORA'!Y:Y,"<>"&"EMPRESAS_2") -> 27 | I18: =SUMIFS('HORA HORA'!L:L,'HORA HORA'!C:C,PJ_B1!$R$1,'HORA HORA'!B:B,PJ_B1!B18,'HORA HORA'!Y:Y,"<>"&"EMPRESAS_2") -> 6 | J18: =COUNTIFS(ACOMPANHAMENTO!S:S,"ACORDO IMPLANTADO",ACOMPANHAMENTO!BC:BC,B18,ACOMPANHAMENTO!H:H,PJ_B1!$R$1,ACOMPANHAMENTO!I:I,"="&"Business Banking 1") -> 4 | K18: =SUMIFS(ACOMPANHAMENTO!O:O,ACOMPANHAMENTO!H:H,PJ_B1!$R$1,ACOMPANHAMENTO!BC:BC,PJ_B1!B18,ACOMPANHAMENTO!I:I,"="&"Business Banking 1") -> 37078.58 | L18: =IFERROR(K18/I18,0) -> 6179.7633 | M18: =SUMIFS(ACOMPANHAMENTO!R:R,ACOMPANHAMENTO!H:H,PJ_B1!$R$1,ACOMPANHAMENTO!BC:BC,PJ_B1!B18,ACOMPANHAMENTO!I:I,"="&"Business Banking 1") -> 227832.3 | N18: =IFERROR(M18/I18,0) -> 37972.05 | O18: =IFERROR(IF(I18/G18=0,"-",I18/G18),"-") -> 0.14285714 | P18: =IFERROR(SUMIFS('HORA HORA'!$K:$K,'HORA HORA'!$B:$B,PJ_B1!$B18,'HORA HORA'!$C:$C,"="&"PJ",'HORA HORA'!$Y:$Y,"<>"&"EMPRESAS_2")/SUMIFS('HORA HORA'!$J:$J,'HORA HORA'!$B:$B,PJ_B1!$B18,'HORA HORA'!$C:$C,"="&"PJ",'HORA HORA'!$Y:$Y,"<>"&"EMPRESAS_2"),0) -> 0.64285714 | Q18: =IFERROR(J18/I18,"-") -> 0.66666667
B19: 46268 | C19: =D19/$A$7 -> 4.6156922 | D19: =SUMIFS(TEMPOS!AL:AL,TEMPOS!X:X,$R$2,TEMPOS!Y:Y,B19) -> 1.256494 | E19: =SUMIFS('HORA HORA'!G:G,'HORA HORA'!C:C,PJ_B1!$R$1,'HORA HORA'!B:B,PJ_B1!B19,'HORA HORA'!Y:Y,"<>"&"EMPRESAS_2") -> 34619 | F19: =SUMIFS('HORA HORA'!H:H,'HORA HORA'!C:C,PJ_B1!$R$1,'HORA HORA'!B:B,PJ_B1!B19,'HORA HORA'!Y:Y,"<>"&"EMPRESAS_2") -> 687 | G19: =SUMIFS('HORA HORA'!J:J,'HORA HORA'!C:C,PJ_B1!$R$1,'HORA HORA'!B:B,PJ_B1!B19,'HORA HORA'!Y:Y,"<>"&"EMPRESAS_2") -> 49 | H19: =SUMIFS('HORA HORA'!K:K,'HORA HORA'!C:C,PJ_B1!$R$1,'HORA HORA'!B:B,PJ_B1!B19,'HORA HORA'!Y:Y,"<>"&"EMPRESAS_2") -> 28 | I19: =SUMIFS('HORA HORA'!L:L,'HORA HORA'!C:C,PJ_B1!$R$1,'HORA HORA'!B:B,PJ_B1!B19,'HORA HORA'!Y:Y,"<>"&"EMPRESAS_2") -> 12 | J19: =COUNTIFS(ACOMPANHAMENTO!S:S,"ACORDO IMPLANTADO",ACOMPANHAMENTO!BC:BC,B19,ACOMPANHAMENTO!H:H,PJ_B1!$R$1,ACOMPANHAMENTO!I:I,"="&"Business Banking 1") -> 0 | K19: =SUMIFS(ACOMPANHAMENTO!O:O,ACOMPANHAMENTO!H:H,PJ_B1!$R$1,ACOMPANHAMENTO!BC:BC,PJ_B1!B19,ACOMPANHAMENTO!I:I,"="&"Business Banking 1") -> 0 | L19: =IFERROR(K19/I19,0) -> 0 | M19: =SUMIFS(ACOMPANHAMENTO!R:R,ACOMPANHAMENTO!H:H,PJ_B1!$R$1,ACOMPANHAMENTO!BC:BC,PJ_B1!B19,ACOMPANHAMENTO!I:I,"="&"Business Banking 1") -> 0 | N19: =IFERROR(M19/I19,0) -> 0 | O19: =IFERROR(IF(I19/G19=0,"-",I19/G19),"-") -> 0.24489796 | P19: =IFERROR(SUMIFS('HORA HORA'!$K:$K,'HORA HORA'!$B:$B,PJ_B1!$B19,'HORA HORA'!$C:$C,"="&"PJ",'HORA HORA'!$Y:$Y,"<>"&"EMPRESAS_2")/SUMIFS('HORA HORA'!$J:$J,'HORA HORA'!$B:$B,PJ_B1!$B19,'HORA HORA'!$C:$C,"="&"PJ",'HORA HORA'!$Y:$Y,"<>"&"EMPRESAS_2"),0) -> 0.57142857 | Q19: =IFERROR(J19/I19,"-") -> 0
B20: 46269 | C20: =D20/$A$7 -> 3.6886922 | D20: =SUMIFS(TEMPOS!AL:AL,TEMPOS!X:X,$R$2,TEMPOS!Y:Y,B20) -> 1.004144 | E20: =SUMIFS('HORA HORA'!G:G,'HORA HORA'!C:C,PJ_B1!$R$1,'HORA HORA'!B:B,PJ_B1!B20,'HORA HORA'!Y:Y,"<>"&"EMPRESAS_2") -> 32943 | F20: =SUMIFS('HORA HORA'!H:H,'HORA HORA'!C:C,PJ_B1!$R$1,'HORA HORA'!B:B,PJ_B1!B20,'HORA HORA'!Y:Y,"<>"&"EMPRESAS_2") -> 595 | G20: =SUMIFS('HORA HORA'!J:J,'HORA HORA'!C:C,PJ_B1!$R$1,'HORA HORA'!B:B,PJ_B1!B20,'HORA HORA'!Y:Y,"<>"&"EMPRESAS_2") -> 24 | H20: =SUMIFS('HORA HORA'!K:K,'HORA HORA'!C:C,PJ_B1!$R$1,'HORA HORA'!B:B,PJ_B1!B20,'HORA HORA'!Y:Y,"<>"&"EMPRESAS_2") -> 14 | I20: =SUMIFS('HORA HORA'!L:L,'HORA HORA'!C:C,PJ_B1!$R$1,'HORA HORA'!B:B,PJ_B1!B20,'HORA HORA'!Y:Y,"<>"&"EMPRESAS_2") -> 3 | J20: =COUNTIFS(ACOMPANHAMENTO!S:S,"ACORDO IMPLANTADO",ACOMPANHAMENTO!BC:BC,B20,ACOMPANHAMENTO!H:H,PJ_B1!$R$1,ACOMPANHAMENTO!I:I,"="&"Business Banking 1") -> 6 | K20: =SUMIFS(ACOMPANHAMENTO!O:O,ACOMPANHAMENTO!H:H,PJ_B1!$R$1,ACOMPANHAMENTO!BC:BC,PJ_B1!B20,ACOMPANHAMENTO!I:I,"="&"Business Banking 1") -> 82441.3 | L20: =IFERROR(K20/I20,0) -> 27480.433 | M20: =SUMIFS(ACOMPANHAMENTO!R:R,ACOMPANHAMENTO!H:H,PJ_B1!$R$1,ACOMPANHAMENTO!BC:BC,PJ_B1!B20,ACOMPANHAMENTO!I:I,"="&"Business Banking 1") -> 95773.78 | N20: =IFERROR(M20/I20,0) -> 31924.593 | O20: =IFERROR(IF(I20/G20=0,"-",I20/G20),"-") -> 0.125 | P20: =IFERROR(SUMIFS('HORA HORA'!$K:$K,'HORA HORA'!$B:$B,PJ_B1!$B20,'HORA HORA'!$C:$C,"="&"PJ",'HORA HORA'!$Y:$Y,"<>"&"EMPRESAS_2")/SUMIFS('HORA HORA'!$J:$J,'HORA HORA'!$B:$B,PJ_B1!$B20,'HORA HORA'!$C:$C,"="&"PJ",'HORA HORA'!$Y:$Y,"<>"&"EMPRESAS_2"),0) -> 0.58333333 | Q20: =IFERROR(J20/I20,"-") -> 2
B21: 46273 | C21: =D21/$A$7 -> 4.9910731 | D21: =SUMIFS(TEMPOS!AL:AL,TEMPOS!X:X,$R$2,TEMPOS!Y:Y,B21) -> 1.358681 | E21: =SUMIFS('HORA HORA'!G:G,'HORA HORA'!C:C,PJ_B1!$R$1,'HORA HORA'!B:B,PJ_B1!B21,'HORA HORA'!Y:Y,"<>"&"EMPRESAS_2") -> 49897 | F21: =SUMIFS('HORA HORA'!H:H,'HORA HORA'!C:C,PJ_B1!$R$1,'HORA HORA'!B:B,PJ_B1!B21,'HORA HORA'!Y:Y,"<>"&"EMPRESAS_2") -> 913 | G21: =SUMIFS('HORA HORA'!J:J,'HORA HORA'!C:C,PJ_B1!$R$1,'HORA HORA'!B:B,PJ_B1!B21,'HORA HORA'!Y:Y,"<>"&"EMPRESAS_2") -> 53 | H21: =SUMIFS('HORA HORA'!K:K,'HORA HORA'!C:C,PJ_B1!$R$1,'HORA HORA'!B:B,PJ_B1!B21,'HORA HORA'!Y:Y,"<>"&"EMPRESAS_2") -> 28 | I21: =SUMIFS('HORA HORA'!L:L,'HORA HORA'!C:C,PJ_B1!$R$1,'HORA HORA'!B:B,PJ_B1!B21,'HORA HORA'!Y:Y,"<>"&"EMPRESAS_2") -> 5 | J21: =COUNTIFS(ACOMPANHAMENTO!S:S,"ACORDO IMPLANTADO",ACOMPANHAMENTO!BC:BC,B21,ACOMPANHAMENTO!H:H,PJ_B1!$R$1,ACOMPANHAMENTO!I:I,"="&"Business Banking 1") -> 6 | K21: =SUMIFS(ACOMPANHAMENTO!O:O,ACOMPANHAMENTO!H:H,PJ_B1!$R$1,ACOMPANHAMENTO!BC:BC,PJ_B1!B21,ACOMPANHAMENTO!I:I,"="&"Business Banking 1") -> 34385.19 | L21: =IFERROR(K21/I21,0) -> 6877.038 | M21: =SUMIFS(ACOMPANHAMENTO!R:R,ACOMPANHAMENTO!H:H,PJ_B1!$R$1,ACOMPANHAMENTO!BC:BC,PJ_B1!B21,ACOMPANHAMENTO!I:I,"="&"Business Banking 1") -> 662287.64 | N21: =IFERROR(M21/I21,0) -> 132457.53 | O21: =IFERROR(IF(I21/G21=0,"-",I21/G21),"-") -> 0.094339623 | P21: =IFERROR(SUMIFS('HORA HORA'!$K:$K,'HORA HORA'!$B:$B,PJ_B1!$B21,'HORA HORA'!$C:$C,"="&"PJ",'HORA HORA'!$Y:$Y,"<>"&"EMPRESAS_2")/SUMIFS('HORA HORA'!$J:$J,'HORA HORA'!$B:$B,PJ_B1!$B21,'HORA HORA'!$C:$C,"="&"PJ",'HORA HORA'!$Y:$Y,"<>"&"EMPRESAS_2"),0) -> 0.52830189 | Q21: =IFERROR(J21/I21,"-") -> 1.2
B22: 46274 | C22: =D22/$A$7 -> 4.9892878 | D22: =SUMIFS(TEMPOS!AL:AL,TEMPOS!X:X,$R$2,TEMPOS!Y:Y,B22) -> 1.358195 | E22: =SUMIFS('HORA HORA'!G:G,'HORA HORA'!C:C,PJ_B1!$R$1,'HORA HORA'!B:B,PJ_B1!B22,'HORA HORA'!Y:Y,"<>"&"EMPRESAS_2") -> 78395 | F22: =SUMIFS('HORA HORA'!H:H,'HORA HORA'!C:C,PJ_B1!$R$1,'HORA HORA'!B:B,PJ_B1!B22,'HORA HORA'!Y:Y,"<>"&"EMPRESAS_2") -> 1486 | G22: =SUMIFS('HORA HORA'!J:J,'HORA HORA'!C:C,PJ_B1!$R$1,'HORA HORA'!B:B,PJ_B1!B22,'HORA HORA'!Y:Y,"<>"&"EMPRESAS_2") -> 59 | H22: =SUMIFS('HORA HORA'!K:K,'HORA HORA'!C:C,PJ_B1!$R$1,'HORA HORA'!B:B,PJ_B1!B22,'HORA HORA'!Y:Y,"<>"&"EMPRESAS_2") -> 28 | I22: =SUMIFS('HORA HORA'!L:L,'HORA HORA'!C:C,PJ_B1!$R$1,'HORA HORA'!B:B,PJ_B1!B22,'HORA HORA'!Y:Y,"<>"&"EMPRESAS_2") -> 10 | J22: =COUNTIFS(ACOMPANHAMENTO!S:S,"ACORDO IMPLANTADO",ACOMPANHAMENTO!BC:BC,B22,ACOMPANHAMENTO!H:H,PJ_B1!$R$1,ACOMPANHAMENTO!I:I,"="&"Business Banking 1") -> 5 | K22: =SUMIFS(ACOMPANHAMENTO!O:O,ACOMPANHAMENTO!H:H,PJ_B1!$R$1,ACOMPANHAMENTO!BC:BC,PJ_B1!B22,ACOMPANHAMENTO!I:I,"="&"Business Banking 1") -> 221827.5 | L22: =IFERROR(K22/I22,0) -> 22182.75 | M22: =SUMIFS(ACOMPANHAMENTO!R:R,ACOMPANHAMENTO!H:H,PJ_B1!$R$1,ACOMPANHAMENTO!BC:BC,PJ_B1!B22,ACOMPANHAMENTO!I:I,"="&"Business Banking 1") -> 304928.99 | N22: =IFERROR(M22/I22,0) -> 30492.899 | O22: =IFERROR(IF(I22/G22=0,"-",I22/G22),"-") -> 0.16949153 | P22: =IFERROR(SUMIFS('HORA HORA'!$K:$K,'HORA HORA'!$B:$B,PJ_B1!$B22,'HORA HORA'!$C:$C,"="&"PJ",'HORA HORA'!$Y:$Y,"<>"&"EMPRESAS_2")/SUMIFS('HORA HORA'!$J:$J,'HORA HORA'!$B:$B,PJ_B1!$B22,'HORA HORA'!$C:$C,"="&"PJ",'HORA HORA'!$Y:$Y,"<>"&"EMPRESAS_2"),0) -> 0.47457627 | Q22: =IFERROR(J22/I22,"-") -> 0.5
B23: 46275 | C23: =D23/$A$7 -> 5.8236024 | D23: =SUMIFS(TEMPOS!AL:AL,TEMPOS!X:X,$R$2,TEMPOS!Y:Y,B23) -> 1.585314 | E23: =SUMIFS('HORA HORA'!G:G,'HORA HORA'!C:C,PJ_B1!$R$1,'HORA HORA'!B:B,PJ_B1!B23,'HORA HORA'!Y:Y,"<>"&"EMPRESAS_2") -> 94812 | F23: =SUMIFS('HORA HORA'!H:H,'HORA HORA'!C:C,PJ_B1!$R$1,'HORA HORA'!B:B,PJ_B1!B23,'HORA HORA'!Y:Y,"<>"&"EMPRESAS_2") -> 1171 | G23: =SUMIFS('HORA HORA'!J:J,'HORA HORA'!C:C,PJ_B1!$R$1,'HORA HORA'!B:B,PJ_B1!B23,'HORA HORA'!Y:Y,"<>"&"EMPRESAS_2") -> 60 | H23: =SUMIFS('HORA HORA'!K:K,'HORA HORA'!C:C,PJ_B1!$R$1,'HORA HORA'!B:B,PJ_B1!B23,'HORA HORA'!Y:Y,"<>"&"EMPRESAS_2") -> 40 | I23: =SUMIFS('HORA HORA'!L:L,'HORA HORA'!C:C,PJ_B1!$R$1,'HORA HORA'!B:B,PJ_B1!B23,'HORA HORA'!Y:Y,"<>"&"EMPRESAS_2") -> 7 | J23: =COUNTIFS(ACOMPANHAMENTO!S:S,"ACORDO IMPLANTADO",ACOMPANHAMENTO!BC:BC,B23,ACOMPANHAMENTO!H:H,PJ_B1!$R$1,ACOMPANHAMENTO!I:I,"="&"Business Banking 1") -> 5 | K23: =SUMIFS(ACOMPANHAMENTO!O:O,ACOMPANHAMENTO!H:H,PJ_B1!$R$1,ACOMPANHAMENTO!BC:BC,PJ_B1!B23,ACOMPANHAMENTO!I:I,"="&"Business Banking 1") -> 34020.92 | L23: =IFERROR(K23/I23,0) -> 4860.1314 | M23: =SUMIFS(ACOMPANHAMENTO!R:R,ACOMPANHAMENTO!H:H,PJ_B1!$R$1,ACOMPANHAMENTO!BC:BC,PJ_B1!B23,ACOMPANHAMENTO!I:I,"="&"Business Banking 1") -> 397651 | N23: =IFERROR(M23/I23,0) -> 56807.286 | O23: =IFERROR(IF(I23/G23=0,"-",I23/G23),"-") -> 0.11666667 | P23: =IFERROR(SUMIFS('HORA HORA'!$K:$K,'HORA HORA'!$B:$B,PJ_B1!$B23,'HORA HORA'!$C:$C,"="&"PJ",'HORA HORA'!$Y:$Y,"<>"&"EMPRESAS_2")/SUMIFS('HORA HORA'!$J:$J,'HORA HORA'!$B:$B,PJ_B1!$B23,'HORA HORA'!$C:$C,"="&"PJ",'HORA HORA'!$Y:$Y,"<>"&"EMPRESAS_2"),0) -> 0.66666667 | Q23: =IFERROR(J23/I23,"-") -> 0.71428571
B24: 46276 | C24: =D24/$A$7 -> 0 | D24: =SUMIFS(TEMPOS!AL:AL,TEMPOS!X:X,$R$2,TEMPOS!Y:Y,B24) -> 0 | E24: =SUMIFS('HORA HORA'!G:G,'HORA HORA'!C:C,PJ_B1!$R$1,'HORA HORA'!B:B,PJ_B1!B24,'HORA HORA'!Y:Y,"<>"&"EMPRESAS_2") -> 106972 | F24: =SUMIFS('HORA HORA'!H:H,'HORA HORA'!C:C,PJ_B1!$R$1,'HORA HORA'!B:B,PJ_B1!B24,'HORA HORA'!Y:Y,"<>"&"EMPRESAS_2") -> 1284 | G24: =SUMIFS('HORA HORA'!J:J,'HORA HORA'!C:C,PJ_B1!$R$1,'HORA HORA'!B:B,PJ_B1!B24,'HORA HORA'!Y:Y,"<>"&"EMPRESAS_2") -> 55 | H24: =SUMIFS('HORA HORA'!K:K,'HORA HORA'!C:C,PJ_B1!$R$1,'HORA HORA'!B:B,PJ_B1!B24,'HORA HORA'!Y:Y,"<>"&"EMPRESAS_2") -> 35 | I24: =SUMIFS('HORA HORA'!L:L,'HORA HORA'!C:C,PJ_B1!$R$1,'HORA HORA'!B:B,PJ_B1!B24,'HORA HORA'!Y:Y,"<>"&"EMPRESAS_2") -> 8 | J24: =COUNTIFS(ACOMPANHAMENTO!S:S,"ACORDO IMPLANTADO",ACOMPANHAMENTO!BC:BC,B24,ACOMPANHAMENTO!H:H,PJ_B1!$R$1,ACOMPANHAMENTO!I:I,"="&"Business Banking 1") -> 3 | K24: =SUMIFS(ACOMPANHAMENTO!O:O,ACOMPANHAMENTO!H:H,PJ_B1!$R$1,ACOMPANHAMENTO!BC:BC,PJ_B1!B24,ACOMPANHAMENTO!I:I,"="&"Business Banking 1") -> 84000 | L24: =IFERROR(K24/I24,0) -> 10500 | M24: =SUMIFS(ACOMPANHAMENTO!R:R,ACOMPANHAMENTO!H:H,PJ_B1!$R$1,ACOMPANHAMENTO!BC:BC,PJ_B1!B24,ACOMPANHAMENTO!I:I,"="&"Business Banking 1") -> 42695.21 | N24: =IFERROR(M24/I24,0) -> 5336.9012 | O24: =IFERROR(IF(I24/G24=0,"-",I24/G24),"-") -> 0.14545455 | P24: =IFERROR(SUMIFS('HORA HORA'!$K:$K,'HORA HORA'!$B:$B,PJ_B1!$B24,'HORA HORA'!$C:$C,"="&"PJ",'HORA HORA'!$Y:$Y,"<>"&"EMPRESAS_2")/SUMIFS('HORA HORA'!$J:$J,'HORA HORA'!$B:$B,PJ_B1!$B24,'HORA HORA'!$C:$C,"="&"PJ",'HORA HORA'!$Y:$Y,"<>"&"EMPRESAS_2"),0) -> 0.63636364 | Q24: =IFERROR(J24/I24,"-") -> 0.375
B25: 46279 | C25: =D25/$A$7 -> 0 | D25: =SUMIFS(TEMPOS!AL:AL,TEMPOS!X:X,$R$2,TEMPOS!Y:Y,B25) -> 0 | E25: =SUMIFS('HORA HORA'!G:G,'HORA HORA'!C:C,PJ_B1!$R$1,'HORA HORA'!B:B,PJ_B1!B25,'HORA HORA'!Y:Y,"<>"&"EMPRESAS_2") -> 0 | F25: =SUMIFS('HORA HORA'!H:H,'HORA HORA'!C:C,PJ_B1!$R$1,'HORA HORA'!B:B,PJ_B1!B25,'HORA HORA'!Y:Y,"<>"&"EMPRESAS_2") -> 0 | G25: =SUMIFS('HORA HORA'!J:J,'HORA HORA'!C:C,PJ_B1!$R$1,'HORA HORA'!B:B,PJ_B1!B25,'HORA HORA'!Y:Y,"<>"&"EMPRESAS_2") -> 0 | H25: =SUMIFS('HORA HORA'!K:K,'HORA HORA'!C:C,PJ_B1!$R$1,'HORA HORA'!B:B,PJ_B1!B25,'HORA HORA'!Y:Y,"<>"&"EMPRESAS_2") -> 0 | I25: =SUMIFS('HORA HORA'!L:L,'HORA HORA'!C:C,PJ_B1!$R$1,'HORA HORA'!B:B,PJ_B1!B25,'HORA HORA'!Y:Y,"<>"&"EMPRESAS_2") -> 0 | J25: =COUNTIFS(ACOMPANHAMENTO!S:S,"ACORDO IMPLANTADO",ACOMPANHAMENTO!BC:BC,B25,ACOMPANHAMENTO!H:H,PJ_B1!$R$1,ACOMPANHAMENTO!I:I,"="&"Business Banking 1") -> 0 | K25: =SUMIFS(ACOMPANHAMENTO!O:O,ACOMPANHAMENTO!H:H,PJ_B1!$R$1,ACOMPANHAMENTO!BC:BC,PJ_B1!B25,ACOMPANHAMENTO!I:I,"="&"Business Banking 1") -> 0 | L25: =IFERROR(K25/I25,0) -> 0 | M25: =SUMIFS(ACOMPANHAMENTO!R:R,ACOMPANHAMENTO!H:H,PJ_B1!$R$1,ACOMPANHAMENTO!BC:BC,PJ_B1!B25,ACOMPANHAMENTO!I:I,"="&"Business Banking 1") -> 0 | N25: =IFERROR(M25/I25,0) -> 0 | O25: =IFERROR(IF(I25/G25=0,"-",I25/G25),"-") -> - | P25: =IFERROR(SUMIFS('HORA HORA'!$K:$K,'HORA HORA'!$B:$B,PJ_B1!$B25,'HORA HORA'!$C:$C,"="&"PJ",'HORA HORA'!$Y:$Y,"<>"&"EMPRESAS_2")/SUMIFS('HORA HORA'!$J:$J,'HORA HORA'!$B:$B,PJ_B1!$B25,'HORA HORA'!$C:$C,"="&"PJ",'HORA HORA'!$Y:$Y,"<>"&"EMPRESAS_2"),0) -> 0 | Q25: =IFERROR(J25/I25,"-") -> -
B26: 46280 | C26: =D26/$A$7 -> 0 | D26: =SUMIFS(TEMPOS!AL:AL,TEMPOS!X:X,$R$2,TEMPOS!Y:Y,B26) -> 0 | E26: =SUMIFS('HORA HORA'!G:G,'HORA HORA'!C:C,PJ_B1!$R$1,'HORA HORA'!B:B,PJ_B1!B26,'HORA HORA'!Y:Y,"<>"&"EMPRESAS_2") -> 0 | F26: =SUMIFS('HORA HORA'!H:H,'HORA HORA'!C:C,PJ_B1!$R$1,'HORA HORA'!B:B,PJ_B1!B26,'HORA HORA'!Y:Y,"<>"&"EMPRESAS_2") -> 0 | G26: =SUMIFS('HORA HORA'!J:J,'HORA HORA'!C:C,PJ_B1!$R$1,'HORA HORA'!B:B,PJ_B1!B26,'HORA HORA'!Y:Y,"<>"&"EMPRESAS_2") -> 0 | H26: =SUMIFS('HORA HORA'!K:K,'HORA HORA'!C:C,PJ_B1!$R$1,'HORA HORA'!B:B,PJ_B1!B26,'HORA HORA'!Y:Y,"<>"&"EMPRESAS_2") -> 0 | I26: =SUMIFS('HORA HORA'!L:L,'HORA HORA'!C:C,PJ_B1!$R$1,'HORA HORA'!B:B,PJ_B1!B26,'HORA HORA'!Y:Y,"<>"&"EMPRESAS_2") -> 0 | J26: =COUNTIFS(ACOMPANHAMENTO!S:S,"ACORDO IMPLANTADO",ACOMPANHAMENTO!BC:BC,B26,ACOMPANHAMENTO!H:H,PJ_B1!$R$1,ACOMPANHAMENTO!I:I,"="&"Business Banking 1") -> 0 | K26: =SUMIFS(ACOMPANHAMENTO!O:O,ACOMPANHAMENTO!H:H,PJ_B1!$R$1,ACOMPANHAMENTO!BC:BC,PJ_B1!B26,ACOMPANHAMENTO!I:I,"="&"Business Banking 1") -> 0 | L26: =IFERROR(K26/I26,0) -> 0 | M26: =SUMIFS(ACOMPANHAMENTO!R:R,ACOMPANHAMENTO!H:H,PJ_B1!$R$1,ACOMPANHAMENTO!BC:BC,PJ_B1!B26,ACOMPANHAMENTO!I:I,"="&"Business Banking 1") -> 0 | N26: =IFERROR(M26/I26,0) -> 0 | O26: =IFERROR(IF(I26/G26=0,"-",I26/G26),"-") -> - | P26: =IFERROR(SUMIFS('HORA HORA'!$K:$K,'HORA HORA'!$B:$B,PJ_B1!$B26,'HORA HORA'!$C:$C,"="&"PJ",'HORA HORA'!$Y:$Y,"<>"&"EMPRESAS_2")/SUMIFS('HORA HORA'!$J:$J,'HORA HORA'!$B:$B,PJ_B1!$B26,'HORA HORA'!$C:$C,"="&"PJ",'HORA HORA'!$Y:$Y,"<>"&"EMPRESAS_2"),0) -> 0 | Q26: =IFERROR(J26/I26,"-") -> -
B27: 46281 | C27: =D27/$A$7 -> 0 | D27: =SUMIFS(TEMPOS!AL:AL,TEMPOS!X:X,$R$2,TEMPOS!Y:Y,B27) -> 0 | E27: =SUMIFS('HORA HORA'!G:G,'HORA HORA'!C:C,PJ_B1!$R$1,'HORA HORA'!B:B,PJ_B1!B27,'HORA HORA'!Y:Y,"<>"&"EMPRESAS_2") -> 0 | F27: =SUMIFS('HORA HORA'!H:H,'HORA HORA'!C:C,PJ_B1!$R$1,'HORA HORA'!B:B,PJ_B1!B27,'HORA HORA'!Y:Y,"<>"&"EMPRESAS_2") -> 0 | G27: =SUMIFS('HORA HORA'!J:J,'HORA HORA'!C:C,PJ_B1!$R$1,'HORA HORA'!B:B,PJ_B1!B27,'HORA HORA'!Y:Y,"<>"&"EMPRESAS_2") -> 0 | H27: =SUMIFS('HORA HORA'!K:K,'HORA HORA'!C:C,PJ_B1!$R$1,'HORA HORA'!B:B,PJ_B1!B27,'HORA HORA'!Y:Y,"<>"&"EMPRESAS_2") -> 0 | I27: =SUMIFS('HORA HORA'!L:L,'HORA HORA'!C:C,PJ_B1!$R$1,'HORA HORA'!B:B,PJ_B1!B27,'HORA HORA'!Y:Y,"<>"&"EMPRESAS_2") -> 0 | J27: =COUNTIFS(ACOMPANHAMENTO!S:S,"ACORDO IMPLANTADO",ACOMPANHAMENTO!BC:BC,B27,ACOMPANHAMENTO!H:H,PJ_B1!$R$1,ACOMPANHAMENTO!I:I,"="&"Business Banking 1") -> 0 | K27: =SUMIFS(ACOMPANHAMENTO!O:O,ACOMPANHAMENTO!H:H,PJ_B1!$R$1,ACOMPANHAMENTO!BC:BC,PJ_B1!B27,ACOMPANHAMENTO!I:I,"="&"Business Banking 1") -> 0 | L27: =IFERROR(K27/I27,0) -> 0 | M27: =SUMIFS(ACOMPANHAMENTO!R:R,ACOMPANHAMENTO!H:H,PJ_B1!$R$1,ACOMPANHAMENTO!BC:BC,PJ_B1!B27,ACOMPANHAMENTO!I:I,"="&"Business Banking 1") -> 0 | N27: =IFERROR(M27/I27,0) -> 0 | O27: =IFERROR(IF(I27/G27=0,"-",I27/G27),"-") -> - | P27: =IFERROR(SUMIFS('HORA HORA'!$K:$K,'HORA HORA'!$B:$B,PJ_B1!$B27,'HORA HORA'!$C:$C,"="&"PJ",'HORA HORA'!$Y:$Y,"<>"&"EMPRESAS_2")/SUMIFS('HORA HORA'!$J:$J,'HORA HORA'!$B:$B,PJ_B1!$B27,'HORA HORA'!$C:$C,"="&"PJ",'HORA HORA'!$Y:$Y,"<>"&"EMPRESAS_2"),0) -> 0 | Q27: =IFERROR(J27/I27,"-") -> -
B28: 46282 | C28: =D28/$A$7 -> 0 | D28: =SUMIFS(TEMPOS!AL:AL,TEMPOS!X:X,$R$2,TEMPOS!Y:Y,B28) -> 0 | E28: =SUMIFS('HORA HORA'!G:G,'HORA HORA'!C:C,PJ_B1!$R$1,'HORA HORA'!B:B,PJ_B1!B28,'HORA HORA'!Y:Y,"<>"&"EMPRESAS_2") -> 0 | F28: =SUMIFS('HORA HORA'!H:H,'HORA HORA'!C:C,PJ_B1!$R$1,'HORA HORA'!B:B,PJ_B1!B28,'HORA HORA'!Y:Y,"<>"&"EMPRESAS_2") -> 0 | G28: =SUMIFS('HORA HORA'!J:J,'HORA HORA'!C:C,PJ_B1!$R$1,'HORA HORA'!B:B,PJ_B1!B28,'HORA HORA'!Y:Y,"<>"&"EMPRESAS_2") -> 0 | H28: =SUMIFS('HORA HORA'!K:K,'HORA HORA'!C:C,PJ_B1!$R$1,'HORA HORA'!B:B,PJ_B1!B28,'HORA HORA'!Y:Y,"<>"&"EMPRESAS_2") -> 0 | I28: =SUMIFS('HORA HORA'!L:L,'HORA HORA'!C:C,PJ_B1!$R$1,'HORA HORA'!B:B,PJ_B1!B28,'HORA HORA'!Y:Y,"<>"&"EMPRESAS_2") -> 0 | J28: =COUNTIFS(ACOMPANHAMENTO!S:S,"ACORDO IMPLANTADO",ACOMPANHAMENTO!BC:BC,B28,ACOMPANHAMENTO!H:H,PJ_B1!$R$1,ACOMPANHAMENTO!I:I,"="&"Business Banking 1") -> 0 | K28: =SUMIFS(ACOMPANHAMENTO!O:O,ACOMPANHAMENTO!H:H,PJ_B1!$R$1,ACOMPANHAMENTO!BC:BC,PJ_B1!B28,ACOMPANHAMENTO!I:I,"="&"Business Banking 1") -> 0 | L28: =IFERROR(K28/I28,0) -> 0 | M28: =SUMIFS(ACOMPANHAMENTO!R:R,ACOMPANHAMENTO!H:H,PJ_B1!$R$1,ACOMPANHAMENTO!BC:BC,PJ_B1!B28,ACOMPANHAMENTO!I:I,"="&"Business Banking 1") -> 0 | N28: =IFERROR(M28/I28,0) -> 0 | O28: =IFERROR(IF(I28/G28=0,"-",I28/G28),"-") -> - | P28: =IFERROR(SUMIFS('HORA HORA'!$K:$K,'HORA HORA'!$B:$B,PJ_B1!$B28,'HORA HORA'!$C:$C,"="&"PJ",'HORA HORA'!$Y:$Y,"<>"&"EMPRESAS_2")/SUMIFS('HORA HORA'!$J:$J,'HORA HORA'!$B:$B,PJ_B1!$B28,'HORA HORA'!$C:$C,"="&"PJ",'HORA HORA'!$Y:$Y,"<>"&"EMPRESAS_2"),0) -> 0 | Q28: =IFERROR(J28/I28,"-") -> -
B29: 46283 | C29: =D29/$A$7 -> 0 | D29: =SUMIFS(TEMPOS!AL:AL,TEMPOS!X:X,$R$2,TEMPOS!Y:Y,B29) -> 0 | E29: =SUMIFS('HORA HORA'!G:G,'HORA HORA'!C:C,PJ_B1!$R$1,'HORA HORA'!B:B,PJ_B1!B29,'HORA HORA'!Y:Y,"<>"&"EMPRESAS_2") -> 0 | F29: =SUMIFS('HORA HORA'!H:H,'HORA HORA'!C:C,PJ_B1!$R$1,'HORA HORA'!B:B,PJ_B1!B29,'HORA HORA'!Y:Y,"<>"&"EMPRESAS_2") -> 0 | G29: =SUMIFS('HORA HORA'!J:J,'HORA HORA'!C:C,PJ_B1!$R$1,'HORA HORA'!B:B,PJ_B1!B29,'HORA HORA'!Y:Y,"<>"&"EMPRESAS_2") -> 0 | H29: =SUMIFS('HORA HORA'!K:K,'HORA HORA'!C:C,PJ_B1!$R$1,'HORA HORA'!B:B,PJ_B1!B29,'HORA HORA'!Y:Y,"<>"&"EMPRESAS_2") -> 0 | I29: =SUMIFS('HORA HORA'!L:L,'HORA HORA'!C:C,PJ_B1!$R$1,'HORA HORA'!B:B,PJ_B1!B29,'HORA HORA'!Y:Y,"<>"&"EMPRESAS_2") -> 0 | J29: =COUNTIFS(ACOMPANHAMENTO!S:S,"ACORDO IMPLANTADO",ACOMPANHAMENTO!BC:BC,B29,ACOMPANHAMENTO!H:H,PJ_B1!$R$1,ACOMPANHAMENTO!I:I,"="&"Business Banking 1") -> 0 | K29: =SUMIFS(ACOMPANHAMENTO!O:O,ACOMPANHAMENTO!H:H,PJ_B1!$R$1,ACOMPANHAMENTO!BC:BC,PJ_B1!B29,ACOMPANHAMENTO!I:I,"="&"Business Banking 1") -> 0 | L29: =IFERROR(K29/I29,0) -> 0 | M29: =SUMIFS(ACOMPANHAMENTO!R:R,ACOMPANHAMENTO!H:H,PJ_B1!$R$1,ACOMPANHAMENTO!BC:BC,PJ_B1!B29,ACOMPANHAMENTO!I:I,"="&"Business Banking 1") -> 0 | N29: =IFERROR(M29/I29,0) -> 0 | O29: =IFERROR(IF(I29/G29=0,"-",I29/G29),"-") -> - | P29: =IFERROR(SUMIFS('HORA HORA'!$K:$K,'HORA HORA'!$B:$B,PJ_B1!$B29,'HORA HORA'!$C:$C,"="&"PJ",'HORA HORA'!$Y:$Y,"<>"&"EMPRESAS_2")/SUMIFS('HORA HORA'!$J:$J,'HORA HORA'!$B:$B,PJ_B1!$B29,'HORA HORA'!$C:$C,"="&"PJ",'HORA HORA'!$Y:$Y,"<>"&"EMPRESAS_2"),0) -> 0 | Q29: =IFERROR(J29/I29,"-") -> -
... B37: 46295 | C37: =D37/$A$7 -> 0 | D37: =SUMIFS(TEMPOS!AL:AL,TEMPOS!X:X,$R$2,TEMPOS!Y:Y,B37) -> 0 | E37: =SUMIFS('HORA HORA'!G:G,'HORA HORA'!C:C,PJ_B1!$R$1,'HORA HORA'!B:B,PJ_B1!B37,'HORA HORA'!Y:Y,"<>"&"EMPRESAS_2") -> 0 | F37: =SUMIFS('HORA HORA'!H:H,'HORA HORA'!C:C,PJ_B1!$R$1,'HORA HORA'!B:B,PJ_B1!B37,'HORA HORA'!Y:Y,"<>"&"EMPRESAS_2") -> 0 | G37: =SUMIFS('HORA HORA'!J:J,'HORA HORA'!C:C,PJ_B1!$R$1,'HORA HORA'!B:B,PJ_B1!B37,'HORA HORA'!Y:Y,"<>"&"EMPRESAS_2") -> 0 | H37: =SUMIFS('HORA HORA'!K:K,'HORA HORA'!C:C,PJ_B1!$R$1,'HORA HORA'!B:B,PJ_B1!B37,'HORA HORA'!Y:Y,"<>"&"EMPRESAS_2") -> 0 | I37: =SUMIFS('HORA HORA'!L:L,'HORA HORA'!C:C,PJ_B1!$R$1,'HORA HORA'!B:B,PJ_B1!B37,'HORA HORA'!Y:Y,"<>"&"EMPRESAS_2") -> 0 | J37: =COUNTIFS(ACOMPANHAMENTO!S:S,"ACORDO IMPLANTADO",ACOMPANHAMENTO!BC:BC,B37,ACOMPANHAMENTO!H:H,PJ_B1!$R$1,ACOMPANHAMENTO!I:I,"="&"Business Banking 1") -> 0 | K37: =SUMIFS(ACOMPANHAMENTO!O:O,ACOMPANHAMENTO!H:H,PJ_B1!$R$1,ACOMPANHAMENTO!BC:BC,PJ_B1!B37,ACOMPANHAMENTO!I:I,"="&"Business Banking 1") -> 0 | L37: =IFERROR(K37/I37,0) -> 0 | M37: =SUMIFS(ACOMPANHAMENTO!R:R,ACOMPANHAMENTO!H:H,PJ_B1!$R$1,ACOMPANHAMENTO!BC:BC,PJ_B1!B37,ACOMPANHAMENTO!I:I,"="&"Business Banking 1") -> 0 | N37: =IFERROR(M37/I37,0) -> 0 | O37: =IFERROR(IF(I37/G37=0,"-",I37/G37),"-") -> - | P37: =IFERROR(SUMIFS('HORA HORA'!$K:$K,'HORA HORA'!$B:$B,PJ_B1!$B37,'HORA HORA'!$C:$C,"="&"PJ",'HORA HORA'!$Y:$Y,"<>"&"EMPRESAS_2")/SUMIFS('HORA HORA'!$J:$J,'HORA HORA'!$B:$B,PJ_B1!$B37,'HORA HORA'!$C:$C,"="&"PJ",'HORA HORA'!$Y:$Y,"<>"&"EMPRESAS_2"),0) -> 0 | Q37: =IFERROR(J37/I37,"-") -> -

Sheet PJ_B2
A1: X' | R1: PJ
I2: Business Banking 2 | R2: B2
B6: DIA | C6: CAPACITY | D6: TEMPO DISP | E6: DISCAGEM | F6: ATENDIDA | G6: CPC | H6: CPCA | I6: PROPOSTA | J6: PAGAMENTO | K6: ($) CASH | L6: ($) TKT CASH | M6: ($) CONTABIL | N6: ($) TKT CONTABIL | O6: (%) CONVERSÃO | P6: =AUX!B11 -> (%) CPC | Q6: (%) EFETIVIDADE
A7: 0.27222222 | C7: =AVERAGE(C9) -> 3 | D7: =A7*4 -> 1.0888889 | E7: 4528 | F7: 106 | G7: 5 | H7: 4 | I7: 2 | J7: 1 | K7: =AUX!C31 -> 52471.543 | L7: =AUX!C32 -> 26235.771 | M7: =AUX!C33 -> 1282413.6 | N7: =AUX!C34 -> 320603.39 | O7: =AUX!C35 -> 0.43 | P7: =AUX!C36 -> 0.58 | Q7: =AUX!C37 -> 0.46
A9: 8 | B9: META GERAL | C9: 3 | D9: =D7*A9 -> 8.7111111 | E9: =E7*A9 -> 36224 | F9: =F7*A9 -> 848 | G9: =G7*A9 -> 40 | H9: =H7*A9 -> 32 | I9: =I7*A9 -> 16 | J9: =J7*A9 -> 8 | K9: 1245000 | L9: =L7 -> 26235.771 | M9: 10200000 | N9: =N7 -> 320603.39 | O9: =O7 -> 0.43 | P9: =P7 -> 0.58 | Q9: =Q7 -> 0.46
B10: REALIZADO | C10: =AVERAGE(C17:C24) -> 1.0909823 | D10: =SUM(D17:D37) -> 2.375917 | E10: =SUM(E17:E34) -> 57210 | F10: =SUM(F17:F37) -> 1229 | G10: =SUM(G17:G37) -> 105 | H10: =SUM(H17:H34) -> 89 | I10: =SUM(I17:I37) -> 30 | J10: =SUM(J17:J37) -> 6 | K10: =SUM(K17:K37) -> 182711.71 | L10: =IFERROR(K10/J10,0) -> 30451.952 | M10: =SUM(M17:M37) -> 760855.69 | N10: =IFERROR(M10/J10,0) -> 126809.28 | O10: =AVERAGE(O17:O36) -> 0.27411183 | P10: =IFERROR(AVERAGE(P17:P24),0) -> 0.82964223 | Q10: =AVERAGE(Q17:Q37) -> 0.21994048
B11: META RELOGIO | C11: - | D11: =D7*(COUNTIFS(D17:D34,">="&0)) -> 19.6 | E11: =E7*(COUNTIFS(E17:E33,">="&1)) -> 36224 | F11: =F7*(COUNTIFS(F17:F33,">="&1)) -> 848 | G11: =G7*(COUNTIFS(G16:G30,">="&1)) -> 40 | H11: =H7*(COUNTIFS(H17:H34,">="&1)) -> 32 | I11: =I7*(COUNTIFS(I17:I34,">="&1)) -> 16 | J11: =J7*(COUNTIFS(J16:J33,">="&1)) -> 5 | K11: =K7*(COUNTIFS(K16:K34,">="&1)) -> 262357.71 | L11: =L9 -> 26235.771 | M11: =M7*(COUNTIFS(M16:M34,">="&1)) -> 6412067.8 | N11: =N9 -> 320603.39 | O11: =O9 -> 0.43 | P11: =P9 -> 0.58 | Q11: =Q9 -> 0.46
B13: (%) META REALIZADO | C13: =C10/C9 -> 0.36366077 | E13: =E10/E9 -> 1.5793397 | F13: =F10/F9 -> 1.4492925 | G13: =G10/G9 -> 2.625 | H13: =H10/H9 -> 2.78125 | I13: =I10/I9 -> 1.875 | J13: =J10/J9 -> 0.75 | K13: =K10/K9 -> 0.14675639 | L13: =L10/L9 -> 1.1607035 | ... Q13: =Q10/Q9 -> 0.47813147
B14: (%) META RELOGIO | C14: - | E14: =E10/E11 -> 1.5793397 | F14: =F10/F11 -> 1.4492925 | G14: =G10/G11 -> 2.625 | H14: =H10/H11 -> 2.78125 | I14: =I10/I11 -> 1.875 | J14: =IFERROR(J10/J11,0) -> 1.2 | K14: =IFERROR(K10/K11,0) -> 0.6964221 | L14: =L10/L11 -> 1.1607035 | M14: =IFERROR(M10/M11,0) -> 0.11865996 | N14: =N10/N11 -> 0.39553319 | O14: =O10/O11 -> 0.63746936 | P14: =P10/P11 -> 1.4304176 | Q14: =Q10/Q11 -> 0.47813147
B16: DATA | C16: REALIZADO | D16: TEMPO REALIZADO | E16: DISCAGEM | F16: ATENDIDA | G16: CPC | H16: CPCA | I16: PROPOSTA | J16: PAGAMENTO | K16: ($) CASH | L16: ($) TKT CASH | M16: ($) CONTABIL | N16: ($) TKT CONTABIL | O16: (%) CONVERSÃO | P16: (%) CPC | Q16: (%) EFETIVIDADE
B17: 46266 | C17: =D17/$A$7 -> 0.64153469 | D17: =SUMIFS(TEMPOS!AL:AL,TEMPOS!X:X,$R$2,TEMPOS!Y:Y,B17) -> 0.17464 | E17: =SUMIFS('HORA HORA'!G:G,'HORA HORA'!C:C,PJ_B2!$R$1,'HORA HORA'!B:B,PJ_B2!B17,'HORA HORA'!Y:Y,"="&"EMPRESAS_2") -> 5059 | F17: =SUMIFS('HORA HORA'!H:H,'HORA HORA'!C:C,PJ_B2!$R$1,'HORA HORA'!B:B,PJ_B2!B17,'HORA HORA'!Y:Y,"="&"EMPRESAS_2") -> 136 | G17: =SUMIFS('HORA HORA'!J:J,'HORA HORA'!C:C,PJ_B2!$R$1,'HORA HORA'!B:B,PJ_B2!B17,'HORA HORA'!Y:Y,"="&"EMPRESAS_2") -> 16 | H17: =SUMIFS('HORA HORA'!K:K,'HORA HORA'!C:C,PJ_B2!$R$1,'HORA HORA'!B:B,PJ_B2!B17,'HORA HORA'!Y:Y,"="&"EMPRESAS_2") -> 16 | I17: =SUMIFS('HORA HORA'!L:L,'HORA HORA'!C:C,PJ_B2!$R$1,'HORA HORA'!B:B,PJ_B2!B17,'HORA HORA'!Y:Y,"="&"EMPRESAS_2") -> 5 | J17: =COUNTIFS(ACOMPANHAMENTO!S:S,"ACORDO IMPLANTADO",ACOMPANHAMENTO!BC:BC,B17,ACOMPANHAMENTO!H:H,PJ_B2!$R$1,ACOMPANHAMENTO!I:I,"="&"Business Banking 2") -> 1 | K17: =SUMIFS(ACOMPANHAMENTO!O:O,ACOMPANHAMENTO!H:H,PJ_B1!$R$1,ACOMPANHAMENTO!BC:BC,PJ_B1!B17,ACOMPANHAMENTO!I:I,"="&"Business Banking 2") -> 57697.26 | L17: =K17/I17 -> 11539.452 | M17: =SUMIFS(ACOMPANHAMENTO!R:R,ACOMPANHAMENTO!H:H,PJ_B1!$R$1,ACOMPANHAMENTO!BC:BC,PJ_B2!B17,ACOMPANHAMENTO!I:I,"="&"Business Banking 2") -> 354701.99 | N17: =M17/I17 -> 70940.398 | O17: =IFERROR(IF(I17/G17=0,"-",I17/G17),"-") -> 0.3125 | P17: =SUMIFS('HORA HORA'!$K:$K,'HORA HORA'!$B:$B,PJ_B2!$B17,'HORA HORA'!$C:$C,"="&"PJ",'HORA HORA'!$Y:$Y,"="&"EMPRESAS_2")/SUMIFS('HORA HORA'!$J:$J,'HORA HORA'!$B:$B,PJ_B1!$B17,'HORA HORA'!$C:$C,"="&"PJ",'HORA HORA'!$Y:$Y,"="&"EMPRESAS_2") -> 1 | Q17: =IFERROR(J17/I17,"-") -> 0.2
B18: 46267 | C18: =D18/$A$7 -> 1.5763629 | D18: =SUMIFS(TEMPOS!AL:AL,TEMPOS!X:X,$R$2,TEMPOS!Y:Y,B18) -> 0.429121 | E18: =SUMIFS('HORA HORA'!G:G,'HORA HORA'!C:C,PJ_B2!$R$1,'HORA HORA'!B:B,PJ_B2!B18,'HORA HORA'!Y:Y,"="&"EMPRESAS_2") -> 8044 | F18: =SUMIFS('HORA HORA'!H:H,'HORA HORA'!C:C,PJ_B2!$R$1,'HORA HORA'!B:B,PJ_B2!B18,'HORA HORA'!Y:Y,"="&"EMPRESAS_2") -> 208 | G18: =SUMIFS('HORA HORA'!J:J,'HORA HORA'!C:C,PJ_B2!$R$1,'HORA HORA'!B:B,PJ_B2!B18,'HORA HORA'!Y:Y,"="&"EMPRESAS_2") -> 13 | H18: =SUMIFS('HORA HORA'!K:K,'HORA HORA'!C:C,PJ_B2!$R$1,'HORA HORA'!B:B,PJ_B2!B18,'HORA HORA'!Y:Y,"="&"EMPRESAS_2") -> 12 | I18: =SUMIFS('HORA HORA'!L:L,'HORA HORA'!C:C,PJ_B2!$R$1,'HORA HORA'!B:B,PJ_B2!B18,'HORA HORA'!Y:Y,"="&"EMPRESAS_2") -> 3 | J18: =COUNTIFS(ACOMPANHAMENTO!S:S,"ACORDO IMPLANTADO",ACOMPANHAMENTO!BC:BC,B18,ACOMPANHAMENTO!H:H,PJ_B2!$R$1,ACOMPANHAMENTO!I:I,"="&"Business Banking 2") -> 0 | K18: =SUMIFS(ACOMPANHAMENTO!O:O,ACOMPANHAMENTO!H:H,PJ_B1!$R$1,ACOMPANHAMENTO!BC:BC,PJ_B1!B18,ACOMPANHAMENTO!I:I,"="&"Business Banking 2") -> 0 | L18: =IFERROR(K18/I18,0) -> 0 | M18: =SUMIFS(ACOMPANHAMENTO!R:R,ACOMPANHAMENTO!H:H,PJ_B1!$R$1,ACOMPANHAMENTO!BC:BC,PJ_B2!B18,ACOMPANHAMENTO!I:I,"="&"Business Banking 2") -> 0 | N18: =IFERROR(M18/I18,0) -> 0 | O18: =IFERROR(IF(I18/G18=0,"-",I18/G18),"-") -> 0.23076923 | P18: =SUMIFS('HORA HORA'!$K:$K,'HORA HORA'!$B:$B,PJ_B2!$B18,'HORA HORA'!$C:$C,"="&"PJ",'HORA HORA'!$Y:$Y,"="&"EMPRESAS_2")/SUMIFS('HORA HORA'!$J:$J,'HORA HORA'!$B:$B,PJ_B1!$B18,'HORA HORA'!$C:$C,"="&"PJ",'HORA HORA'!$Y:$Y,"="&"EMPRESAS_2") -> 0.92307692 | Q18: =IFERROR(J18/I18,"-") -> 0
B19: 46268 | C19: =D19/$A$7 -> 1.1154343 | D19: =SUMIFS(TEMPOS!AL:AL,TEMPOS!X:X,$R$2,TEMPOS!Y:Y,B19) -> 0.303646 | E19: =SUMIFS('HORA HORA'!G:G,'HORA HORA'!C:C,PJ_B2!$R$1,'HORA HORA'!B:B,PJ_B2!B19,'HORA HORA'!Y:Y,"="&"EMPRESAS_2") -> 7599 | F19: =SUMIFS('HORA HORA'!H:H,'HORA HORA'!C:C,PJ_B2!$R$1,'HORA HORA'!B:B,PJ_B2!B19,'HORA HORA'!Y:Y,"="&"EMPRESAS_2") -> 210 | G19: =SUMIFS('HORA HORA'!J:J,'HORA HORA'!C:C,PJ_B2!$R$1,'HORA HORA'!B:B,PJ_B2!B19,'HORA HORA'!Y:Y,"="&"EMPRESAS_2") -> 14 | H19: =SUMIFS('HORA HORA'!K:K,'HORA HORA'!C:C,PJ_B2!$R$1,'HORA HORA'!B:B,PJ_B2!B19,'HORA HORA'!Y:Y,"="&"EMPRESAS_2") -> 13 | I19: =SUMIFS('HORA HORA'!L:L,'HORA HORA'!C:C,PJ_B2!$R$1,'HORA HORA'!B:B,PJ_B2!B19,'HORA HORA'!Y:Y,"="&"EMPRESAS_2") -> 5 | J19: =COUNTIFS(ACOMPANHAMENTO!S:S,"ACORDO IMPLANTADO",ACOMPANHAMENTO!BC:BC,B19,ACOMPANHAMENTO!H:H,PJ_B2!$R$1,ACOMPANHAMENTO!I:I,"="&"Business Banking 2") -> 0 | K19: =SUMIFS(ACOMPANHAMENTO!O:O,ACOMPANHAMENTO!H:H,PJ_B1!$R$1,ACOMPANHAMENTO!BC:BC,PJ_B1!B19,ACOMPANHAMENTO!I:I,"="&"Business Banking 2") -> 0 | L19: =IFERROR(K19/I19,0) -> 0 | M19: =SUMIFS(ACOMPANHAMENTO!R:R,ACOMPANHAMENTO!H:H,PJ_B1!$R$1,ACOMPANHAMENTO!BC:BC,PJ_B2!B19,ACOMPANHAMENTO!I:I,"="&"Business Banking 2") -> 0 | N19: =IFERROR(M19/I19,0) -> 0 | O19: =IFERROR(IF(I19/G19=0,"-",I19/G19),"-") -> 0.35714286 | P19: =SUMIFS('HORA HORA'!$K:$K,'HORA HORA'!$B:$B,PJ_B1!$B19,'HORA HORA'!$C:$C,"="&"PJ",'HORA HORA'!$Y:$Y,"="&"EMPRESAS_2")/SUMIFS('HORA HORA'!$J:$J,'HORA HORA'!$B:$B,PJ_B2!$B19,'HORA HORA'!$C:$C,"="&"PJ",'HORA HORA'!$Y:$Y,"="&"EMPRESAS_2") -> 0.92857143 | Q19: =IFERROR(J19/I19,"-") -> 0
B20: 46269 | C20: =D20/$A$7 -> 1.3118694 | D20: =SUMIFS(TEMPOS!AL:AL,TEMPOS!X:X,$R$2,TEMPOS!Y:Y,B20) -> 0.35712 | E20: =SUMIFS('HORA HORA'!G:G,'HORA HORA'!C:C,PJ_B2!$R$1,'HORA HORA'!B:B,PJ_B2!B20,'HORA HORA'!Y:Y,"="&"EMPRESAS_2") -> 5941 | F20: =SUMIFS('HORA HORA'!H:H,'HORA HORA'!C:C,PJ_B2!$R$1,'HORA HORA'!B:B,PJ_B2!B20,'HORA HORA'!Y:Y,"="&"EMPRESAS_2") -> 113 | G20: =SUMIFS('HORA HORA'!J:J,'HORA HORA'!C:C,PJ_B2!$R$1,'HORA HORA'!B:B,PJ_B2!B20,'HORA HORA'!Y:Y,"="&"EMPRESAS_2") -> 8 | H20: =SUMIFS('HORA HORA'!K:K,'HORA HORA'!C:C,PJ_B2!$R$1,'HORA HORA'!B:B,PJ_B2!B20,'HORA HORA'!Y:Y,"="&"EMPRESAS_2") -> 5 | I20: =SUMIFS('HORA HORA'!L:L,'HORA HORA'!C:C,PJ_B2!$R$1,'HORA HORA'!B:B,PJ_B2!B20,'HORA HORA'!Y:Y,"="&"EMPRESAS_2") -> 1 | J20: =COUNTIFS(ACOMPANHAMENTO!S:S,"ACORDO IMPLANTADO",ACOMPANHAMENTO!BC:BC,B20,ACOMPANHAMENTO!H:H,PJ_B2!$R$1,ACOMPANHAMENTO!I:I,"="&"Business Banking 2") -> 0 | K20: =SUMIFS(ACOMPANHAMENTO!O:O,ACOMPANHAMENTO!H:H,PJ_B1!$R$1,ACOMPANHAMENTO!BC:BC,PJ_B1!#REF!,ACOMPANHAMENTO!I:I,"="&"Business Banking 2") -> 0 | L20: =IFERROR(K20/I20,0) -> 0 | M20: =SUMIFS(ACOMPANHAMENTO!R:R,ACOMPANHAMENTO!H:H,PJ_B1!$R$1,ACOMPANHAMENTO!BC:BC,PJ_B2!B20,ACOMPANHAMENTO!I:I,"="&"Business Banking 2") -> 0 | N20: =IFERROR(M20/I20,0) -> 0 | O20: =IFERROR(IF(I20/G20=0,"-",I20/G20),"-") -> 0.125 | P20: =SUMIFS('HORA HORA'!$K:$K,'HORA HORA'!$B:$B,PJ_B1!$B20,'HORA HORA'!$C:$C,"="&"PJ",'HORA HORA'!$Y:$Y,"="&"EMPRESAS_2")/SUMIFS('HORA HORA'!$J:$J,'HORA HORA'!$B:$B,PJ_B1!$B20,'HORA HORA'!$C:$C,"="&"PJ",'HORA HORA'!$Y:$Y,"="&"EMPRESAS_2") -> 0.625 | Q20: =IFERROR(J20/I20,"-") -> 0
B21: 46273 | C21: =D21/$A$7 -> 1.5344816 | D21: =SUMIFS(TEMPOS!AL:AL,TEMPOS!X:X,$R$2,TEMPOS!Y:Y,B21) -> 0.41772 | E21: =SUMIFS('HORA HORA'!G:G,'HORA HORA'!C:C,PJ_B2!$R$1,'HORA HORA'!B:B,PJ_B2!B21,'HORA HORA'!Y:Y,"="&"EMPRESAS_2") -> 6960 | F21: =SUMIFS('HORA HORA'!H:H,'HORA HORA'!C:C,PJ_B2!$R$1,'HORA HORA'!B:B,PJ_B2!B21,'HORA HORA'!Y:Y,"="&"EMPRESAS_2") -> 130 | G21: =SUMIFS('HORA HORA'!J:J,'HORA HORA'!C:C,PJ_B2!$R$1,'HORA HORA'!B:B,PJ_B2!B21,'HORA HORA'!Y:Y,"="&"EMPRESAS_2") -> 20 | H21: =SUMIFS('HORA HORA'!K:K,'HORA HORA'!C:C,PJ_B2!$R$1,'HORA HORA'!B:B,PJ_B2!B21,'HORA HORA'!Y:Y,"="&"EMPRESAS_2") -> 17 | I21: =SUMIFS('HORA HORA'!L:L,'HORA HORA'!C:C,PJ_B2!$R$1,'HORA HORA'!B:B,PJ_B2!B21,'HORA HORA'!Y:Y,"="&"EMPRESAS_2") -> 7 | J21: =COUNTIFS(ACOMPANHAMENTO!S:S,"ACORDO IMPLANTADO",ACOMPANHAMENTO!BC:BC,B21,ACOMPANHAMENTO!H:H,PJ_B2!$R$1,ACOMPANHAMENTO!I:I,"="&"Business Banking 2") -> 1 | K21: =SUMIFS(ACOMPANHAMENTO!O:O,ACOMPANHAMENTO!H:H,PJ_B1!$R$1,ACOMPANHAMENTO!BC:BC,PJ_B1!#REF!,ACOMPANHAMENTO!I:I,"="&"Business Banking 2") -> 0 | L21: =IFERROR(K21/I21,0) -> 0 | M21: =SUMIFS(ACOMPANHAMENTO!R:R,ACOMPANHAMENTO!H:H,PJ_B1!$R$1,ACOMPANHAMENTO!BC:BC,PJ_B2!B21,ACOMPANHAMENTO!I:I,"="&"Business Banking 2") -> 33523.07 | N21: =IFERROR(M21/I21,0) -> 4789.01 | O21: =IFERROR(IF(I21/G21=0,"-",I21/G21),"-") -> 0.35 | P21: =SUMIFS('HORA HORA'!$K:$K,'HORA HORA'!$B:$B,PJ_B2!$B21,'HORA HORA'!$C:$C,"="&"PJ",'HORA HORA'!$Y:$Y,"="&"EMPRESAS_2")/SUMIFS('HORA HORA'!$J:$J,'HORA HORA'!$B:$B,PJ_B2!$B21,'HORA HORA'!$C:$C,"="&"PJ",'HORA HORA'!$Y:$Y,"="&"EMPRESAS_2") -> 0.85 | Q21: =IFERROR(J21/I21,"-") -> 0.14285714
B22: 46274 | C22: =D22/$A$7 -> 1.8583788 | D22: =SUMIFS(TEMPOS!AL:AL,TEMPOS!X:X,$R$2,TEMPOS!Y:Y,B22) -> 0.505892 | E22: =SUMIFS('HORA HORA'!G:G,'HORA HORA'!C:C,PJ_B2!$R$1,'HORA HORA'!B:B,PJ_B2!B22,'HORA HORA'!Y:Y,"="&"EMPRESAS_2") -> 9155 | F22: =SUMIFS('HORA HORA'!H:H,'HORA HORA'!C:C,PJ_B2!$R$1,'HORA HORA'!B:B,PJ_B2!B22,'HORA HORA'!Y:Y,"="&"EMPRESAS_2") -> 179 | G22: =SUMIFS('HORA HORA'!J:J,'HORA HORA'!C:C,PJ_B2!$R$1,'HORA HORA'!B:B,PJ_B2!B22,'HORA HORA'!Y:Y,"="&"EMPRESAS_2") -> 13 | H22: =SUMIFS('HORA HORA'!K:K,'HORA HORA'!C:C,PJ_B2!$R$1,'HORA HORA'!B:B,PJ_B2!B22,'HORA HORA'!Y:Y,"="&"EMPRESAS_2") -> 9 | I22: =SUMIFS('HORA HORA'!L:L,'HORA HORA'!C:C,PJ_B2!$R$1,'HORA HORA'!B:B,PJ_B2!B22,'HORA HORA'!Y:Y,"="&"EMPRESAS_2") -> 2 | J22: =COUNTIFS(ACOMPANHAMENTO!S:S,"ACORDO IMPLANTADO",ACOMPANHAMENTO!BC:BC,B22,ACOMPANHAMENTO!H:H,PJ_B2!$R$1,ACOMPANHAMENTO!I:I,"="&"Business Banking 2") -> 1 | K22: =SUMIFS(ACOMPANHAMENTO!O:O,ACOMPANHAMENTO!H:H,PJ_B1!$R$1,ACOMPANHAMENTO!BC:BC,PJ_B1!B21,ACOMPANHAMENTO!I:I,"="&"Business Banking 2") -> 85000 | L22: =IFERROR(K22/I22,0) -> 42500 | M22: =SUMIFS(ACOMPANHAMENTO!R:R,ACOMPANHAMENTO!H:H,PJ_B1!$R$1,ACOMPANHAMENTO!BC:BC,PJ_B2!B22,ACOMPANHAMENTO!I:I,"="&"Business Banking 2") -> 21086.32 | N22: =IFERROR(M22/I22,0) -> 10543.16 | O22: =IFERROR(IF(I22/G22=0,"-",I22/G22),"-") -> 0.15384615 | P22: =SUMIFS('HORA HORA'!$K:$K,'HORA HORA'!$B:$B,PJ_B2!$B22,'HORA HORA'!$C:$C,"="&"PJ",'HORA HORA'!$Y:$Y,"="&"EMPRESAS_2")/SUMIFS('HORA HORA'!$J:$J,'HORA HORA'!$B:$B,PJ_B2!$B22,'HORA HORA'!$C:$C,"="&"PJ",'HORA HORA'!$Y:$Y,"="&"EMPRESAS_2") -> 0.69230769 | Q22: =IFERROR(J22/I22,"-") -> 0.5
B23: 46275 | C23: =D23/$A$7 -> 0.68979673 | D23: =SUMIFS(TEMPOS!AL:AL,TEMPOS!X:X,$R$2,TEMPOS!Y:Y,B23) -> 0.187778 | E23: =SUMIFS('HORA HORA'!G:G,'HORA HORA'!C:C,PJ_B2!$R$1,'HORA HORA'!B:B,PJ_B2!B23,'HORA HORA'!Y:Y,"="&"EMPRESAS_2") -> 9391 | F23: =SUMIFS('HORA HORA'!H:H,'HORA HORA'!C:C,PJ_B2!$R$1,'HORA HORA'!B:B,PJ_B2!B23,'HORA HORA'!Y:Y,"="&"EMPRESAS_2") -> 168 | G23: =SUMIFS('HORA HORA'!J:J,'HORA HORA'!C:C,PJ_B2!$R$1,'HORA HORA'!B:B,PJ_B2!B23,'HORA HORA'!Y:Y,"="&"EMPRESAS_2") -> 11 | H23: =SUMIFS('HORA HORA'!K:K,'HORA HORA'!C:C,PJ_B2!$R$1,'HORA HORA'!B:B,PJ_B2!B23,'HORA HORA'!Y:Y,"="&"EMPRESAS_2") -> 9 | I23: =SUMIFS('HORA HORA'!L:L,'HORA HORA'!C:C,PJ_B2!$R$1,'HORA HORA'!B:B,PJ_B2!B23,'HORA HORA'!Y:Y,"="&"EMPRESAS_2") -> 4 | J23: =COUNTIFS(ACOMPANHAMENTO!S:S,"ACORDO IMPLANTADO",ACOMPANHAMENTO!BC:BC,B23,ACOMPANHAMENTO!H:H,PJ_B2!$R$1,ACOMPANHAMENTO!I:I,"="&"Business Banking 2") -> 1 | K23: =SUMIFS(ACOMPANHAMENTO!O:O,ACOMPANHAMENTO!H:H,PJ_B1!$R$1,ACOMPANHAMENTO!BC:BC,PJ_B1!B22,ACOMPANHAMENTO!I:I,"="&"Business Banking 2") -> 10000 | L23: =IFERROR(K23/I23,0) -> 2500 | M23: =SUMIFS(ACOMPANHAMENTO!R:R,ACOMPANHAMENTO!H:H,PJ_B1!$R$1,ACOMPANHAMENTO!BC:BC,PJ_B2!B23,ACOMPANHAMENTO!I:I,"="&"Business Banking 2") -> 80464.97 | N23: =IFERROR(M23/I23,0) -> 20116.243 | O23: =IFERROR(IF(I23/G23=0,"-",I23/G23),"-") -> 0.36363636 | P23: =SUMIFS('HORA HORA'!$K:$K,'HORA HORA'!$B:$B,PJ_B2!$B23,'HORA HORA'!$C:$C,"="&"PJ",'HORA HORA'!$Y:$Y,"="&"EMPRESAS_2")/SUMIFS('HORA HORA'!$J:$J,'HORA HORA'!$B:$B,PJ_B2!$B23,'HORA HORA'!$C:$C,"="&"PJ",'HORA HORA'!$Y:$Y,"="&"EMPRESAS_2") -> 0.81818182 | Q23: =IFERROR(J23/I23,"-") -> 0.25
B24: 46276 | C24: =D24/$A$7 -> 0 | D24: =SUMIFS(TEMPOS!AL:AL,TEMPOS!X:X,$R$2,TEMPOS!Y:Y,B24) -> 0 | E24: =SUMIFS('HORA HORA'!G:G,'HORA HORA'!C:C,PJ_B2!$R$1,'HORA HORA'!B:B,PJ_B2!B24,'HORA HORA'!Y:Y,"="&"EMPRESAS_2") -> 5061 | F24: =SUMIFS('HORA HORA'!H:H,'HORA HORA'!C:C,PJ_B2!$R$1,'HORA HORA'!B:B,PJ_B2!B24,'HORA HORA'!Y:Y,"="&"EMPRESAS_2") -> 85 | G24: =SUMIFS('HORA HORA'!J:J,'HORA HORA'!C:C,PJ_B2!$R$1,'HORA HORA'!B:B,PJ_B2!B24,'HORA HORA'!Y:Y,"="&"EMPRESAS_2") -> 10 | H24: =SUMIFS('HORA HORA'!K:K,'HORA HORA'!C:C,PJ_B2!$R$1,'HORA HORA'!B:B,PJ_B2!B24,'HORA HORA'!Y:Y,"="&"EMPRESAS_2") -> 8 | I24: =SUMIFS('HORA HORA'!L:L,'HORA HORA'!C:C,PJ_B2!$R$1,'HORA HORA'!B:B,PJ_B2!B24,'HORA HORA'!Y:Y,"="&"EMPRESAS_2") -> 3 | J24: =COUNTIFS(ACOMPANHAMENTO!S:S,"ACORDO IMPLANTADO",ACOMPANHAMENTO!BC:BC,B24,ACOMPANHAMENTO!H:H,PJ_B2!$R$1,ACOMPANHAMENTO!I:I,"="&"Business Banking 2") -> 2 | K24: =SUMIFS(ACOMPANHAMENTO!O:O,ACOMPANHAMENTO!H:H,PJ_B1!$R$1,ACOMPANHAMENTO!BC:BC,PJ_B1!B23,ACOMPANHAMENTO!I:I,"="&"Business Banking 2") -> 10005.78 | L24: =IFERROR(K24/I24,0) -> 3335.26 | M24: =SUMIFS(ACOMPANHAMENTO!R:R,ACOMPANHAMENTO!H:H,PJ_B1!$R$1,ACOMPANHAMENTO!BC:BC,PJ_B2!B24,ACOMPANHAMENTO!I:I,"="&"Business Banking 2") -> 271079.34 | N24: =IFERROR(M24/I24,0) -> 90359.78 | O24: =IFERROR(IF(I24/G24=0,"-",I24/G24),"-") -> 0.3 | P24: =SUMIFS('HORA HORA'!$K:$K,'HORA HORA'!$B:$B,PJ_B2!$B24,'HORA HORA'!$C:$C,"="&"PJ",'HORA HORA'!$Y:$Y,"="&"EMPRESAS_2")/SUMIFS('HORA HORA'!$J:$J,'HORA HORA'!$B:$B,PJ_B2!$B24,'HORA HORA'!$C:$C,"="&"PJ",'HORA HORA'!$Y:$Y,"="&"EMPRESAS_2") -> 0.8 | Q24: =IFERROR(J24/I24,"-") -> 0.66666667
B25: 46279 | C25: =D25/$A$7 -> 0 | D25: =SUMIFS(TEMPOS!AL:AL,TEMPOS!X:X,$R$2,TEMPOS!Y:Y,B25) -> 0 | E25: =SUMIFS('HORA HORA'!G:G,'HORA HORA'!C:C,PJ_B2!$R$1,'HORA HORA'!B:B,PJ_B2!B25,'HORA HORA'!Y:Y,"="&"EMPRESAS_2") -> 0 | F25: =SUMIFS('HORA HORA'!H:H,'HORA HORA'!C:C,PJ_B2!$R$1,'HORA HORA'!B:B,PJ_B2!B25,'HORA HORA'!Y:Y,"="&"EMPRESAS_2") -> 0 | G25: =SUMIFS('HORA HORA'!J:J,'HORA HORA'!C:C,PJ_B2!$R$1,'HORA HORA'!B:B,PJ_B2!B25,'HORA HORA'!Y:Y,"="&"EMPRESAS_2") -> 0 | H25: =SUMIFS('HORA HORA'!K:K,'HORA HORA'!C:C,PJ_B2!$R$1,'HORA HORA'!B:B,PJ_B2!B25,'HORA HORA'!Y:Y,"="&"EMPRESAS_2") -> 0 | I25: =SUMIFS('HORA HORA'!L:L,'HORA HORA'!C:C,PJ_B2!$R$1,'HORA HORA'!B:B,PJ_B2!B25,'HORA HORA'!Y:Y,"="&"EMPRESAS_2") -> 0 | J25: =COUNTIFS(ACOMPANHAMENTO!S:S,"ACORDO IMPLANTADO",ACOMPANHAMENTO!BC:BC,B25,ACOMPANHAMENTO!H:H,PJ_B2!$R$1,ACOMPANHAMENTO!I:I,"="&"Business Banking 2") -> 0 | K25: =SUMIFS(ACOMPANHAMENTO!O:O,ACOMPANHAMENTO!H:H,PJ_B1!$R$1,ACOMPANHAMENTO!BC:BC,PJ_B1!B24,ACOMPANHAMENTO!I:I,"="&"Business Banking 2") -> 20008.67 | L25: =IFERROR(K25/I25,0) -> 0 | M25: =SUMIFS(ACOMPANHAMENTO!R:R,ACOMPANHAMENTO!H:H,PJ_B1!$R$1,ACOMPANHAMENTO!BC:BC,PJ_B2!B25,ACOMPANHAMENTO!I:I,"="&"Business Banking 2") -> 0 | N25: =IFERROR(M25/I25,0) -> 0 | O25: =IFERROR(IF(I25/G25=0,"-",I25/G25),"-") -> - | P25: =SUMIFS('HORA HORA'!$K:$K,'HORA HORA'!$B:$B,PJ_B2!$B25,'HORA HORA'!$C:$C,"="&"PJ",'HORA HORA'!$Y:$Y,"="&"EMPRESAS_2")/SUMIFS('HORA HORA'!$J:$J,'HORA HORA'!$B:$B,PJ_B2!$B25,'HORA HORA'!$C:$C,"="&"PJ",'HORA HORA'!$Y:$Y,"="&"EMPRESAS_2") -> #DIV/0! | Q25: =IFERROR(J25/I25,"-") -> -
B26: 46280 | C26: =D26/$A$7 -> 0 | D26: =SUMIFS(TEMPOS!AL:AL,TEMPOS!X:X,$R$2,TEMPOS!Y:Y,B26) -> 0 | E26: =SUMIFS('HORA HORA'!G:G,'HORA HORA'!C:C,PJ_B2!$R$1,'HORA HORA'!B:B,PJ_B2!B26,'HORA HORA'!Y:Y,"="&"EMPRESAS_2") -> 0 | F26: =SUMIFS('HORA HORA'!H:H,'HORA HORA'!C:C,PJ_B2!$R$1,'HORA HORA'!B:B,PJ_B2!B26,'HORA HORA'!Y:Y,"="&"EMPRESAS_2") -> 0 | G26: =SUMIFS('HORA HORA'!J:J,'HORA HORA'!C:C,PJ_B2!$R$1,'HORA HORA'!B:B,PJ_B2!B26,'HORA HORA'!Y:Y,"="&"EMPRESAS_2") -> 0 | H26: =SUMIFS('HORA HORA'!K:K,'HORA HORA'!C:C,PJ_B2!$R$1,'HORA HORA'!B:B,PJ_B2!B26,'HORA HORA'!Y:Y,"="&"EMPRESAS_2") -> 0 | I26: =SUMIFS('HORA HORA'!L:L,'HORA HORA'!C:C,PJ_B2!$R$1,'HORA HORA'!B:B,PJ_B2!B26,'HORA HORA'!Y:Y,"="&"EMPRESAS_2") -> 0 | J26: =COUNTIFS(ACOMPANHAMENTO!S:S,"ACORDO IMPLANTADO",ACOMPANHAMENTO!BC:BC,B26,ACOMPANHAMENTO!H:H,PJ_B2!$R$1,ACOMPANHAMENTO!I:I,"="&"Business Banking 2") -> 0 | K26: =SUMIFS(ACOMPANHAMENTO!O:O,ACOMPANHAMENTO!H:H,PJ_B1!$R$1,ACOMPANHAMENTO!BC:BC,PJ_B1!B25,ACOMPANHAMENTO!I:I,"="&"Business Banking 2") -> 0 | L26: =IFERROR(K26/I26,0) -> 0 | M26: =SUMIFS(ACOMPANHAMENTO!R:R,ACOMPANHAMENTO!H:H,PJ_B1!$R$1,ACOMPANHAMENTO!BC:BC,PJ_B2!B26,ACOMPANHAMENTO!I:I,"="&"Business Banking 2") -> 0 | N26: =IFERROR(M26/I26,0) -> 0 | O26: =IFERROR(IF(I26/G26=0,"-",I26/G26),"-") -> - | P26: =SUMIFS('HORA HORA'!$K:$K,'HORA HORA'!$B:$B,PJ_B2!$B26,'HORA HORA'!$C:$C,"="&"PJ",'HORA HORA'!$Y:$Y,"="&"EMPRESAS_2")/SUMIFS('HORA HORA'!$J:$J,'HORA HORA'!$B:$B,PJ_B2!$B26,'HORA HORA'!$C:$C,"="&"PJ",'HORA HORA'!$Y:$Y,"="&"EMPRESAS_2") -> #DIV/0! | Q26: =IFERROR(J26/I26,"-") -> -
B27: 46281 | C27: =D27/$A$7 -> 0 | D27: =SUMIFS(TEMPOS!AL:AL,TEMPOS!X:X,$R$2,TEMPOS!Y:Y,B27) -> 0 | E27: =SUMIFS('HORA HORA'!G:G,'HORA HORA'!C:C,PJ_B2!$R$1,'HORA HORA'!B:B,PJ_B2!B27,'HORA HORA'!Y:Y,"="&"EMPRESAS_2") -> 0 | F27: =SUMIFS('HORA HORA'!H:H,'HORA HORA'!C:C,PJ_B2!$R$1,'HORA HORA'!B:B,PJ_B2!B27,'HORA HORA'!Y:Y,"="&"EMPRESAS_2") -> 0 | G27: =SUMIFS('HORA HORA'!J:J,'HORA HORA'!C:C,PJ_B2!$R$1,'HORA HORA'!B:B,PJ_B2!B27,'HORA HORA'!Y:Y,"="&"EMPRESAS_2") -> 0 | H27: =SUMIFS('HORA HORA'!K:K,'HORA HORA'!C:C,PJ_B2!$R$1,'HORA HORA'!B:B,PJ_B2!B27,'HORA HORA'!Y:Y,"="&"EMPRESAS_2") -> 0 | I27: =SUMIFS('HORA HORA'!L:L,'HORA HORA'!C:C,PJ_B2!$R$1,'HORA HORA'!B:B,PJ_B2!B27,'HORA HORA'!Y:Y,"="&"EMPRESAS_2") -> 0 | J27: =COUNTIFS(ACOMPANHAMENTO!S:S,"ACORDO IMPLANTADO",ACOMPANHAMENTO!BC:BC,B27,ACOMPANHAMENTO!H:H,PJ_B2!$R$1,ACOMPANHAMENTO!I:I,"="&"Business Banking 2") -> 0 | K27: =SUMIFS(ACOMPANHAMENTO!O:O,ACOMPANHAMENTO!H:H,PJ_B1!$R$1,ACOMPANHAMENTO!BC:BC,PJ_B1!B26,ACOMPANHAMENTO!I:I,"="&"Business Banking 2") -> 0 | L27: =IFERROR(K27/I27,0) -> 0 | M27: =SUMIFS(ACOMPANHAMENTO!R:R,ACOMPANHAMENTO!H:H,PJ_B1!$R$1,ACOMPANHAMENTO!BC:BC,PJ_B2!B27,ACOMPANHAMENTO!I:I,"="&"Business Banking 2") -> 0 | N27: =IFERROR(M27/I27,0) -> 0 | O27: =IFERROR(IF(I27/G27=0,"-",I27/G27),"-") -> - | P27: =SUMIFS('HORA HORA'!$K:$K,'HORA HORA'!$B:$B,PJ_B2!$B27,'HORA HORA'!$C:$C,"="&"PJ",'HORA HORA'!$Y:$Y,"="&"EMPRESAS_2")/SUMIFS('HORA HORA'!$J:$J,'HORA HORA'!$B:$B,PJ_B2!$B27,'HORA HORA'!$C:$C,"="&"PJ",'HORA HORA'!$Y:$Y,"="&"EMPRESAS_2") -> #DIV/0! | Q27: =IFERROR(J27/I27,"-") -> -
B28: 46282 | C28: =D28/$A$7 -> 0 | D28: =SUMIFS(TEMPOS!AL:AL,TEMPOS!X:X,$R$2,TEMPOS!Y:Y,B28) -> 0 | E28: =SUMIFS('HORA HORA'!G:G,'HORA HORA'!C:C,PJ_B2!$R$1,'HORA HORA'!B:B,PJ_B2!B28,'HORA HORA'!Y:Y,"="&"EMPRESAS_2") -> 0 | F28: =SUMIFS('HORA HORA'!H:H,'HORA HORA'!C:C,PJ_B2!$R$1,'HORA HORA'!B:B,PJ_B2!B28,'HORA HORA'!Y:Y,"="&"EMPRESAS_2") -> 0 | G28: =SUMIFS('HORA HORA'!J:J,'HORA HORA'!C:C,PJ_B2!$R$1,'HORA HORA'!B:B,PJ_B2!B28,'HORA HORA'!Y:Y,"="&"EMPRESAS_2") -> 0 | H28: =SUMIFS('HORA HORA'!K:K,'HORA HORA'!C:C,PJ_B2!$R$1,'HORA HORA'!B:B,PJ_B2!B28,'HORA HORA'!Y:Y,"="&"EMPRESAS_2") -> 0 | I28: =SUMIFS('HORA HORA'!L:L,'HORA HORA'!C:C,PJ_B2!$R$1,'HORA HORA'!B:B,PJ_B2!B28,'HORA HORA'!Y:Y,"="&"EMPRESAS_2") -> 0 | J28: =COUNTIFS(ACOMPANHAMENTO!S:S,"ACORDO IMPLANTADO",ACOMPANHAMENTO!BC:BC,B28,ACOMPANHAMENTO!H:H,PJ_B2!$R$1,ACOMPANHAMENTO!I:I,"="&"Business Banking 2") -> 0 | K28: =SUMIFS(ACOMPANHAMENTO!O:O,ACOMPANHAMENTO!H:H,PJ_B1!$R$1,ACOMPANHAMENTO!BC:BC,PJ_B1!B27,ACOMPANHAMENTO!I:I,"="&"Business Banking 2") -> 0 | L28: =IFERROR(K28/I28,0) -> 0 | M28: =SUMIFS(ACOMPANHAMENTO!R:R,ACOMPANHAMENTO!H:H,PJ_B1!$R$1,ACOMPANHAMENTO!BC:BC,PJ_B2!B28,ACOMPANHAMENTO!I:I,"="&"Business Banking 2") -> 0 | N28: =IFERROR(M28/I28,0) -> 0 | O28: =IFERROR(IF(I28/G28=0,"-",I28/G28),"-") -> - | P28: =SUMIFS('HORA HORA'!$K:$K,'HORA HORA'!$B:$B,PJ_B2!$B28,'HORA HORA'!$C:$C,"="&"PJ",'HORA HORA'!$Y:$Y,"="&"EMPRESAS_2")/SUMIFS('HORA HORA'!$J:$J,'HORA HORA'!$B:$B,PJ_B2!$B28,'HORA HORA'!$C:$C,"="&"PJ",'HORA HORA'!$Y:$Y,"="&"EMPRESAS_2") -> #DIV/0! | Q28: =IFERROR(J28/I28,"-") -> -
B29: 46283 | C29: =D29/$A$7 -> 0 | D29: =SUMIFS(TEMPOS!AL:AL,TEMPOS!X:X,$R$2,TEMPOS!Y:Y,B29) -> 0 | E29: =SUMIFS('HORA HORA'!G:G,'HORA HORA'!C:C,PJ_B2!$R$1,'HORA HORA'!B:B,PJ_B2!B29,'HORA HORA'!Y:Y,"="&"EMPRESAS_2") -> 0 | F29: =SUMIFS('HORA HORA'!H:H,'HORA HORA'!C:C,PJ_B2!$R$1,'HORA HORA'!B:B,PJ_B2!B29,'HORA HORA'!Y:Y,"="&"EMPRESAS_2") -> 0 | G29: =SUMIFS('HORA HORA'!J:J,'HORA HORA'!C:C,PJ_B2!$R$1,'HORA HORA'!B:B,PJ_B2!B29,'HORA HORA'!Y:Y,"="&"EMPRESAS_2") -> 0 | H29: =SUMIFS('HORA HORA'!K:K,'HORA HORA'!C:C,PJ_B2!$R$1,'HORA HORA'!B:B,PJ_B2!B29,'HORA HORA'!Y:Y,"="&"EMPRESAS_2") -> 0 | I29: =SUMIFS('HORA HORA'!L:L,'HORA HORA'!C:C,PJ_B2!$R$1,'HORA HORA'!B:B,PJ_B2!B29,'HORA HORA'!Y:Y,"="&"EMPRESAS_2") -> 0 | J29: =COUNTIFS(ACOMPANHAMENTO!S:S,"ACORDO IMPLANTADO",ACOMPANHAMENTO!BC:BC,B29,ACOMPANHAMENTO!H:H,PJ_B2!$R$1,ACOMPANHAMENTO!I:I,"="&"Business Banking 2") -> 0 | K29: =SUMIFS(ACOMPANHAMENTO!O:O,ACOMPANHAMENTO!H:H,PJ_B1!$R$1,ACOMPANHAMENTO!BC:BC,PJ_B1!B28,ACOMPANHAMENTO!I:I,"="&"Business Banking 2") -> 0 | L29: =IFERROR(K29/I29,0) -> 0 | M29: =SUMIFS(ACOMPANHAMENTO!R:R,ACOMPANHAMENTO!H:H,PJ_B1!$R$1,ACOMPANHAMENTO!BC:BC,PJ_B2!B29,ACOMPANHAMENTO!I:I,"="&"Business Banking 2") -> 0 | N29: =IFERROR(M29/I29,0) -> 0 | O29: =IFERROR(IF(I29/G29=0,"-",I29/G29),"-") -> - | P29: =SUMIFS('HORA HORA'!$K:$K,'HORA HORA'!$B:$B,PJ_B2!$B29,'HORA HORA'!$C:$C,"="&"PJ",'HORA HORA'!$Y:$Y,"="&"EMPRESAS_2")/SUMIFS('HORA HORA'!$J:$J,'HORA HORA'!$B:$B,PJ_B2!$B29,'HORA HORA'!$C:$C,"="&"PJ",'HORA HORA'!$Y:$Y,"="&"EMPRESAS_2") -> #DIV/0! | Q29: =IFERROR(J29/I29,"-") -> -
B30: 46286 | C30: =D30/$A$7 -> 0 | D30: =SUMIFS(TEMPOS!AL:AL,TEMPOS!X:X,$R$2,TEMPOS!Y:Y,B30) -> 0 | E30: =SUMIFS('HORA HORA'!G:G,'HORA HORA'!C:C,PJ_B2!$R$1,'HORA HORA'!B:B,PJ_B2!B30,'HORA HORA'!Y:Y,"="&"EMPRESAS_2") -> 0 | F30: =SUMIFS('HORA HORA'!H:H,'HORA HORA'!C:C,PJ_B2!$R$1,'HORA HORA'!B:B,PJ_B2!B30,'HORA HORA'!Y:Y,"="&"EMPRESAS_2") -> 0 | G30: =SUMIFS('HORA HORA'!J:J,'HORA HORA'!C:C,PJ_B2!$R$1,'HORA HORA'!B:B,PJ_B2!B30,'HORA HORA'!Y:Y,"="&"EMPRESAS_2") -> 0 | H30: =SUMIFS('HORA HORA'!K:K,'HORA HORA'!C:C,PJ_B2!$R$1,'HORA HORA'!B:B,PJ_B2!B30,'HORA HORA'!Y:Y,"="&"EMPRESAS_2") -> 0 | I30: =SUMIFS('HORA HORA'!L:L,'HORA HORA'!C:C,PJ_B2!$R$1,'HORA HORA'!B:B,PJ_B2!B30,'HORA HORA'!Y:Y,"="&"EMPRESAS_2") -> 0 | J30: =COUNTIFS(ACOMPANHAMENTO!S:S,"ACORDO IMPLANTADO",ACOMPANHAMENTO!BC:BC,B30,ACOMPANHAMENTO!H:H,PJ_B2!$R$1,ACOMPANHAMENTO!I:I,"="&"Business Banking 2") -> 0 | K30: =SUMIFS(ACOMPANHAMENTO!O:O,ACOMPANHAMENTO!H:H,PJ_B1!$R$1,ACOMPANHAMENTO!BC:BC,PJ_B1!B29,ACOMPANHAMENTO!I:I,"="&"Business Banking 2") -> 0 | L30: =IFERROR(K30/I30,0) -> 0 | M30: =SUMIFS(ACOMPANHAMENTO!R:R,ACOMPANHAMENTO!H:H,PJ_B1!$R$1,ACOMPANHAMENTO!BC:BC,PJ_B2!B30,ACOMPANHAMENTO!I:I,"="&"Business Banking 2") -> 0 | N30: =IFERROR(M30/I30,0) -> 0 | O30: =IFERROR(IF(I30/G30=0,"-",I30/G30),"-") -> - | P30: =SUMIFS('HORA HORA'!$K:$K,'HORA HORA'!$B:$B,PJ_B2!$B30,'HORA HORA'!$C:$C,"="&"PJ",'HORA HORA'!$Y:$Y,"="&"EMPRESAS_2")/SUMIFS('HORA HORA'!$J:$J,'HORA HORA'!$B:$B,PJ_B2!$B30,'HORA HORA'!$C:$C,"="&"PJ",'HORA HORA'!$Y:$Y,"="&"EMPRESAS_2") -> #DIV/0! | Q30: =IFERROR(J30/I30,"-") -> -
B31: 46287 | C31: =D31/$A$7 -> 0 | D31: =SUMIFS(TEMPOS!AL:AL,TEMPOS!X:X,$R$2,TEMPOS!Y:Y,B31) -> 0 | E31: =SUMIFS('HORA HORA'!G:G,'HORA HORA'!C:C,PJ_B2!$R$1,'HORA HORA'!B:B,PJ_B2!B31,'HORA HORA'!Y:Y,"="&"EMPRESAS_2") -> 0 | F31: =SUMIFS('HORA HORA'!H:H,'HORA HORA'!C:C,PJ_B2!$R$1,'HORA HORA'!B:B,PJ_B2!B31,'HORA HORA'!Y:Y,"="&"EMPRESAS_2") -> 0 | G31: =SUMIFS('HORA HORA'!J:J,'HORA HORA'!C:C,PJ_B2!$R$1,'HORA HORA'!B:B,PJ_B2!B31,'HORA HORA'!Y:Y,"="&"EMPRESAS_2") -> 0 | H31: =SUMIFS('HORA HORA'!K:K,'HORA HORA'!C:C,PJ_B2!$R$1,'HORA HORA'!B:B,PJ_B2!B31,'HORA HORA'!Y:Y,"="&"EMPRESAS_2") -> 0 | I31: =SUMIFS('HORA HORA'!L:L,'HORA HORA'!C:C,PJ_B2!$R$1,'HORA HORA'!B:B,PJ_B2!B31,'HORA HORA'!Y:Y,"="&"EMPRESAS_2") -> 0 | J31: =COUNTIFS(ACOMPANHAMENTO!S:S,"ACORDO IMPLANTADO",ACOMPANHAMENTO!BC:BC,B31,ACOMPANHAMENTO!H:H,PJ_B2!$R$1,ACOMPANHAMENTO!I:I,"="&"Business Banking 2") -> 0 | K31: =SUMIFS(ACOMPANHAMENTO!O:O,ACOMPANHAMENTO!H:H,PJ_B1!$R$1,ACOMPANHAMENTO!BC:BC,PJ_B1!B30,ACOMPANHAMENTO!I:I,"="&"Business Banking 2") -> 0 | L31: =IFERROR(K31/I31,0) -> 0 | M31: =SUMIFS(ACOMPANHAMENTO!R:R,ACOMPANHAMENTO!H:H,PJ_B1!$R$1,ACOMPANHAMENTO!BC:BC,PJ_B2!B31,ACOMPANHAMENTO!I:I,"="&"Business Banking 2") -> 0 | N31: =IFERROR(M31/I31,0) -> 0 | O31: =IFERROR(IF(I31/G31=0,"-",I31/G31),"-") -> - | P31: =SUMIFS('HORA HORA'!$K:$K,'HORA HORA'!$B:$B,PJ_B2!$B31,'HORA HORA'!$C:$C,"="&"PJ",'HORA HORA'!$Y:$Y,"="&"EMPRESAS_2")/SUMIFS('HORA HORA'!$J:$J,'HORA HORA'!$B:$B,PJ_B2!$B31,'HORA HORA'!$C:$C,"="&"PJ",'HORA HORA'!$Y:$Y,"="&"EMPRESAS_2") -> #DIV/0! | Q31: =IFERROR(J31/I31,"-") -> -
B32: 46288 | C32: =D32/$A$7 -> 0 | D32: =SUMIFS(TEMPOS!AL:AL,TEMPOS!X:X,$R$2,TEMPOS!Y:Y,B32) -> 0 | E32: =SUMIFS('HORA HORA'!G:G,'HORA HORA'!C:C,PJ_B2!$R$1,'HORA HORA'!B:B,PJ_B2!B32,'HORA HORA'!Y:Y,"="&"EMPRESAS_2") -> 0 | F32: =SUMIFS('HORA HORA'!H:H,'HORA HORA'!C:C,PJ_B2!$R$1,'HORA HORA'!B:B,PJ_B2!B32,'HORA HORA'!Y:Y,"="&"EMPRESAS_2") -> 0 | G32: =SUMIFS('HORA HORA'!J:J,'HORA HORA'!C:C,PJ_B2!$R$1,'HORA HORA'!B:B,PJ_B2!B32,'HORA HORA'!Y:Y,"="&"EMPRESAS_2") -> 0 | H32: =SUMIFS('HORA HORA'!K:K,'HORA HORA'!C:C,PJ_B2!$R$1,'HORA HORA'!B:B,PJ_B2!B32,'HORA HORA'!Y:Y,"="&"EMPRESAS_2") -> 0 | I32: =SUMIFS('HORA HORA'!L:L,'HORA HORA'!C:C,PJ_B2!$R$1,'HORA HORA'!B:B,PJ_B2!B32,'HORA HORA'!Y:Y,"="&"EMPRESAS_2") -> 0 | J32: =COUNTIFS(ACOMPANHAMENTO!S:S,"ACORDO IMPLANTADO",ACOMPANHAMENTO!BC:BC,B32,ACOMPANHAMENTO!H:H,PJ_B2!$R$1,ACOMPANHAMENTO!I:I,"="&"Business Banking 2") -> 0 | K32: =SUMIFS(ACOMPANHAMENTO!O:O,ACOMPANHAMENTO!H:H,PJ_B1!$R$1,ACOMPANHAMENTO!BC:BC,PJ_B1!B31,ACOMPANHAMENTO!I:I,"="&"Business Banking 2") -> 0 | L32: =IFERROR(K32/I32,0) -> 0 | M32: =SUMIFS(ACOMPANHAMENTO!R:R,ACOMPANHAMENTO!H:H,PJ_B1!$R$1,ACOMPANHAMENTO!BC:BC,PJ_B2!B32,ACOMPANHAMENTO!I:I,"="&"Business Banking 2") -> 0 | N32: =IFERROR(M32/I32,0) -> 0 | O32: =IFERROR(IF(I32/G32=0,"-",I32/G32),"-") -> - | P32: =SUMIFS('HORA HORA'!$K:$K,'HORA HORA'!$B:$B,PJ_B2!$B32,'HORA HORA'!$C:$C,"="&"PJ",'HORA HORA'!$Y:$Y,"="&"EMPRESAS_2")/SUMIFS('HORA HORA'!$J:$J,'HORA HORA'!$B:$B,PJ_B2!$B32,'HORA HORA'!$C:$C,"="&"PJ",'HORA HORA'!$Y:$Y,"="&"EMPRESAS_2") -> #DIV/0! | Q32: =IFERROR(J32/I32,"-") -> -
B33: 46289 | C33: =D33/$A$7 -> 0 | D33: =SUMIFS(TEMPOS!AL:AL,TEMPOS!X:X,$R$2,TEMPOS!Y:Y,B33) -> 0 | E33: =SUMIFS('HORA HORA'!G:G,'HORA HORA'!C:C,PJ_B2!$R$1,'HORA HORA'!B:B,PJ_B2!B33,'HORA HORA'!Y:Y,"="&"EMPRESAS_2") -> 0 | F33: =SUMIFS('HORA HORA'!H:H,'HORA HORA'!C:C,PJ_B2!$R$1,'HORA HORA'!B:B,PJ_B2!B33,'HORA HORA'!Y:Y,"="&"EMPRESAS_2") -> 0 | G33: =SUMIFS('HORA HORA'!J:J,'HORA HORA'!C:C,PJ_B2!$R$1,'HORA HORA'!B:B,PJ_B2!B33,'HORA HORA'!Y:Y,"="&"EMPRESAS_2") -> 0 | H33: =SUMIFS('HORA HORA'!K:K,'HORA HORA'!C:C,PJ_B2!$R$1,'HORA HORA'!B:B,PJ_B2!B33,'HORA HORA'!Y:Y,"="&"EMPRESAS_2") -> 0 | I33: =SUMIFS('HORA HORA'!L:L,'HORA HORA'!C:C,PJ_B2!$R$1,'HORA HORA'!B:B,PJ_B2!B33,'HORA HORA'!Y:Y,"="&"EMPRESAS_2") -> 0 | J33: =COUNTIFS(ACOMPANHAMENTO!S:S,"ACORDO IMPLANTADO",ACOMPANHAMENTO!BC:BC,B33,ACOMPANHAMENTO!H:H,PJ_B2!$R$1,ACOMPANHAMENTO!I:I,"="&"Business Banking 2") -> 0 | K33: =SUMIFS(ACOMPANHAMENTO!O:O,ACOMPANHAMENTO!H:H,PJ_B1!$R$1,ACOMPANHAMENTO!BC:BC,PJ_B1!B32,ACOMPANHAMENTO!I:I,"="&"Business Banking 2") -> 0 | L33: =IFERROR(K33/I33,0) -> 0 | M33: =SUMIFS(ACOMPANHAMENTO!R:R,ACOMPANHAMENTO!H:H,PJ_B1!$R$1,ACOMPANHAMENTO!BC:BC,PJ_B2!B33,ACOMPANHAMENTO!I:I,"="&"Business Banking 2") -> 0 | N33: =IFERROR(M33/I33,0) -> 0 | O33: =IFERROR(IF(I33/G33=0,"-",I33/G33),"-") -> - | P33: =SUMIFS('HORA HORA'!$K:$K,'HORA HORA'!$B:$B,PJ_B2!$B33,'HORA HORA'!$C:$C,"="&"PJ",'HORA HORA'!$Y:$Y,"="&"EMPRESAS_2")/SUMIFS('HORA HORA'!$J:$J,'HORA HORA'!$B:$B,PJ_B2!$B33,'HORA HORA'!$C:$C,"="&"PJ",'HORA HORA'!$Y:$Y,"="&"EMPRESAS_2") -> #DIV/0! | Q33: =IFERROR(J33/I33,"-") -> -
... B37: 46295 | C37: =D37/$A$7 -> 0 | D37: =SUMIFS(TEMPOS!AL:AL,TEMPOS!X:X,$R$2,TEMPOS!Y:Y,B37) -> 0 | E37: =SUMIFS('HORA HORA'!G:G,'HORA HORA'!C:C,PJ_B2!$R$1,'HORA HORA'!B:B,PJ_B2!B37,'HORA HORA'!Y:Y,"="&"EMPRESAS_2") -> 0 | F37: =SUMIFS('HORA HORA'!H:H,'HORA HORA'!C:C,PJ_B2!$R$1,'HORA HORA'!B:B,PJ_B2!B37,'HORA HORA'!Y:Y,"="&"EMPRESAS_2") -> 0 | G37: =SUMIFS('HORA HORA'!J:J,'HORA HORA'!C:C,PJ_B2!$R$1,'HORA HORA'!B:B,PJ_B2!B37,'HORA HORA'!Y:Y,"="&"EMPRESAS_2") -> 0 | H37: =SUMIFS('HORA HORA'!K:K,'HORA HORA'!C:C,PJ_B2!$R$1,'HORA HORA'!B:B,PJ_B2!B37,'HORA HORA'!Y:Y,"="&"EMPRESAS_2") -> 0 | I37: =SUMIFS('HORA HORA'!L:L,'HORA HORA'!C:C,PJ_B2!$R$1,'HORA HORA'!B:B,PJ_B2!B37,'HORA HORA'!Y:Y,"="&"EMPRESAS_2") -> 0 | J37: =COUNTIFS(ACOMPANHAMENTO!S:S,"ACORDO IMPLANTADO",ACOMPANHAMENTO!BC:BC,B37,ACOMPANHAMENTO!H:H,PJ_B2!$R$1,ACOMPANHAMENTO!I:I,"="&"Business Banking 2") -> 0 | K37: =SUMIFS(ACOMPANHAMENTO!O:O,ACOMPANHAMENTO!H:H,PJ_B1!$R$1,ACOMPANHAMENTO!BC:BC,PJ_B1!B36,ACOMPANHAMENTO!I:I,"="&"Business Banking 2") -> 0 | L37: =IFERROR(K37/I37,0) -> 0 | M37: =SUMIFS(ACOMPANHAMENTO!R:R,ACOMPANHAMENTO!H:H,PJ_B1!$R$1,ACOMPANHAMENTO!BC:BC,PJ_B2!B37,ACOMPANHAMENTO!I:I,"="&"Business Banking 2") -> 0 | N37: =IFERROR(M37/I37,0) -> 0 | O37: =IFERROR(IF(I37/G37=0,"-",I37/G37),"-") -> - | P37: =SUMIFS('HORA HORA'!$K:$K,'HORA HORA'!$B:$B,PJ_B2!$B37,'HORA HORA'!$C:$C,"="&"PJ",'HORA HORA'!$Y:$Y,"="&"EMPRESAS_2")/SUMIFS('HORA HORA'!$J:$J,'HORA HORA'!$B:$B,PJ_B2!$B37,'HORA HORA'!$C:$C,"="&"PJ",'HORA HORA'!$Y:$Y,"="&"EMPRESAS_2") -> #DIV/0! | Q37: =IFERROR(J37/I37,"-") -> -

Sheet PRODUÇÃO
A1: ANO | B1: MÊS | C1: DATA DO ENVIO DA PROPOSTA | D1: DATA DA APROVAÇÃO | E1: EQUIPE INTERNA | F1: GESTOR | G1: ESCRITÓRIO | H1: TIPO DE PESSOA | I1: SEGMENTO | J1: FAIXA_ATRASO | K1: DATA DE ENVIO DA PROPOSTA | L1: D.U DO ENVIO DA PROPOSTA | M1: CLIENTE | N1: CPF/CNPJ | O1: CASH | P1: VALOR NEGOCIADO | Q1: RISCO | R1: SDO. CONTABIL / F6 | S1: STATUS DAS PROPOSTAS | T1: Nº DO ACORDO | U1: PREVISÃO DE PAGAMENTO | V1: DATA EXPURGADA | W1: ALTO IMPACTO/ALTO TICKET | X1: ESTRATÉGIAS | Y1: CAMPANHAS | Z1: FLAG AJUIZADO | AA1: FLAG ALTO IMPACTO | AB1: MACRO REGIÃO | AC1: ORIGEM NEGOCIAÇÃO | AD1: CANCELADA? | AE1: MOTIVO DO CANCELAMENTO | AF1: PROPOSTA NEGADA NO MÊS VIGENTE | AG1: MOTIVO DA NEGATIVA | AH1: ALÇADA | AI1: TAXA APLICADA | AJ1: % DESCONTO CONCEDIDO | AK1: % DESCONTO CAMPANHA | AL1: NEGOCIADOR | AM1: UF | AN1: ASSINATURA C2 | AO1: EXCEÇÃO | AP1: PARCELAMENTO | AQ1: VALOR DA PARCELA | AR1: VAL. PARC. IRREG. | AS1: VENC. PARC. | AT1: REVALIDAÇÃO | AU1: COMITÊ | AV1: TIPO DE AÇÃO | AW1: TIPO DE CITAÇÃO | AX1: PESQUISA PATRIMONIAL | AY1: STATUS DA PESQUISA PATRIMONIAL | AZ1: RETORNO DA PESQUISA PATRIMONIAL | BA1: EFEITO_ PESQUISA | BB1: Garantia | BC1: Tipo _Garantia | BD1: GATILHO BANCO | BE1: STATUS DO GATILHO | BF1: Nº Dossie | BG1: DATA DO PAGAMENTO | BH1: BACKOFFICE | BI1: Column61 | BJ1: Column62
A2: 2025 | B2: 46003 | C2: 45960 | D2: 45967 | E2: E2 - Alto Ticket | F2: ANDREZA SOUZA | G2: Viana Peixoto Advogados Associados | H2: PJ | I2: EMPRESAS 2 | J2: PR | K2: 45960 | L2: BALDE | M2: COLEGIO COC SUDOESTE LTDA | N2: 34507664000163 | O2: 15000 | P2: 766157.1 | Q2: 766157.1 | R2: 634531.29 | S2: PROPOSTA EXPURGADA | T2: 255777495 | U2: 45986 | V2: 45996 | W2: Alto Ticket | X2: Campanha mês | Y2: B-SEM CAMPANHA | Z2: SIM | AA2: NÃO | AB2: CENTRO_OESTE | AC2: Multicanalidade | AH2: FORMULARIO | AI2: 0.0112 | AJ2: 0 | AK2: 0.9 | AL2: EXPEDITO ONEDES | AM2: DF | AO2: NÃO | AP2: 49 | AQ2: 20462.77 | AS2: 46016 | AV2: Ação de execução | AW2: Positiva | AX2: Realizado | AY2: Efeitos Negativos | BB2: NÃO | BH2: Cecília Sousa
A3: 2025 | B3: 46003 | C3: 45960 | D3: 45967 | E3: E2 - Alto Ticket | F3: ANDREZA SOUZA | G3: Viana Peixoto Advogados Associados | H3: PJ | I3: EMPRESAS 2 | J3: PR | K3: 45960 | L3: BALDE | M3: COLEGIO JARDIM BOTANICO COC LTDA | N3: 23630816000102 | O3: 10000 | P3: 221820.48 | Q3: 221820.48 | R3: 191915.73 | S3: PROPOSTA EXPURGADA | T3: 255777405 | U3: 45986 | V3: 45996 | W3: Alto Ticket | X3: Campanha mês | Y3: B-SEM CAMPANHA | Z3: SIM | AA3: NÃO | AB3: CENTRO_OESTE | AC3: Multicanalidade | AH3: FORMULARIO | AI3: 0.0112 | AJ3: 0 | AK3: 0.9 | AL3: EXPEDITO ONEDES | AM3: DF | AO3: NÃO | AP3: 49 | AQ3: 5771.45 | AS3: 46016 | AV3: Ação de execução | AW3: Positiva | AX3: Realizado | AY3: Efeitos Negativos | BB3: NÃO | BH3: Cecília Sousa
A4: 2025 | B4: 46003 | C4: 45967 | D4: 45967 | E4: E2 - Alto Ticket | F4: ANDREZA SOUZA | G4: Viana Peixoto Advogados Associados | H4: PJ | I4: EMPRESAS 2 | J4: PR | K4: 45967 | L4: BALDE | M4: FEIRAO DA FARTURA LTDA | N4: 29105174000109 | O4: 9000 | P4: 790145.23 | Q4: 804985.56 | R4: 770273.94 | S4: PROPOSTA EXPURGADA | T4: 255815132 | U4: 45981 | V4: 45993 | W4: Alto Ticket | X4: Campanha mês | Y4: B-SEM CAMPANHA | Z4: NÃO | AA4: NÃO | AB4: CENTRO_OESTE | AC4: Multicanalidade | AH4: FORMULARIO | AI4: 0.0112 | AJ4: 0.0184 | AK4: 0.9 | AL4: SAMARA SOARES | AM4: MT | AO4: NÃO | AP4: 80 | AQ4: 8996.99 | AR4: 15561.65 | AS4: 46011 | BB4: NÃO | BH4: Cecília Sousa
A5: 2025 | B5: 46003 | C5: 45968 | D5: 45968 | E5: Massificado PF | F5: BRUNO MONTEIRO | G5: Viana Peixoto Advogados Associados | H5: PF | I5: PESSOA FÍSICA | J5: PR | K5: 45968 | L5: BALDE | M5: ADRIANA RIBEIRO FILHO | N5: 77211774134 | O5: 1321.71 | P5: 1321.71 | Q5: 33043.02 | R5: 20915.07 | S5: PROPOSTA EXPURGADA | T5: 255786480 | U5: 45980 | V5: 45993 | X5: Campanha mês | Y5: CAMPANHA PRE APROVADO C2 | Z5: NÃO | AA5: NÃO | AB5: CENTRO_OESTE | AC5: Multicanalidade | AH5: SEM ALÇADA | AI5: 0 | AJ5: 0.96 | AK5: 0.9 | AL5: MAIRLE SILVA | AM5: GO | AO5: NÃO | AP5: QUITAÇÃO | AQ5: QUITAÇÃO | AS5: QUITAÇÃO | BB5: NÃO | BH5: Hillary Cavalcanti
A6: 2025 | B6: 46003 | C6: 45971 | D6: 45971 | E6: Massificado PJ | F6: RICARDO SOUZA | G6: Viana Peixoto Advogados Associados | H6: PJ | I6: EMPRESAS 1 | J6: CV | K6: 45971 | L6: BALDE | M6: ROCHASANTOS ENGENHARIA LTDA ME | N6: 44019569000174 | O6: 19243.59 | P6: 19243.59 | Q6: 46935.58 | R6: 45024.46 | S6: PROPOSTA EXPURGADA | T6: 255797958 | U6: 45982 | V6: 45994 | X6: Campanha mês | Y6: CAMPANHA PRE APROVADO C2 | Z6: NÃO | AA6: NÃO | AB6: NORDESTE | AC6: Telefone | AH6: SEM ALÇADA | AI6: 0 | AJ6: 0.59 | AK6: 0.9 | AL6: JOSE ADAILTON | AM6: BA | AO6: NÃO | AP6: QUITAÇÃO | AQ6: QUITAÇÃO | AS6: QUITAÇÃO | BB6: NÃO | BH6: Cecília Sousa
A7: 2025 | B7: 46003 | C7: 45971 | D7: 45972 | E7: Massificado PJ | F7: RICARDO SOUZA | G7: Viana Peixoto Advogados Associados | H7: PJ | I7: EMPRESAS 1 | J7: CV | K7: 45971 | L7: BALDE | M7: HENRIQUE SOUZA GOMES LTDA | N7: 46819465000170 | O7: 1500 | P7: 6835.48 | Q7: 6835.48 | R7: 6429.73 | S7: PROPOSTA EXPURGADA | T7: 255818486 | U7: 45985 | V7: 45995 | X7: Campanha mês | Y7: B-SEM CAMPANHA | Z7: NÃO | AA7: NÃO | AB7: NORDESTE | AC7: Telefone | AH7: 90 | AI7: 0.0112 | AJ7: 0 | AK7: 0.9 | AL7: JOSE ADAILTON | AM7: PE | AO7: NÃO | AP7: 9 | AQ7: 705.67 | AS7: 46015 | BB7: NÃO | BH7: Hillary Cavalcanti
A8: 2025 | B8: 46003 | C8: 45973 | D8: 45973 | E8: Massificado PF | F8: BRUNO MONTEIRO | G8: Viana Peixoto Advogados Associados | H8: PF | I8: PESSOA FÍSICA | J8: PR | K8: 45973 | L8: BALDE | M8: GERSINO SANTOS TRINDADE JUNIOR | N8: 298756501 | O8: 4744.74 | P8: 4744.74 | Q8: 94658.72 | R8: 68965.31 | S8: PROPOSTA EXPURGADA | T8: 255835605 | U8: 45989 | V8: 46001 | X8: Campanha mês | Y8: CAMPANHA PRE APROVADO C2 | Z8: NÃO | AA8: NÃO | AB8: NORDESTE | AC8: Multicanalidade | AH8: SEM ALÇADA | AI8: 0 | AJ8: 0.9499 | AK8: 0.9 | AL8: FRANCISCA JOCILANE | AM8: BA | AO8: NÃO | AP8: QUITAÇÃO | AQ8: QUITAÇÃO | AS8: QUITAÇÃO | BB8: NÃO | BH8: Cecília Sousa
A9: 2025 | B9: 46003 | C9: 45973 | D9: 45973 | E9: Massificado PJ | F9: RICARDO SOUZA | G9: Viana Peixoto Advogados Associados | H9: PJ | I9: EMPRESAS 1 | J9: PR | K9: 45973 | L9: BALDE | M9: CONSTRUTORA IDEAL LTDA | N9: 5959269000113 | O9: 28018.64 | P9: 28018.64 | Q9: 254022.04 | R9: 174108.16 | S9: PROPOSTA EXPURGADA | T9: 255844169 | U9: 45986 | V9: 45996 | X9: Campanha mês | Y9: B-SEM CAMPANHA | Z9: SIM | AA9: NÃO | AB9: NORTE | AC9: Multicanalidade | AH9: SEM ALÇADA | AI9: 0 | AJ9: 0.8897 | AK9: 0.9 | AL9: WELLER FERREIRA | AM9: PI | AO9: NÃO | AP9: QUITAÇÃO | AQ9: QUITAÇÃO | AS9: QUITAÇÃO | BB9: NÃO | BH9: Cecília Sousa
A10: 2025 | B10: 46003 | C10: 45973 | D10: 45973 | E10: Massificado PJ | F10: RICARDO SOUZA | G10: Viana Peixoto Advogados Associados | H10: PJ | I10: EMPRESAS 1 | J10: PR | K10: 45973 | L10: BALDE | M10: E C B PARENTE | N10: 11301635000145 | O10: 40030.2 | P10: 40030.2 | Q10: 231659.98 | R10: 118786.33 | S10: PROPOSTA EXPURGADA | T10: 256047496 | U10: 45987 | V10: 45999 | X10: Campanha mês | Y10: B-SEM CAMPANHA | Z10: SIM | AA10: NÃO | AB10: NORTE | AC10: Telefone | AH10: SEM ALÇADA | AI10: 0 | AJ10: 0.8272 | AK10: 0.9 | AL10: WELLER FERREIRA | AM10: PA | AO10: NÃO | AP10: QUITAÇÃO | AQ10: QUITAÇÃO | AS10: QUITAÇÃO | AV10: Ação busca e apreensão. | AW10: Positiva | AX10: Não realizado | BB10: SIM | BC10: VEICULO | BH10: Hillary Cavalcanti
A11: 2025 | B11: 46003 | C11: 45973 | D11: 45973 | E11: Massificado PF | F11: BRUNO MONTEIRO | G11: Viana Peixoto Advogados Associados | H11: PF | I11: PESSOA FÍSICA | J11: PR | K11: 45973 | L11: BALDE | M11: WYARA LIMA FERREIRA HOLANDA | N11: 4921574480 | O11: 1598.71 | P11: 36904.65 | Q11: 106580.76 | R11: 36905.3 | S11: PROPOSTA EXPURGADA | T11: 255843351 | U11: 45985 | V11: 45995 | X11: Campanha mês | Y11: CAMPANHA PRE APROVADO C2 | Z11: NÃO | AA11: NÃO | AB11: NORDESTE | AC11: Multicanalidade | AH11: SEM ALÇADA | AI11: 0 | AJ11: 0.6537 | AK11: 0.9 | AL11: FRANCISCA JOCILANE | AM11: PE | AO11: NÃO | AP11: 72 | AQ11: 497.26 | AS11: 46015 | BB11: NÃO | BH11: Hillary Cavalcanti
A12: 2025 | B12: 46003 | C12: 45974 | D12: 45975 | E12: Massificado PF | F12: BRUNO MONTEIRO | G12: Viana Peixoto Advogados Associados | H12: PF | I12: PESSOA FÍSICA | J12: PR | K12: 45974 | L12: BALDE | M12: LUIZ HENRIQUE BRUM BANDEIRA JUNIOR | N12: 859091902 | O12: 2000 | P12: 138447.16 | Q12: 532489.05 | R12: 377675.55 | S12: PROPOSTA EXPURGADA | T12: 255852197 | U12: 45981 | V12: 45993 | W12: Alto Impacto | X12: Campanha mês | Y12: B-SEM CAMPANHA | Z12: NÃO | AA12: SIM | AB12: CENTRO_OESTE | AC12: Multicanalidade | AH12: 90 | AI12: 0.01 | AJ12: 0.74 | AK12: 0.9 | AL12: MICHELE GUIMARAES | AM12: DF | AO12: NÃO | AP12: 121 | AQ12: 1962.9 | AS12: 46011 | BB12: NÃO | BH12: Cecília Sousa
A13: 2025 | B13: 46003 | C13: 45974 | E13: E2 - Alto Ticket | F13: ANDREZA SOUZA | G13: Viana Peixoto Advogados Associados | H13: PJ | I13: EMPRESAS 2 | J13: PR | K13: 45974 | L13: BALDE | M13: LOOK KIDS 25 COMERCIO DE CONFECCOES LTDA | N13: 37929386000120 | O13: 50000 | P13: 196701.68 | Q13: 1032793 | R13: 880630.06 | S13: PROPOSTA NEGADA | T13: FORMULARIO | U13: 45975 | W13: Alto Ticket | X13: Campanha mês | Y13: B-SEM CAMPANHA | Z13: SIM | AA13: NÃO | AB13: NORDESTE | AC13: Multicanalidade | AG13: O referido crédito imobiliário da MARTA de trata de AF para o banco, certo? Aqui não podemos pedir penhora desse imóvel, pois não pertente ao devedor. O que poderíamos fazer é pedir a penhora dos direitos que ela possui sobre o imóvel, contudo, e considerando a informação de que esse crédito imobiliário está em atraso, tal pedido atrapalharia/atrasaria a retomada extrajudicial do bem pela equipe responsável então não acho viável. | AH13: FORMULARIO | AI13: 0.0112 | AJ13: 0.809 | AK13: 0.9 | AL13: SAMARA SOARES | AM13: BA | AO13: NÃO | AP13: 4 | AQ13: 50000 | AS13: 46005 | AV13: Ação de execução | AW13: Positiva | AX13: Não realizado | BB13: NÃO | BH13: Matheus Leão
A14: 2025 | B14: 46003 | C14: 45974 | E14: E2 - Alto Ticket | F14: ANDREZA SOUZA | G14: Viana Peixoto Advogados Associados | H14: PJ | I14: EMPRESAS 2 | J14: PR | K14: 45974 | L14: BALDE | M14: MARTA COMERCIO DE CONFECCOES LTDA | N14: 33172034000112 | O14: 20000 | P14: 20000 | Q14: 152834.45 | R14: 132786.3 | S14: PROPOSTA NEGADA | T14: FORMULARIO | U14: 45975 | W14: Alto Ticket | X14: Campanha mês | Y14: B-SEM CAMPANHA | Z14: SIM | AA14: NÃO | AB14: NORDESTE | AC14: Multicanalidade | AG14: O referido crédito imobiliário da MARTA de trata de AF para o banco, certo? Aqui não podemos pedir penhora desse imóvel, pois não pertente ao devedor. O que poderíamos fazer é pedir a penhora dos direitos que ela possui sobre o imóvel, contudo, e considerando a informação de que esse crédito imobiliário está em atraso, tal pedido atrapalharia/atrasaria a retomada extrajudicial do bem pela equipe responsável então não acho viável. | AH14: FORMULARIO | AI14: 0 | AJ14: 0.869 | AK14: 0.9 | AL14: SAMARA SOARES | AM14: BA | AO14: NÃO | AP14: QUITAÇÃO | AQ14: QUITAÇÃO | AS14: QUITAÇÃO | AV14: Ação Monitória | AW14: Positiva | AX14: Realizado | AY14: Positivo | BB14: NÃO | BH14: Matheus Leão
A15: 2025 | B15: 46003 | C15: 45975 | D15: 45978 | E15: Massificado PJ | F15: RICARDO SOUZA | G15: Viana Peixoto Advogados Associados | H15: PJ | I15: EMPRESAS 1 | J15: PR | K15: 45975 | L15: BALDE | M15: MAAB ESTETICA LTDA | N15: 41076924000159 | O15: 5405.38 | P15: 5405.38 | Q15: 90089.52 | R15: 58941.38 | S15: PROPOSTA EXPURGADA | T15: 255901688 | U15: 45980 | V15: 45993 | X15: Campanha mês | Y15: B-SEM CAMPANHA | Z15: NÃO | AA15: NÃO | AB15: CENTRO_OESTE | AC15: Multicanalidade | AH15: 90 | AI15: 0 | AJ15: 0.94 | AK15: 0.9 | AL15: JAQUELINE MAGALHAES | AM15: GO | AO15: NÃO | AP15: QUITAÇÃO | AQ15: QUITAÇÃO | AS15: QUITAÇÃO | BB15: NÃO | BH15: Cecília Sousa
A16: 2025 | B16: 46003 | C16: 45975 | D16: 45975 | E16: Massificado PF | F16: BRUNO MONTEIRO | G16: Viana Peixoto Advogados Associados | H16: PF | I16: PESSOA FÍSICA | J16: PR | K16: 45975 | L16: BALDE | M16: FABIO DONIZETE BERTOLOTI | N16: 26810288848 | O16: 2870.03 | P16: 2870.03 | Q16: 47833.8 | R16: 41643.19 | S16: PROPOSTA EXPURGADA | T16: 255915346 | U16: 45980 | V16: 45993 | X16: Campanha mês | Y16: CAMPANHA PRE APROVADO C2 | Z16: NÃO | AA16: NÃO | AB16: CENTRO_OESTE | AC16: Multicanalidade | AH16: SEM ALÇADA | AI16: 0 | AJ16: 0.94 | AK16: 0.9 | AL16: FRANCISCA JOCILANE | AM16: MS | AO16: NÃO | AP16: QUITAÇÃO | AQ16: QUITAÇÃO | AS16: QUITAÇÃO | BB16: NÃO | BH16: Cecília Sousa
A17: 2025 | B17: 46003 | C17: 45978 | D17: 45979 | E17: Massificado PJ | F17: RICARDO SOUZA | G17: Viana Peixoto Advogados Associados | H17: PJ | I17: EMPRESAS 1 | J17: CV | K17: 45978 | L17: BALDE | M17: D S DA SILVA REPRESENTACOES LTDA | N17: 46519022000163 | O17: 10000 | P17: 200125.69 | Q17: 200125.69 | R17: 199579.9 | S17: PROPOSTA EXPURGADA | T17: 255941562 | U17: 45982 | V17: 45994 | X17: Campanha mês | Y17: B-SEM CAMPANHA | Z17: NÃO | AA17: NÃO | AB17: NORDESTE | AC17: Multicanalidade | AH17: 90 | AI17: 0.0112 | AJ17: 0 | AK17: 0.9 | AL17: FRANCISCA ROSANGELA | AM17: PE | AO17: NÃO | AP17: 85 | AQ17: 3508.57 | AS17: 46011 | BB17: NÃO | BH17: Cecília Sousa
A18: 2025 | B18: 46003 | C18: 45978 | D18: 45978 | E18: Massificado PF | F18: BRUNO MONTEIRO | G18: Viana Peixoto Advogados Associados | H18: PF | I18: PESSOA FÍSICA | J18: PR | K18: 45978 | L18: BALDE | M18: ELINALDO BARBOSA DA SILVA | N18: 45678464 | O18: 8961.78 | P18: 8961.78 | Q18: 149363 | R18: 120664.87 | S18: PROPOSTA EXPURGADA | T18: 255929914 | U18: 45989 | V18: 46001 | X18: Campanha mês | Y18: CAMPANHA PRE APROVADO C2 | Z18: NÃO | AA18: NÃO | AB18: NORDESTE | AC18: Multicanalidade | AH18: SEM ALÇADA | AI18: 0 | AJ18: 0.94 | AK18: 0.9 | AL18: FRANCISCA JOCILANE | AM18: PE | AO18: NÃO | AP18: QUITAÇÃO | AQ18: QUITAÇÃO | AS18: QUITAÇÃO | BB18: NÃO | BH18: Hillary Cavalcanti
A19: 2025 | B19: 46003 | C19: 45979 | D19: 45982 | E19: Massificado PJ | F19: RICARDO SOUZA | G19: Viana Peixoto Advogados Associados | H19: PJ | I19: EMPRESAS 1 | J19: CV | K19: 45979 | L19: BALDE | M19: LS AUTOMOVEIS LOCACAO E COMERCIO LTDA | N19: 33734391000127 | O19: 600 | P19: 77740.52 | Q19: 78605.17 | R19: 77309.77 | S19: PROPOSTA EXPURGADA | T19: 255955586 | U19: 45982 | V19: 45994 | X19: Campanha mês | Y19: B-SEM CAMPANHA | Z19: NÃO | AA19: NÃO | AB19: CENTRO_OESTE | AC19: Multicanalidade | AH19: 90 | AI19: 0.0112 | AJ19: 0.011 | AK19: 0.9 | AL19: FRANCISCA ROSANGELA | AM19: DF | AO19: NÃO | AP19: 49 | AQ19: 2088.72 | AS19: 46012 | BB19: NÃO | BH19: Cecília Sousa
A20: 2025 | B20: 46003 | C20: 45980 | D20: 45982 | E20: Massificado PF | F20: BRUNO MONTEIRO | G20: Viana Peixoto Advogados Associados | H20: PF | I20: PESSOA FÍSICA | J20: PR | K20: 45980 | L20: BALDE | M20: DIOGENES COSTA MIRANDA | N20: 42307120149 | O20: 2100 | P20: 25935.53 | Q20: 185253.73 | R20: 124869.55 | S20: PROPOSTA EXPURGADA | T20: 255944371 | U20: 45982 | V20: 45994 | X20: Campanha mês | Y20: B-SEM CAMPANHA | Z20: NÃO | AA20: NÃO | AB20: CENTRO_OESTE | AC20: Multicanalidade | AH20: 90 | AI20: 0.01 | AJ20: 0.86 | AK20: 0.9 | AL20: MICHELE GUIMARAES | AM20: GO | AO20: NÃO | AP20: 13 | AQ20: 2120.82 | AS20: 46012 | BB20: NÃO | BH20: Hillary Cavalcanti
A21: 2025 | B21: 46003 | C21: 45980 | D21: 45980 | E21: Massificado PJ | F21: RICARDO SOUZA | G21: Viana Peixoto Advogados Associados | H21: PJ | I21: EMPRESAS 1 | J21: PR | K21: 45980 | L21: BALDE | M21: PINGUIM DISTRIBUIDORA E CONVENIENCIA LTD | N21: 30002001000136 | O21: 4000 | P21: 23748.82 | Q21: 158325.47 | R21: 133990.7 | S21: PROPOSTA EXPURGADA | T21: 255975177 | U21: 45987 | V21: 45995 | X21: Campanha mês | Y21: B-SEM CAMPANHA | Z21: NÃO | AA21: NÃO | AB21: CENTRO_OESTE | AC21: Multicanalidade | AH21: SEM ALÇADA | AI21: 0.0077 | AJ21: 0.85 | AK21: 0.9 | AL21: WELLER FERREIRA | AM21: MT | AO21: NÃO | AP21: 12 | AQ21: 1883.4 | AS21: 46017 | BB21: NÃO | BH21: Cecília Sousa
A22: 2025 | B22: 46003 | C22: 45980 | D22: 45985 | E22: E2 - Baixo Ticket | F22: ANDREZA SOUZA | G22: Viana Peixoto Advogados Associados | H22: PJ | I22: EMPRESAS 2 | J22: CV | K22: 45980 | L22: BALDE | M22: N BATISTA DA SILVA EIRELI | N22: 19104906000184 | O22: 105000 | P22: 105000 | Q22: 374033.98 | R22: 347492.05 | S22: PROPOSTA EXPURGADA | T22: 255976710 | U22: 45989 | V22: 46001 | X22: Campanha mês | Y22: B-SEM CAMPANHA | Z22: SIM | AA22: NÃO | AB22: CENTRO_OESTE | AC22: Multicanalidade | AH22: 90 | AI22: 0 | AJ22: 0.7193 | AK22: 0.9 | AL22: SAMARA SOARES | AM22: MS | AO22: NÃO | AP22: QUITAÇÃO | AQ22: QUITAÇÃO | AS22: QUITAÇÃO | AV22: Ação de execução | AW22: Positiva | AX22: Realizado | AY22: Positivo | BB22: NÃO | BH22: Cecília Sousa
A23: 2025 | B23: 46003 | C23: 45982 | D23: 45982 | E23: Massificado PJ | F23: RICARDO SOUZA | G23: Viana Peixoto Advogados Associados | H23: PJ | I23: EMPRESAS 1 | J23: PR | K23: 45982 | L23: BALDE | M23: ALINE CARLOS RIBEIRO | N23: 13635622000138 | O23: 1595.8 | P23: 1595.8 | Q23: 4986.89 | R23: 4693.88 | S23: PROPOSTA EXPURGADA | T23: 255973691 | U23: 45985 | V23: 45995 | X23: Campanha mês | Y23: CAMPANHA PRE APROVADO C2 | Z23: NÃO | AA23: NÃO | AB23: CENTRO_OESTE | AC23: Telefone | AH23: SEM ALÇADA | AI23: 0 | AJ23: 0.68 | AK23: 0.9 | AL23: FRANCISCO CLEONTE | AM23: TO | AO23: NÃO | AP23: QUITAÇÃO | AQ23: QUITAÇÃO | AS23: QUITAÇÃO | BB23: NÃO | BH23: Hillary Cavalcanti
A24: 2025 | B24: 46003 | C24: 45982 | D24: 45985 | E24: Massificado PJ | F24: RICARDO SOUZA | G24: Viana Peixoto Advogados Associados | H24: PJ | I24: EMPRESAS 1 | J24: CV | K24: 45982 | L24: BALDE | M24: RESTAURANTE REI DO ASSADO LTDA | N24: 38402508000199 | O24: 3000 | P24: 75373.35 | Q24: 125622.24 | R24: 123656.77 | S24: PROPOSTA EXPURGADA | T24: 255973682 | U24: 45987 | V24: 45999 | X24: Campanha mês | Y24: B-SEM CAMPANHA | Z24: NÃO | AA24: NÃO | AB24: CENTRO_OESTE | AC24: Multicanalidade | AH24: 90 | AI24: 0.0112 | AJ24: 0.4 | AK24: 0.9 | AL24: WELLER FERREIRA | AM24: MT | AO24: NÃO | AP24: 49 | AQ24: 1974.13 | AS24: 46017 | BB24: NÃO | BH24: Cecília Sousa
A25: 2025 | B25: 46003 | C25: 45982 | D25: 45987 | E25: E2 - Alto Ticket | F25: ANDREZA SOUZA | G25: Viana Peixoto Advogados Associados | H25: PJ | I25: EMPRESAS 2 | J25: PR | K25: 45982 | L25: BALDE | M25: MMC COM DE FERRAMENTAS LTDA | N25: 28731579000181 | O25: 36429.98 | P25: 569240.13 | Q25: 569240.13 | R25: 482277.65 | S25: ACORDO IMPLANTADO | T25: 256056827 | U25: 45988 | W25: Alto Ticket | X25: Campanha mês | Y25: B-SEM CAMPANHA | Z25: SIM | AA25: NÃO | AB25: CENTRO_OESTE | AC25: Multicanalidade | AH25: FORMULARIO | AI25: 0.0112 | AJ25: 0 | AK25: 0.9 | AL25: SAMARA SOARES | AM25: TO | AO25: NÃO | AP25: 95 | AQ25: 9198.61 | AS25: 46018 | AV25: Ação de execução | AW25: Positiva | AX25: Realizado | AY25: Positivo | BB25: NÃO | BG25: 45993 | BH25: Cecília Sousa
A26: 2025 | B26: 46003 | C26: 45982 | D26: 45987 | E26: E2 - Alto Ticket | F26: ANDREZA SOUZA | G26: Viana Peixoto Advogados Associados | H26: PJ | I26: EMPRESAS 2 | J26: PR | K26: 45982 | L26: BALDE | M26: MMCL COM. DE MATERIAL DE CONSTRUCAO EIRE | N26: 36481941000131 | O26: 36465.98 | P26: 569751.37 | Q26: 569751.37 | R26: 484206.59 | S26: PROPOSTA EXPURGADA | T26: 256056985 | U26: 45988 | V26: 46000 | W26: Alto Ticket | X26: Campanha mês | Y26: B-SEM CAMPANHA | Z26: SIM | AA26: NÃO | AB26: CENTRO_OESTE | AC26: Multicanalidade | AH26: FORMULARIO | AI26: 0.0112 | AJ26: 0 | AK26: 0.9 | AL26: SAMARA SOARES | AM26: TO | AO26: NÃO | AP26: 95 | AQ26: 9206.83 | AS26: 46018 | AV26: Ação busca e apreensão. | AW26: Positiva | AX26: Realizado | AY26: Efeitos Negativos | BB26: SIM | BC26: VEICULO | BH26: Cecília Sousa
A27: 2025 | B27: 46003 | C27: 45985 | D27: 45985 | E27: E2 - Baixo Ticket | F27: ANDREZA SOUZA | G27: Viana Peixoto Advogados Associados | H27: PJ | I27: EMPRESAS 2 | J27: PR | K27: 45985 | L27: BALDE | M27: CASA DE CARNE ALTA FLORESTA EIRELI | N27: 23937309000108 | O27: 6956.61 | P27: 6956.61 | Q27: 231558.03 | R27: 119619.82 | S27: PROPOSTA EXPURGADA | T27: 256023099 | U27: 45987 | V27: 45999 | X27: Campanha mês | Y27: CAMPANHA PRE APROVADO C2 | Z27: NÃO | AA27: NÃO | AB27: CENTRO_OESTE | AC27: Multicanalidade | AH27: SEM ALÇADA | AI27: 0 | AJ27: 0.97 | AK27: 0.9 | AL27: SABRINA ERLLEN | AM27: MT | AO27: NÃO | AP27: QUITAÇÃO | AQ27: QUITAÇÃO | AS27: QUITAÇÃO | BB27: NÃO | BH27: Cecília Sousa
A28: 2025 | B28: 46003 | C28: 45986 | D28: 45986 | E28: Massificado PJ | F28: RICARDO SOUZA | G28: Viana Peixoto Advogados Associados | H28: PJ | I28: EMPRESAS 1 | J28: PR | K28: 45986 | L28: BALDE | M28: AMERICAN PRINT DIGITAL GRAFICA LTDA | N28: 968434000180 | O28: 6967.05 | P28: 6967.05 | Q28: 232235.04 | R28: 72521.19 | S28: PROPOSTA EXPURGADA | T28: 256040176 | U28: 45989 | V28: 46001 | X28: Campanha mês | Y28: CAMPANHA PRE APROVADO C2 | Z28: NÃO | AA28: NÃO | AB28: NORDESTE | AC28: Multicanalidade | AH28: SEM ALÇADA | AI28: 0 | AJ28: 0.97 | AK28: 0.9 | AL28: MIKELYNE ALVES | AM28: PE | AO28: NÃO | AP28: QUITAÇÃO | AQ28: QUITAÇÃO | AS28: QUITAÇÃO | BB28: NÃO | BH28: Hillary Cavalcanti
A29: 2025 | B29: 46003 | C29: 45986 | D29: 45986 | E29: Massificado PJ | F29: RICARDO SOUZA | G29: Viana Peixoto Advogados Associados | H29: PJ | I29: EMPRESAS 1 | J29: CV | K29: 45986 | L29: BALDE | M29: SUPER ECONOMICO COMERCIO DE GENEROS ALIM | N29: 14206585000105 | O29: 30000 | P29: 106402.41 | Q29: 152003.43 | R29: 149729.62 | S29: PROPOSTA EXPURGADA | T29: 255997777 | U29: 45989 | V29: 45996 | X29: Campanha mês | Y29: B-SEM CAMPANHA | Z29: SIM | AA29: NÃO | AB29: NORTE | AC29: Multicanalidade | AH29: 90 | AI29: 0.0112 | AJ29: 0.3 | AK29: 0.9 | AL29: LUCAS SILVA | AM29: AM | AO29: NÃO | AP29: 12 | AQ29: 7442.45 | AS29: 46017 | BB29: NÃO | BH29: Cecília Sousa
A30: 2025 | B30: 46003 | C30: 45986 | D30: 45986 | E30: Massificado PF | F30: BRUNO MONTEIRO | G30: Viana Peixoto Advogados Associados | H30: PF | I30: PESSOA FÍSICA | J30: PR | K30: 45986 | L30: BALDE | M30: SILVIA PINHEIRO DE AZEVEDO | N30: 9209352300 | O30: 14544.79 | P30: 14544.79 | Q30: 363619.68 | R30: 225678.72 | S30: ACORDO IMPLANTADO | T30: 256026229 | U30: 45995 | W30: Alto Impacto | X30: Campanha mês | Y30: CAMPANHA PRE APROVADO C2 | Z30: NÃO | AA30: SIM | AB30: NORTE | AC30: Multicanalidade | AH30: SEM ALÇADA | AI30: 0 | AJ30: 0.96 | AK30: 0.9 | AL30: MICHELE GUIMARAES | AM30: CE | AO30: NÃO | AP30: QUITAÇÃO | AQ30: QUITAÇÃO | AS30: QUITAÇÃO | BB30: NÃO | BG30: 45994 | BH30: Cecília Sousa
A31: 2025 | B31: 46003 | C31: 45987 | D31: 45987 | E31: Massificado PF | F31: BRUNO MONTEIRO | G31: Viana Peixoto Advogados Associados | H31: PF | I31: PESSOA FÍSICA | J31: CV | K31: 45987 | L31: BALDE | M31: FERNANDO VILAR DE MEDEIROS | N31: 37211900172 | O31: 13768.47 | P31: 13768.47 | Q31: 105911.34 | R31: 97434.71 | S31: ACORDO IMPLANTADO | T31: 256058835 | U31: 45999 | X31: Campanha mês | Y31: CAMPANHA PRE APROVADO C2 | Z31: NÃO | AA31: NÃO | AB31: CENTRO_OESTE | AC31: Telefone | AH31: SEM ALÇADA | AI31: 0 | AJ31: 0.87 | AK31: 0.9 | AL31: MICHELE GUIMARAES | AM31: DF | AO31: NÃO | AP31: QUITAÇÃO | AQ31: QUITAÇÃO | AS31: QUITAÇÃO | BB31: NÃO | BG31: 45999 | BH31: Hillary Cavalcanti
A32: 2025 | B32: 46003 | C32: 45987 | D32: 45987 | E32: Massificado PF | F32: BRUNO MONTEIRO | G32: Viana Peixoto Advogados Associados | H32: PF | I32: PESSOA FÍSICA | J32: PR | K32: 45987 | L32: BALDE | M32: KELVIO FELIPE DOS SANTOS | N32: 998526320 | O32: 2074.55 | P32: 2074.55 | Q32: 51863.66 | R32: 32252.79 | S32: ACORDO IMPLANTADO | T32: 256046393 | U32: 45996 | X32: Campanha mês | Y32: CAMPANHA PRE APROVADO C2 | Z32: NÃO | AA32: NÃO | AB32: NORTE | AC32: Multicanalidade | AH32: SEM ALÇADA | AI32: 0 | AJ32: 0.96 | AK32: 0.9 | AL32: MICHELE GUIMARAES | AM32: CE | AO32: NÃO | AP32: QUITAÇÃO | AQ32: QUITAÇÃO | AS32: QUITAÇÃO | BB32: NÃO | BG32: 45996 | BH32: Hillary Cavalcanti
A33: 2025 | B33: 46003 | C33: 45987 | D33: 45988 | E33: Massificado PJ | F33: RICARDO SOUZA | G33: Viana Peixoto Advogados Associados | H33: PJ | I33: EMPRESAS 1 | J33: CV | K33: 45987 | L33: BALDE | M33: SANTANA COMERCIO DE HORTIFRUTIGRANJEIROS | N33: 51636054000189 | O33: 1000 | P33: 175365.61 | Q33: 175365.61 | R33: 172452.36 | S33: PROPOSTA EXPURGADA | T33: 256028447 | U33: 45989 | V33: 46001 | X33: Campanha mês | Y33: B-SEM CAMPANHA | Z33: SIM | AA33: NÃO | AB33: NORDESTE | AC33: Multicanalidade | AH33: 90 | AI33: 0.0112 | AJ33: 0 | AK33: 0.9 | AL33: AMANDA DA SILVA | AM33: BA | AO33: NÃO | AP33: 97 | AQ33: 999.99 | AR33: 2199.99 | AS33: 46020 | AV33: Ação de execução | AW33: Positiva | AX33: Não realizado | BB33: NÃO | BH33: Cecília Sousa
A34: 2025 | B34: 46003 | C34: 45987 | D34: 45987 | E34: Massificado PJ | F34: RICARDO SOUZA | G34: Viana Peixoto Advogados Associados | H34: PJ | I34: EMPRESAS 1 | J34: CV | K34: 45987 | L34: BALDE | M34: MEN STYLE COMERCIO DE ROUPAS E ACESSORIO | N34: 50219770000106 | O34: 2700 | P34: 252357.48 | Q34: 280397.19 | R34: 276309.65 | S34: PROPOSTA EXPURGADA | T34: 256060201 | U34: 45988 | V34: 46000 | X34: Campanha mês | Y34: B-SEM CAMPANHA | Z34: SIM | AA34: NÃO | AB34: NORDESTE | AC34: Multicanalidade | AH34: 90 | AI34: 0.0112 | AJ34: 0.1 | AK34: 0.9 | AL34: FRANCISCA ROSANGELA | AM34: PE | AO34: NÃO | AP34: 85 | AQ34: 4603.42 | AS34: 46018 | AV34: Ação de execução | AW34: Positiva | AX34: Não realizado | BB34: NÃO | BH34: Hillary Cavalcanti
A35: 2025 | B35: 46003 | C35: 45987 | D35: 45987 | E35: E2 - Baixo Ticket | F35: ANDREZA SOUZA | G35: Viana Peixoto Advogados Associados | H35: PJ | I35: EMPRESAS 2 | J35: CV | K35: 45987 | L35: BALDE | M35: GROUP CINERGIA LTDA | N35: 17678452000120 | O35: 45000.02 | P35: 45000.02 | Q35: 65495.44 | R35: 65495.44 | S35: PROPOSTA EXPURGADA | T35: 256517566 | U35: 46003 | V35: 46008 | W35: Alto Impacto | X35: Campanha mês | Y35: B-SEM CAMPANHA | Z35: NÃO | AA35: SIM | AB35: NORTE | AC35: Multicanalidade | AH35: FORMULARIO | AI35: 0 | AJ35: 0.3129 | AK35: 0.9 | AL35: SAMARA SOARES | AM35: MA | AO35: NÃO | AP35: QUITAÇÃO | AQ35: QUITAÇÃO | AS35: QUITAÇÃO | BB35: SIM | BC35: VEICULO | BH35: Cecília Sousa
A36: 2025 | B36: 46003 | C36: 45987 | D36: 45988 | E36: E2 - Baixo Ticket | F36: ANDREZA SOUZA | G36: Viana Peixoto Advogados Associados | H36: PJ | I36: EMPRESAS 2 | J36: PR | K36: 45987 | L36: BALDE | M36: NORDESTE FRIOS E CONGELADOS EIRELI | N36: 15576467000151 | O36: 5000 | P36: 15309.2 | Q36: 153092 | R36: 124104.73 | S36: PROPOSTA EXPURGADA | T36: 256016049 | U36: 45989 | V36: 46001 | X36: Campanha mês | Y36: B-SEM CAMPANHA | Z36: SIM | AA36: NÃO | AB36: NORDESTE | AC36: Multicanalidade | AH36: 90 | AI36: 0 | AJ36: 0.9 | AK36: 0.9 | AL36: SAMARA SOARES | AM36: RN | AO36: NÃO | AP36: 4 | AQ36: 3436.4 | AS36: 46019 | AV36: Ação de execução | AW36: Positiva | AX36: Realizado | AY36: Efeitos Negativos | BB36: NÃO | BH36: Cecília Sousa
A37: 2025 | B37: 46003 | C37: 45987 | D37: 45988 | E37: E2 - Alto Ticket | F37: ANDREZA SOUZA | G37: Viana Peixoto Advogados Associados | H37: PJ | I37: EMPRESAS 2 | J37: PR | K37: 45987 | L37: BALDE | M37: M&N AUTOCENTER E MULTIMARCAS LTDA | N37: 19316131000100 | O37: 8285.86 | P37: 8285.86 | Q37: 163606.78 | R37: 106256.98 | S37: PROPOSTA EXPURGADA | T37: 256215704 | U37: 45989 | V37: 46001 | W37: Alto Ticket | X37: Campanha mês | Y37: B-SEM CAMPANHA | Z37: SIM | AA37: NÃO | AB37: CENTRO_OESTE | AC37: Multicanalidade | AH37: FORMULARIO | AI37: 0 | AJ37: 0.9562 | AK37: 0.9 | AL37: LUCAS SILVA | AM37: DF | AO37: NÃO | AP37: QUITAÇÃO | AQ37: QUITAÇÃO | AS37: QUITAÇÃO | AV37: Ação Monitória | AW37: Positiva | AX37: Realizado | AY37: Efeitos Negativos | BB37: NÃO | BH37: Cecília Sousa
A38: 2025 | B38: 46003 | C38: 45988 | D38: 45988 | E38: Massificado PJ | F38: RICARDO SOUZA | G38: Viana Peixoto Advogados Associados | H38: PJ | I38: EMPRESAS 1 | J38: PR | K38: 45988 | L38: BALDE | M38: ELIANO FERREIRA DE LIMA LTDA | N38: 36712204000100 | O38: 30006.46 | P38: 30006.46 | Q38: 152471.84 | R38: 136024.85 | S38: PROPOSTA EXPURGADA | T38: 256210699 | U38: 46001 | V38: 45996 | X38: Campanha mês | Y38: B-SEM CAMPANHA | Z38: NÃO | AA38: NÃO | AB38: NORTE | AC38: Multicanalidade | AH38: 90 | AI38: 0 | AJ38: 0.8032 | AK38: 0.9 | AL38: MICHELE GUIMARAES | AM38: PI | AO38: NÃO | AP38: QUITAÇÃO | AQ38: QUITAÇÃO | AS38: QUITAÇÃO | BB38: NÃO | BH38: Cecília Sousa
A39: 2025 | B39: 46003 | C39: 45988 | D39: 45988 | E39: Massificado PF | F39: BRUNO MONTEIRO | G39: Viana Peixoto Advogados Associados | H39: PF | I39: PESSOA FÍSICA | J39: PR | K39: 45988 | L39: BALDE | M39: FERNANDA TERESA DOS ANJOS BARBOSA SALES | N39: 93447086572 | O39: 3404.7 | P39: 3404.7 | Q39: 68093.86 | R39: 51712.56 | S39: PROPOSTA EXPURGADA | T39: 256211358 | U39: 45996 | V39: 45993 | X39: Campanha mês | Y39: CAMPANHA PRE APROVADO C2 | Z39: NÃO | AA39: NÃO | AB39: NORDESTE | AC39: Telefone | AH39: SEM ALÇADA | AI39: 0 | AJ39: 0.95 | AK39: 0.9 | AL39: CAMILA PINTO | AM39: BA | AO39: NÃO | AP39: QUITAÇÃO | AQ39: QUITAÇÃO | AS39: QUITAÇÃO | BB39: NÃO | BH39: Cecília Sousa
A40: 2025 | B40: 46003 | C40: 45988 | D40: 45988 | E40: Massificado PJ | F40: RICARDO SOUZA | G40: Viana Peixoto Advogados Associados | H40: PJ | I40: EMPRESAS 1 | J40: PR | K40: 45988 | L40: BALDE | M40: J A MACAMBIRA LTDA | N40: 18001672000187 | O40: 6004.47 | P40: 6004.47 | Q40: 59273.97 | R40: 45169.42 | S40: ACORDO IMPLANTADO | T40: 256359041 | U40: 45989 | X40: Campanha mês | Y40: B-SEM CAMPANHA | Z40: SIM | AA40: NÃO | AB40: NORTE | AC40: Multicanalidade | AH40: SEM ALÇADA | AI40: 0 | AJ40: 0.8987 | AK40: 0.9 | AL40: WELLER FERREIRA | AM40: AC | AO40: NÃO | AP40: QUITAÇÃO | AQ40: QUITAÇÃO | AS40: QUITAÇÃO | AV40: Ação de execução | AW40: Positiva | AX40: Não realizado | BB40: SIM | BC40: GERADOR FOTOVOLTAICO | BG40: 45992 | BH40: Cecília Sousa
A41: 2025 | B41: 46003 | C41: 45988 | D41: 45988 | E41: Massificado PJ | F41: RICARDO SOUZA | G41: Viana Peixoto Advogados Associados | H41: PJ | I41: EMPRESAS 1 | J41: PR | K41: 45988 | L41: BALDE | M41: TOP CAR SERVICOS AUTOMOTIVOS LTDA | N41: 23156679000108 | O41: 5000 | P41: 67186.63 | Q41: 223955.42 | R41: 187504.83 | S41: PROPOSTA EXPURGADA | T41: 256207024 | U41: 45996 | V41: 46008 | X41: Campanha mês | Y41: B-SEM CAMPANHA | Z41: NÃO | AA41: NÃO | AB41: CENTRO_OESTE | AC41: Telefone | AH41: 90 | AI41: 0.0112 | AJ41: 0.7 | AK41: 0.9 | AL41: RENATO SOUSA | AM41: MS | AO41: NÃO | AP41: 26 | AQ41: 2874.96 | AS41: 46027 | BB41: NÃO | BH41: Cecília Sousa
A42: 2025 | B42: 46003 | C42: 45988 | D42: 45988 | E42: Massificado PF | F42: BRUNO MONTEIRO | G42: Viana Peixoto Advogados Associados | H42: PF | I42: PESSOA FÍSICA | J42: PR | K42: 45988 | L42: BALDE | M42: GUSTAVO FREDERICO DAVID PINTO DE CARVALH | N42: 83733540182 | O42: 1248.6 | P42: 31214.97 | Q42: 124859.87 | R42: 111579.11 | S42: PROPOSTA EXPURGADA | T42: 256210693 | U42: 45996 | V42: 45994 | X42: Campanha mês | Y42: CAMPANHA PRE APROVADO C2 | Z42: NÃO | AA42: NÃO | AB42: CENTRO_OESTE | AC42: Telefone | AH42: SEM ALÇADA | AI42: 0 | AJ42: 0.75 | AK42: 0.9 | AL42: CAMILA PINTO | AM42: DF | AO42: NÃO | AP42: 24 | AQ42: 1348.95 | AS42: 46027 | BB42: NÃO | BH42: Cecília Sousa
A43: 2025 | B43: 46003 | C43: 45988 | D43: 45988 | E43: E2 - Baixo Ticket | F43: ANDREZA SOUZA | G43: Viana Peixoto Advogados Associados | H43: PJ | I43: EMPRESAS 2 | J43: CV | K43: 45988 | L43: BALDE | M43: L L DE ARAUJO SOLUCOES EM NEGOCIOS LTDA | N43: 41723815000186 | O43: 3000 | P43: 85528.49 | Q43: 92965.75 | R43: 92321.9 | S43: ACORDO IMPLANTADO | T43: 256217881 | U43: 45989 | X43: Campanha mês | Y43: B-SEM CAMPANHA | Z43: NÃO | AA43: NÃO | AB43: CENTRO_OESTE | AC43: Multicanalidade | AH43: 90 | AI43: 0.0112 | AJ43: 0.08 | AK43: 0.9 | AL43: MICHAELLI DO CARMO | AM43: MS | AO43: NÃO | AP43: 86 | AQ43: 1518.17 | AS43: 46018 | BB43: NÃO | BG43: 45996 | BH43: Cecília Sousa
A44: 2025 | B44: 46003 | C44: 45988 | D44: 45988 | E44: Massificado PF | F44: BRUNO MONTEIRO | G44: Viana Peixoto Advogados Associados | H44: PF | I44: PESSOA FÍSICA | J44: PR | K44: 45988 | L44: BALDE | M44: ANTONIO ALVES DE LIMA | N44: 12421933838 | O44: 5001.08 | P44: 5001.08 | Q44: 19033.42 | R44: 10667.1 | S44: PROMESSA DE PAGAMENTO | T44: 256207402 | U44: 46001 | X44: Campanha mês | Y44: B-SEM CAMPANHA | Z44: NÃO | AA44: NÃO | AB44: NORTE | AC44: Telefone | AH44: SEM ALÇADA | AI44: 0 | AJ44: 0.7372 | AK44: 0.9 | AL44: FELIPE CORREIA | AM44: CE | AO44: NÃO | AP44: QUITAÇÃO | AQ44: QUITAÇÃO | AS44: QUITAÇÃO | BB44: NÃO | BH44: Hillary Cavalcanti
A45: 2025 | B45: 46003 | C45: 45988 | D45: 45988 | E45: Massificado PJ | F45: RICARDO SOUZA | G45: Viana Peixoto Advogados Associados | H45: PJ | I45: EMPRESAS 1 | J45: PR | K45: 45988 | L45: BALDE | M45: S J DOS PASSOS JUNIOR | N45: 1859930000168 | O45: 11814.71 | P45: 11814.71 | Q45: 122817.49 | R45: 90991.7 | S45: PROPOSTA EXPURGADA | T45: 256211529 | U45: 45988 | V45: 45994 | X45: Campanha mês | Y45: B-SEM CAMPANHA | Z45: SIM | AA45: NÃO | AB45: NORTE | AC45: Multicanalidade | AH45: SEM ALÇADA | AI45: 0 | AJ45: 0.9037 | AK45: 0.9 | AL45: JAQUELINE MAGALHAES | AM45: MA | AO45: NÃO | AP45: QUITAÇÃO | AQ45: QUITAÇÃO | AS45: QUITAÇÃO | AV45: Ação busca e apreensão. | AW45: Positiva | AX45: Não realizado | BB45: SIM | BC45: VEICULO | BH45: Cecília Sousa
A46: 2025 | B46: 46003 | C46: 45988 | D46: 45988 | E46: Massificado PJ | F46: RICARDO SOUZA | G46: Viana Peixoto Advogados Associados | H46: PJ | I46: EMPRESAS 1 | J46: PR | K46: 45988 | L46: BALDE | M46: DISTRIBUIDORA DE BEBIDAS PONTO DA LATA L | N46: 45584668000161 | O46: 4090.57 | P46: 4090.57 | Q46: 33613.15 | R46: 14178.84 | S46: ACORDO IMPLANTADO | T46: 256416012 | U46: 46000 | X46: Campanha mês | Y46: B-SEM CAMPANHA | Z46: NÃO | AA46: NÃO | AB46: NORDESTE | AC46: Multicanalidade | AH46: SEM ALÇADA | AI46: 0 | AJ46: 0.8783 | AK46: 0.9 | AL46: FRANCISCA ROSANGELA | AM46: BA | AO46: NÃO | AP46: QUITAÇÃO | AQ46: QUITAÇÃO | AS46: QUITAÇÃO | BB46: SIM | BC46: VEICULO | BG46: 46000 | BH46: Cecília Sousa
A47: 2025 | B47: 46003 | C47: 45988 | D47: 45988 | E47: Massificado PJ | F47: RICARDO SOUZA | G47: Viana Peixoto Advogados Associados | H47: PJ | I47: EMPRESAS 1 | J47: PR | K47: 45988 | L47: BALDE | M47: MERC AKITUDO LTDA | N47: 24269901000141 | O47: 2000 | P47: 27925.73 | Q47: 93232.39 | R47: 45260.16 | S47: PROPOSTA EXPURGADA | T47: 256210432 | U47: 45989 | V47: 46001 | X47: Campanha mês | Y47: B-SEM CAMPANHA | Z47: SIM | AA47: NÃO | AB47: NORDESTE | AC47: Multicanalidade | AH47: 90 | AI47: 0.0112 | AJ47: 0.7005 | AK47: 0.9 | AL47: SAMARA SOARES | AM47: BA | AO47: NÃO | AP47: 25 | AQ47: 1237.96 | AS47: 46018 | AV47: Ação busca e apreensão. | AW47: Positiva | AX47: Não realizado | BB47: SIM | BC47: VEICULO | BH47: Cecília Sousa
A48: 2025 | B48: 46003 | C48: 45988 | D48: 45988 | E48: Massificado PJ | F48: RICARDO SOUZA | G48: Viana Peixoto Advogados Associados | H48: PJ | I48: EMPRESAS 1 | J48: PR | K48: 45988 | L48: BALDE | M48: ALEXEI RIBEIRO COSTA | N48: 12344544000150 | O48: 1000 | P48: 29081.85 | Q48: 238435.54 | R48: 207086.77 | S48: PROPOSTA EXPURGADA | T48: 256210175 | U48: 45993 | V48: 46003 | X48: Campanha mês | Y48: B-SEM CAMPANHA | Z48: SIM | AA48: NÃO | AB48: CENTRO_OESTE | AC48: Telefone | AH48: 90 | AI48: 0.0112 | AJ48: 0.878 | AK48: 0.9 | AL48: RENATO SOUSA | AM48: GO | AO48: NÃO | AP48: 35 | AQ48: 999.63 | AS48: 46024 | AV48: Ação de execução | AW48: Positiva | AX48: Não realizado | BB48: NÃO | BH48: Cecília Sousa
A49: 2025 | B49: 46003 | C49: 45988 | D49: 45988 | E49: Massificado PF | F49: BRUNO MONTEIRO | G49: Viana Peixoto Advogados Associados | H49: PF | I49: PESSOA FÍSICA | J49: PR | K49: 45988 | L49: BALDE | M49: MARIA ZILNEIDE DAMASCENO FELISBERTO | N49: 18484700100 | O49: 610.76 | P49: 610.76 | Q49: 10179.34 | R49: 6611.63 | S49: PROPOSTA EXPURGADA | T49: 256067498 | U49: 45993 | V49: 46003 | X49: Campanha mês | Y49: CAMPANHA PRE APROVADO C2 | Z49: NÃO | AA49: NÃO | AB49: NORTE | AC49: Telefone | AH49: SEM ALÇADA | AI49: 0 | AJ49: 0.94 | AK49: 0.9 | AL49: CAMILA PINTO | AM49: RO | AO49: NÃO | AP49: QUITAÇÃO | AQ49: QUITAÇÃO | AS49: QUITAÇÃO | BB49: NÃO | BH49: Hillary Cavalcanti
A50: 2025 | B50: 46003 | C50: 45988 | D50: 45988 | E50: Massificado PF | F50: BRUNO MONTEIRO | G50: Viana Peixoto Advogados Associados | H50: PF | I50: PESSOA FÍSICA | J50: PR | K50: 45988 | L50: BALDE | M50: JOSIMALIA CAVALCANTE ROCHA | N50: 20797397353 | O50: 7960.4 | P50: 7960.4 | Q50: 132597.22 | R50: 115168.24 | S50: ACORDO IMPLANTADO | T50: 256067310 | U50: 45994 | X50: Campanha mês | Y50: CAMPANHA PRE APROVADO C2 | Z50: NÃO | AA50: NÃO | AB50: NORTE | AC50: Multicanalidade | AH50: SEM ALÇADA | AI50: 0 | AJ50: 0.94 | AK50: 0.9 | AL50: SARAH SALES | AM50: PI | AO50: NÃO | AP50: QUITAÇÃO | AQ50: QUITAÇÃO | AS50: QUITAÇÃO | BB50: NÃO | BG50: 45992 | BH50: Hillary Cavalcanti
A51: 2025 | B51: 46003 | C51: 45988 | D51: 45988 | E51: Massificado PF | F51: BRUNO MONTEIRO | G51: Viana Peixoto Advogados Associados | H51: PF | I51: PESSOA FÍSICA | J51: PR | K51: 45988 | L51: BALDE | M51: EDINOLIA DOS SANTOS COSTA | N51: 91346479534 | O51: 3353.78 | P51: 3353.78 | Q51: 67075.72 | R51: 52481.95 | S51: PROPOSTA EXPURGADA | T51: 256136157 | U51: 45996 | V51: 46008 | X51: Campanha mês | Y51: CAMPANHA PRE APROVADO C2 | Z51: NÃO | AA51: NÃO | AB51: NORDESTE | AC51: Multicanalidade | AH51: SEM ALÇADA | AI51: 0 | AJ51: 0.95 | AK51: 0.9 | AL51: FRANCISCA JOCILANE | AM51: BA | AO51: NÃO | AP51: QUITAÇÃO | AQ51: QUITAÇÃO | AS51: QUITAÇÃO | BB51: NÃO | BH51: Hillary Cavalcanti
A52: 2025 | B52: 46003 | C52: 45988 | D52: 45988 | E52: Massificado PJ | F52: RICARDO SOUZA | G52: Viana Peixoto Advogados Associados | H52: PJ | I52: EMPRESAS 1 | J52: PR | K52: 45988 | L52: BALDE | M52: CARLOS ROBERTO MARTINS MAGALHAES FILHO L | N52: 6538824000104 | O52: 16045.76 | P52: 16045.76 | Q52: 267425.38 | R52: 162752.33 | S52: PROPOSTA EXPURGADA | T52: 256061385 | U52: 45989 | V52: 45994 | X52: Campanha mês | Y52: CAMPANHA PRE APROVADO C2 | Z52: SIM | AA52: NÃO | AB52: NORTE | AC52: Multicanalidade | AH52: SEM ALÇADA | AI52: 0 | AJ52: 0.94 | AK52: 0.9 | AL52: FRANCISCA ROSANGELA | AM52: CE | AO52: NÃO | AP52: QUITAÇÃO | AQ52: QUITAÇÃO | AS52: QUITAÇÃO | BB52: NÃO | BH52: Matheus Leão
A53: 2025 | B53: 46003 | C53: 45989 | D53: 45994 | E53: Alto Ticket | F53: BRUNO MONTEIRO | G53: Viana Peixoto Advogados Associados | H53: PF | I53: PESSOA FÍSICA | J53: PR | K53: 45989 | L53: BALDE | M53: PAULO SERGIO PEREIRA FRANCO | N53: 93951523549 | O53: 29499.99 | P53: 50292.79 | Q53: 295839.89 | R53: 207175.03 | S53: ACORDO IMPLANTADO | T53: 256425595 | U53: 45999 | W53: Alto Ticket | X53: Campanha mês | Y53: B-SEM CAMPANHA | Z53: SIM | AA53: NÃO | AB53: NORDESTE | AC53: Multicanalidade | AH53: FORMULARIO | AI53: 0.0112 | AJ53: 0.834 | AK53: 0.9 | AL53: MICHELE GUIMARAES | AM53: BA | AO53: NÃO | AP53: 33 | AQ53: 780.27 | AS53: 46030 | AV53: Ação Monitória | AW53: Positiva | AX53: Realizado | AY53: Efeitos Negativos | BB53: NÃO | BG53: 45999 | BH53: Cecília Sousa
A54: 2025 | B54: 46003 | C54: 45989 | D54: 45989 | E54: Massificado PF | F54: BRUNO MONTEIRO | G54: Viana Peixoto Advogados Associados | H54: PF | I54: PESSOA FÍSICA | J54: PR | K54: 45989 | L54: BALDE | M54: ANNIEL DA SILVA NEGREIROS | N54: 91416485368 | O54: 25000.85 | P54: 25000.85 | Q54: 164611.28 | R54: 53776.29 | S54: ACORDO IMPLANTADO | T54: 256106529 | U54: 45996 | X54: Campanha mês | Y54: B-SEM CAMPANHA | Z54: SIM | AA54: NÃO | AB54: NORTE | AC54: Multicanalidade | AH54: 90 | AI54: 0 | AJ54: 0.8481 | AK54: 0.9 | AL54: MAIRLE SILVA | AM54: CE | AO54: NÃO | AP54: QUITAÇÃO | AQ54: QUITAÇÃO | AS54: QUITAÇÃO | AV54: Ação Monitória | AW54: Positiva | AX54: Realizado | AY54: Positivo | BB54: NÃO | BG54: 45994 | BH54: Hillary Cavalcanti
A55: 2025 | B55: 46003 | C55: 45989 | D55: 45989 | E55: E2 - Baixo Ticket | F55: ANDREZA SOUZA | G55: Viana Peixoto Advogados Associados | H55: PJ | I55: EMPRESAS 2 | J55: PR | K55: 45989 | L55: BALDE | M55: ENTERCOMPANY SERVICOS EM TECNOLOGIA DA I | N55: 2950570000178 | O55: 30078.75 | P55: 766029.33 | Q55: 960744.66 | R55: 111139.75 | S55: PROMESSA DE PAGAMENTO | T55: 256425254 | U55: 46001 | X55: Campanha mês | Y55: PRODUTOS GOVERNAMENTAIS | Z55: NÃO | AA55: NÃO | AB55: CENTRO_OESTE | AC55: Multicanalidade | AH55: FORMULARIO | AI55: 0.0115 | AJ55: 0.2027 | AK55: 0.9 | AL55: SAMARA SOARES | AM55: DF | AO55: NÃO | AP55: 41 | AQ55: 23033.85 | AS55: 46032 | BB55: NÃO | BH55: Cecília Sousa
A56: 2025 | B56: 46003 | C56: 45989 | D56: 45989 | E56: E2 - Baixo Ticket | F56: ANDREZA SOUZA | G56: Viana Peixoto Advogados Associados | H56: PJ | I56: EMPRESAS 2 | J56: PR | K56: 45989 | L56: BALDE | M56: TRES MARIAS TURISMO LTDA | N56: 7512792000122 | O56: 3001.91 | P56: 69375.62 | Q56: 81106.67 | R56: 18732.54 | S56: ACORDO IMPLANTADO | T56: 256369699 | U56: 45993 | X56: Campanha mês | Y56: PRODUTOS GOVERNAMENTAIS | Z56: NÃO | AA56: NÃO | AB56: NORDESTE | AC56: Multicanalidade | AH56: FORMULARIO | AI56: 0.0049 | AJ56: 0.1446 | AK56: 0.9 | AL56: SAMARA SOARES | AM56: BA | AO56: NÃO | AP56: 51 | AQ56: 1499.22 | AS56: 45667 | BB56: NÃO | BG56: 45993 | BH56: Cecília Sousa
A57: 2025 | B57: 46003 | C57: 45989 | D57: 45989 | E57: E2 - Baixo Ticket | F57: ANDREZA SOUZA | G57: Viana Peixoto Advogados Associados | H57: PJ | I57: EMPRESAS 2 | J57: PR | K57: 45989 | L57: BALDE | M57: TRES MARIAS TURISMO LTDA | N57: 7512792000122 | O57: 5209.97 | P57: 5209.97 | Q57: 34733.19 | R57: 28205.78 | S57: ACORDO IMPLANTADO | T57: 256350058 | U57: 45999 | X57: Campanha mês | Y57: B-SEM CAMPANHA | Z57: NÃO | AA57: NÃO | AB57: NORDESTE | AC57: Multicanalidade | AH57: SEM ALÇADA | AI57: 0 | AJ57: 0.85 | AK57: 0.9 | AL57: SAMARA SOARES | AM57: BA | AO57: NÃO | AP57: QUITAÇÃO | AQ57: QUITAÇÃO | AS57: QUITAÇÃO | BB57: NÃO | BG57: 45995 | BH57: Cecília Sousa
A58: 2025 | B58: 46003 | C58: 45989 | D58: 45989 | E58: Massificado PF | F58: BRUNO MONTEIRO | G58: Viana Peixoto Advogados Associados | H58: PF | I58: PESSOA FÍSICA | J58: PR | K58: 45989 | L58: BALDE | M58: JOSE ALBERTO DOS SANTOS MACIEL | N58: 70911355200 | O58: 1348.48 | P58: 21575.68 | Q58: 269695.99 | R58: 125440.97 | S58: ACORDO IMPLANTADO | T58: 256349092 | U58: 46002 | X58: Campanha mês | Y58: CAMPANHA PRE APROVADO C2 | Z58: NÃO | AA58: NÃO | AB58: NORTE | AC58: Multicanalidade | AH58: SEM ALÇADA | AI58: 0 | AJ58: 0.92 | AK58: 0.9 | AL58: FRANCISCA JOCILANE | AM58: PA | AO58: NÃO | AP58: 48 | AQ58: 430.37 | AS58: 46036 | BB58: NÃO | BG58: 45999 | BH58: Hillary Cavalcanti
A59: 2025 | B59: 46003 | C59: 45989 | D59: 45989 | E59: Massificado PF | F59: BRUNO MONTEIRO | G59: Viana Peixoto Advogados Associados | H59: PF | I59: PESSOA FÍSICA | J59: PR | K59: 45989 | L59: BALDE | M59: JOANA KAFYA MAXIMO MARTINS | N59: 5248068371 | O59: 7902.86 | P59: 7902.86 | Q59: 131714.19 | R59: 102899.35 | S59: PROMESSA DE PAGAMENTO | T59: 256353765 | U59: 46001 | X59: Campanha mês | Y59: CAMPANHA PRE APROVADO C2 | Z59: NÃO | AA59: NÃO | AB59: NORTE | AC59: Multicanalidade | AH59: SEM ALÇADA | AI59: 0 | AJ59: 0.94 | AK59: 0.9 | AL59: FRANCISCA JOCILANE | AM59: CE | AO59: NÃO | AP59: QUITAÇÃO | AQ59: QUITAÇÃO | AS59: QUITAÇÃO | BB59: NÃO | BH59: Hillary Cavalcanti
A60: 2025 | B60: 46003 | C60: 45989 | D60: 45989 | E60: E2 - Baixo Ticket | F60: ANDREZA SOUZA | G60: Viana Peixoto Advogados Associados | H60: PJ | I60: EMPRESAS 2 | J60: PR | K60: 45989 | L60: BALDE | M60: DISTRIBUIDORA DE BEBIDAS PEZAO LTDA | N60: 29680467000101 | O60: 7058.39 | P60: 7058.39 | Q60: 235279.68 | R60: 131440.47 | S60: ACORDO IMPLANTADO | T60: 256351059 | U60: 45999 | X60: Campanha mês | Y60: CAMPANHA PRE APROVADO C2 | Z60: NÃO | AA60: NÃO | AB60: CENTRO_OESTE | AC60: Telefone | AH60: SEM ALÇADA | AI60: 0 | AJ60: 0.97 | AK60: 0.9 | AL60: SABRINA ERLLEN | AM60: DF | AO60: NÃO | AP60: QUITAÇÃO | AQ60: QUITAÇÃO | AS60: QUITAÇÃO | BB60: NÃO | BG60: 45994 | BH60: Cecília Sousa
A61: 2025 | B61: 46003 | C61: 45989 | D61: 45989 | E61: Massificado PJ | F61: RICARDO SOUZA | G61: Viana Peixoto Advogados Associados | H61: PJ | I61: EMPRESAS 1 | J61: PR | K61: 45989 | L61: BALDE | M61: HELIANE GOMES DE OLIVEIRA ME | N61: 70154703000150 | O61: 999.99 | P61: 37999.38 | Q61: 108569.62 | R61: 29859.52 | S61: ACORDO IMPLANTADO | T61: 256038563 | U61: 45989 | X61: Campanha mês | Y61: B-SEM CAMPANHA | Z61: SIM | AA61: NÃO | AB61: NORDESTE | AC61: Telefone | AH61: 90 | AI61: 0.0112 | AJ61: 0.65 | AK61: 0.9 | AL61: JAQUELINE MAGALHAES | AM61: RN | AO61: NÃO | AP61: 79 | AQ61: 714.65 | AS61: 46019 | AV61: Ação busca e apreensão. | AW61: Positiva | AX61: Não realizado | BB61: SIM | BC61: VEICULO | BG61: 45994 | BH61: Cecília Sousa
A62: 2025 | B62: 46003 | C62: 45989 | E62: Massificado PJ | F62: RICARDO SOUZA | G62: Viana Peixoto Advogados Associados | H62: PJ | I62: EMPRESAS 1 | J62: PR | K62: 45989 | L62: BALDE | M62: EDILSON DE OLIVEIRA BRITO ME | N62: 8519014000128 | O62: 2000 | P62: 65900.36 | Q62: 439335.54 | R62: 303877.28 | S62: PROPOSTA NEGADA | T62: 256355656 | U62: 45989 | X62: Campanha mês | Y62: B-SEM CAMPANHA | Z62: SIM | AA62: NÃO | AB62: NORTE | AC62: Multicanalidade | AG62: Majorar para 123k | AH62: 90 | AI62: 0.0112 | AJ62: 0.85 | AK62: 0.9 | AL62: AMANDA DA SILVA | AM62: PI | AO62: NÃO | AP62: 76 | AQ62: 1263.95 | AS62: 46019 | AV62: Ação busca e apreensão. | AW62: Positiva | AX62: Não realizado | BB62: SIM | BC62: VEICULO | BH62: Cecília Sousa
A63: 2025 | B63: 46003 | C63: 45989 | D63: 45989 | E63: Massificado PJ | F63: RICARDO SOUZA | G63: Viana Peixoto Advogados Associados | H63: PJ | I63: EMPRESAS 1 | J63: CV | K63: 45989 | L63: BALDE | M63: BOI NA BRASA CASA DE CARNES & CONVENIENC | N63: 10359810000273 | O63: 3000 | P63: 167651.73 | Q63: 186383.27 | R63: 39092.53 | S63: PROPOSTA EXPURGADA | T63: 256364770 | U63: 45989 | V63: 46001 | X63: Campanha mês | Y63: PRODUTOS GOVERNAMENTAIS | Z63: NÃO | AA63: NÃO | AB63: CENTRO_OESTE | AC63: Multicanalidade | AH63: FORMULARIO | AI63: 0.0049 | AJ63: 0.1005 | AK63: 0.9 | AL63: JAQUELINE MAGALHAES | AM63: MS | AO63: NÃO | AP63: 61 | AQ63: 3174 | AS63: 46019 | BB63: NÃO | BH63: Matheus Leão
A64: 2025 | B64: 46003 | C64: 45989 | D64: 45992 | E64: Massificado PJ | F64: RICARDO SOUZA | G64: Viana Peixoto Advogados Associados | H64: PJ | I64: EMPRESAS 1 | J64: CV | K64: 45989 | L64: BALDE | M64: C A DE SOUZA COMERCIO E REPRESENTACAO LT | N64: 29466322000102 | O64: 4999.99 | P64: 52753.81 | Q64: 70338.41 | R64: 68425.39 | S64: ACORDO IMPLANTADO | T64: 256356882 | U64: 45996 | X64: Campanha mês | Y64: B-SEM CAMPANHA | Z64: NÃO | AA64: NÃO | AB64: NORTE | AC64: Multicanalidade | AH64: 90 | AI64: 0.0112 | AJ64: 0.25 | AK64: 0.9 | AL64: WELLER FERREIRA | AM64: PA | AO64: NÃO | AP64: 37 | AQ64: 1623.81 | AS64: 46027 | BB64: NÃO | BG64: 46001 | BH64: Cecília Sousa
A65: 2025 | B65: 46003 | C65: 45989 | D65: 45989 | E65: E2 - Baixo Ticket | F65: ANDREZA SOUZA | G65: Viana Peixoto Advogados Associados | H65: PJ | I65: EMPRESAS 2 | J65: CV | K65: 45989 | L65: BALDE | M65: L DA F VIANA LTDA | N65: 49530978000154 | O65: 2999.99 | P65: 137241.01 | Q65: 137241.01 | R65: 134287.33 | S65: ACORDO IMPLANTADO | T65: 256360710 | U65: 45996 | X65: Campanha mês | Y65: B-SEM CAMPANHA | Z65: NÃO | AA65: NÃO | AB65: NORTE | AC65: Multicanalidade | AH65: SEM ALÇADA | AI65: 0.0112 | AJ65: 0 | AK65: 0.9 | AL65: SAMARA SOARES | AM65: AM | AO65: NÃO | AP65: 61 | AQ65: 3092.92 | AS65: 46027 | BB65: NÃO | BG65: 46007 | BH65: Cecília Sousa
A66: 2025 | B66: 46003 | C66: 45989 | D66: 45989 | E66: Massificado PJ | F66: RICARDO SOUZA | G66: Viana Peixoto Advogados Associados | H66: PJ | I66: EMPRESAS 1 | J66: PR | K66: 45989 | L66: BALDE | M66: POUSADA RIO DAS LUZES LTDA | N66: 22906855000119 | O66: 6004.11 | P66: 6004.11 | Q66: 31235.49 | R66: 25959.89 | S66: ACORDO IMPLANTADO | T66: 256362831 | U66: 45989 | X66: Campanha mês | Y66: B-SEM CAMPANHA | Z66: NÃO | AA66: NÃO | AB66: CENTRO_OESTE | AC66: Multicanalidade | AH66: SEM ALÇADA | AI66: 0 | AJ66: 0.8078 | AK66: 0.9 | AL66: FRANCISCO CLEONTE | AM66: MT | AO66: NÃO | AP66: QUITAÇÃO | AQ66: QUITAÇÃO | AS66: QUITAÇÃO | BB66: SIM | BC66: GERADOR FOTOVOLTAICO | BG66: 45999 | BH66: Cecília Sousa
A67: 2025 | B67: 46003 | C67: 45989 | D67: 45989 | E67: Massificado PJ | F67: RICARDO SOUZA | G67: Viana Peixoto Advogados Associados | H67: PJ | I67: EMPRESAS 1 | J67: PR | K67: 45989 | L67: BALDE | M67: JOANA DARC MORAIS VERAS E SILVA | N67: 9006582000198 | O67: 20000.03 | P67: 20000.03 | Q67: 646784.57 | R67: 140447.96 | S67: ACORDO IMPLANTADO | T67: 256387122 | U67: 45992 | W67: Alto Impacto | X67: Campanha mês | Y67: B-SEM CAMPANHA | Z67: SIM | AA67: SIM | AB67: NORDESTE | AC67: Multicanalidade | AH67: 90 | AI67: 0 | AJ67: 0.9691 | AK67: 0.9 | AL67: JAQUELINE MAGALHAES | AM67: PE | AO67: NÃO | AP67: QUITAÇÃO | AQ67: QUITAÇÃO | AS67: QUITAÇÃO | AV67: Ação de execução | AW67: Positiva | AX67: Não realizado | BB67: NÃO | BG67: 45992 | BH67: Cecília Sousa
A68: 2025 | B68: 46003 | C68: 45992 | D68: 45992 | E68: Massificado PJ | F68: RICARDO SOUZA | G68: Viana Peixoto Advogados Associados | H68: PJ | I68: EMPRESAS 1 | J68: PR | K68: 45992 | L68: 1 | M68: ESTRELA DALVA GRANJA LTDA ME | N68: 39775904000124 | O68: 24955.58 | P68: 24955.58 | Q68: 166370.51 | R68: 91663.08 | S68: ACORDO IMPLANTADO | T68: 256391626 | U68: 46000 | X68: Campanha mês | Y68: CAMPANHA PRE APROVADO C2 | Z68: NÃO | AA68: NÃO | AB68: CENTRO_OESTE | AC68: Multicanalidade | AH68: SEM ALÇADA | AI68: 0 | AJ68: 0.85 | AK68: 0.9 | AL68: FRANCISCA ROSANGELA | AM68: MT | AO68: NÃO | AP68: QUITAÇÃO | AQ68: QUITAÇÃO | AS68: QUITAÇÃO | BB68: NÃO | BG68: 45999 | BH68: Cecília Sousa
A69: 2025 | B69: 46003 | C69: 45992 | D69: 45992 | E69: Massificado PF | F69: BRUNO MONTEIRO | G69: Viana Peixoto Advogados Associados | H69: PF | I69: PESSOA FÍSICA | J69: PR | K69: 45992 | L69: 1 | M69: CICERO MENDES CARDOSO | N69: 17785103 | O69: 28215.94 | P69: 28215.94 | Q69: 235132.84 | R69: 195703.88 | S69: ACORDO IMPLANTADO | T69: 256388541 | U69: 45994 | X69: Campanha mês | Y69: CAMPANHA PRE APROVADO C2 | Z69: NÃO | AA69: NÃO | AB69: CENTRO_OESTE | AC69: Multicanalidade | AH69: SEM ALÇADA | AI69: 0 | AJ69: 0.88 | AK69: 0.9 | AL69: SARAH SALES | AM69: DF | AO69: NÃO | AP69: QUITAÇÃO | AQ69: QUITAÇÃO | AS69: QUITAÇÃO | BB69: NÃO | BG69: 45992 | BH69: Cecília Sousa
A70: 2025 | B70: 46003 | C70: 45992 | D70: 45992 | E70: Massificado PJ | F70: RICARDO SOUZA | G70: Viana Peixoto Advogados Associados | H70: PJ | I70: EMPRESAS 1 | J70: CV | K70: 45992 | L70: 1 | M70: L S DO NASCIMENTO SERVICOS | N70: 19424170000121 | O70: 499.99 | P70: 8144.76 | Q70: 8144.76 | R70: 8109.14 | S70: ACORDO IMPLANTADO | T70: 256388026 | U70: 46001 | X70: Campanha mês | Y70: CAMPANHA PRE APROVADO C2 | Z70: NÃO | AA70: NÃO | AB70: NORDESTE | AC70: Telefone | AH70: SEM ALÇADA | AI70: 0.0112 | AJ70: 0 | AK70: 0.9 | AL70: RENATO SOUSA | AM70: AL | AO70: NÃO | AP70: 16 | AQ70: 568.67 | AS70: 46032 | BB70: NÃO | BG70: 46000 | BH70: Hillary Cavalcanti
A71: 2025 | B71: 46003 | C71: 45992 | D71: 45995 | E71: Massificado PJ | F71: RICARDO SOUZA | G71: Viana Peixoto Advogados Associados | H71: PJ | I71: EMPRESAS 1 | J71: CV | K71: 45992 | L71: 1 | M71: RILDO DE OLIVEIRA CRESCENCIO | N71: 16560036000160 | O71: 2000 | P71: 62047.81 | Q71: 69113.58 | R71: 15524.47 | S71: ACORDO IMPLANTADO | T71: 256464556 | U71: 45996 | X71: Campanha mês | Y71: PRODUTOS GOVERNAMENTAIS | Z71: NÃO | AA71: NÃO | AB71: NORDESTE | AC71: Multicanalidade | AH71: FORMULARIO | AI71: 0.0049 | AJ71: 0.1022 | AK71: 0.9 | AL71: LUCAS SILVA | AM71: BA | AO71: NÃO | AP71: 51 | AQ71: 1357 | AS71: 46027 | BB71: NÃO | BG71: 45999 | BH71: Cecília Sousa
A72: 2025 | B72: 46003 | C72: 45992 | D72: 45992 | E72: Massificado PF | F72: BRUNO MONTEIRO | G72: Viana Peixoto Advogados Associados | H72: PF | I72: PESSOA FÍSICA | J72: PR | K72: 45992 | L72: 1 | M72: FABIO SANTOS DE MIRANDA | N72: 89131622291 | O72: 8091.65 | P72: 8091.65 | Q72: 134860.78 | R72: 119717.82 | S72: ACORDO IMPLANTADO | T72: 256388207 | U72: 45994 | X72: Campanha mês | Y72: CAMPANHA PRE APROVADO C2 | Z72: NÃO | AA72: NÃO | AB72: NORTE | AC72: Multicanalidade | AH72: SEM ALÇADA | AI72: 0 | AJ72: 0.94 | AK72: 0.9 | AL72: FELIPE CORREIA | AM72: PA | AO72: NÃO | AP72: QUITAÇÃO | AQ72: QUITAÇÃO | AS72: QUITAÇÃO | BB72: NÃO | BG72: 45994 | BH72: Hillary Cavalcanti
A73: 2025 | B73: 46003 | C73: 45992 | D73: 45992 | E73: E2 - Baixo Ticket | F73: ANDREZA SOUZA | G73: Viana Peixoto Advogados Associados | H73: PJ | I73: EMPRESAS 2 | J73: PR | K73: 45992 | L73: 1 | M73: MISTER ROGER COMERCIO DE GAS LTDA | N73: 19433269000190 | O73: 10000.01 | P73: 10000.01 | Q73: 175879.88 | R73: 83479.35 | S73: ACORDO IMPLANTADO | T73: 256395041 | U73: 45996 | W73: Alto Impacto | X73: Campanha mês | Y73: B-SEM CAMPANHA | Z73: SIM | AA73: SIM | AB73: CENTRO_OESTE | AC73: Multicanalidade | AH73: 90 | AI73: 0 | AJ73: 0.9431 | AK73: 0.9 | AL73: SAMARA SOARES | AM73: MS | AO73: NÃO | AP73: QUITAÇÃO | AQ73: QUITAÇÃO | AS73: QUITAÇÃO | AV73: Ação de execução | AW73: Positiva | AX73: Realizado | AY73: Efeitos Negativos | BB73: NÃO | BG73: 45992 | BH73: Cecília Sousa
A74: 2025 | B74: 46003 | C74: 45992 | D74: 45992 | E74: E2 - Baixo Ticket | F74: ANDREZA SOUZA | G74: Viana Peixoto Advogados Associados | H74: PJ | I74: EMPRESAS 2 | J74: PR | K74: 45992 | L74: 1 | M74: JD & FILHOS LATICINIOS LTDA | N74: 14436375000103 | O74: 30000.49 | P74: 30000.49 | Q74: 559107.8 | R74: 399176.58 | S74: ACORDO IMPLANTADO | T74: 256388269 | U74: 45996 | W74: Alto Impacto | X74: Campanha mês | Y74: EVENTO REGIONAL - UF | Z74: SIM | AA74: SIM | AB74: NORDESTE | AC74: Multicanalidade | AH74: 90 | AI74: 0 | AJ74: 0.9463 | AK74: 0.9 | AL74: AMANDA DA SILVA | AM74: PE | AO74: NÃO | AP74: QUITAÇÃO | AQ74: QUITAÇÃO | AS74: QUITAÇÃO | AV74: Ação Monitória | AW74: Positiva | AX74: Realizado | AY74: Efeitos Negativos | BB74: SIM | BC74: GERADOR FOTOVOLTAICO | BG74: 45994 | BH74: Cecília Sousa
A75: 2025 | B75: 46003 | C75: 45992 | E75: Massificado PJ | F75: RICARDO SOUZA | G75: Viana Peixoto Advogados Associados | H75: PJ | I75: EMPRESAS 1 | J75: CV | K75: 45992 | L75: 1 | M75: VITAL GAS LTDA | N75: 1606141000115 | O75: 16000.42 | P75: 16000.42 | Q75: 152533.44 | R75: 137347.68 | S75: PROPOSTA NEGADA | T75: 256388412 | U75: 45994 | X75: Campanha mês | Y75: EVENTO REGIONAL - UF | Z75: NÃO | AA75: NÃO | AB75: NORTE | AC75: Multicanalidade | AG75: Negado, só em 1 operação. cliente deve 40 mil de valor principal. Podem seguir com o processo. | AH75: 90 | AI75: 0 | AJ75: 0.8987 | AK75: 0.9 | AL75: SAMARA SOARES | AM75: PA | AO75: NÃO | AP75: QUITAÇÃO | AQ75: QUITAÇÃO | AS75: QUITAÇÃO | BB75: NÃO | BH75: Cecília Sousa
A76: 2025 | B76: 46003 | C76: 45992 | D76: 45992 | E76: Massificado PF | F76: BRUNO MONTEIRO | G76: Viana Peixoto Advogados Associados | H76: PF | I76: PESSOA FÍSICA | J76: PR | K76: 45992 | L76: 1 | M76: ARGEMIRO PINHO DOS SANTOS | N76: 1161817530 | O76: 1157.47 | P76: 1157.47 | Q76: 14468.33 | R76: 929.15 | S76: PROPOSTA EXPURGADA | T76: 256389497 | U76: 45993 | V76: 46003 | X76: Campanha mês | Y76: CAMPANHA PRE APROVADO C2 | Z76: NÃO | AA76: NÃO | AB76: NORDESTE | AC76: Multicanalidade | AH76: SEM ALÇADA | AI76: 0 | AJ76: 0.92 | AK76: 0.9 | AL76: MAIRLE SILVA | AM76: BA | AO76: NÃO | AP76: QUITAÇÃO | AQ76: QUITAÇÃO | AS76: QUITAÇÃO | BB76: NÃO | BH76: Cecília Sousa
A77: 2025 | B77: 46003 | C77: 45992 | D77: 45992 | E77: E2 - Baixo Ticket | F77: ANDREZA SOUZA | G77: Viana Peixoto Advogados Associados | H77: PJ | I77: EMPRESAS 2 | J77: PR | K77: 45992 | L77: 1 | M77: K R NEGOCIO E IMOVEIS LTDA | N77: 46222224000149 | O77: 20973.37 | P77: 20973.37 | Q77: 202774.58 | R77: 173099.1 | S77: PROMESSA DE PAGAMENTO | T77: 256388260 | U77: 46003 | X77: Campanha mês | Y77: EVENTO REGIONAL - UF | Z77: SIM | AA77: NÃO | AB77: CENTRO_OESTE | AC77: Multicanalidade | AH77: 90 | AI77: 0 | AJ77: 0.9038 | AK77: 0.9 | AL77: SAMARA SOARES | AM77: GO | AO77: NÃO | AP77: QUITAÇÃO | AQ77: QUITAÇÃO | AS77: QUITAÇÃO | AV77: Ação Monitória | AW77: Positiva | AX77: Realizado | AY77: Efeitos Negativos | BB77: NÃO | BH77: Cecília Sousa
A78: 2025 | B78: 46003 | C78: 45992 | D78: 45992 | E78: Massificado PJ | F78: RICARDO SOUZA | G78: Viana Peixoto Advogados Associados | H78: PJ | I78: EMPRESAS 1 | J78: CV | K78: 45992 | L78: 1 | M78: ERICA MARIA DO NASCIMENTO | N78: 28296180000110 | O78: 2256.3 | P78: 2256.3 | Q78: 2256.3 | R78: 0 | S78: PROPOSTA EXPURGADA | T78: 256392039 | U78: 45994 | V78: 46006 | X78: Campanha mês | Y78: B-SEM CAMPANHA | Z78: NÃO | AA78: NÃO | AB78: NORDESTE | AC78: Telefone | AH78: SEM ALÇADA | AI78: 0 | AJ78: 0 | AK78: 0.9 | AL78: JOSE ADAILTON | AM78: AL | AO78: NÃO | AP78: QUITAÇÃO | AQ78: QUITAÇÃO | AS78: QUITAÇÃO | BB78: NÃO | BH78: Cecília Sousa
A79: 2025 | B79: 46003 | C79: 45992 | D79: 45993 | E79: E2 - Baixo Ticket | F79: ANDREZA SOUZA | G79: Viana Peixoto Advogados Associados | H79: PJ | I79: EMPRESAS 2 | J79: PR | K79: 45992 | L79: 1 | M79: ESCOLA ECCOS ME | N79: 2650915000178 | O79: 9499.97 | P79: 357452.53 | Q79: 871835.36 | R79: 293003.29 | S79: PROPOSTA EXPURGADA | T79: 256390885 | U79: 45999 | V79: 46009 | W79: Alto Impacto | X79: Campanha mês | Y79: EVENTO REGIONAL - UF | Z79: SIM | AA79: SIM | AB79: NORDESTE | AC79: Multicanalidade | AH79: 90 | AI79: 0.0112 | AJ79: 0.59 | AK79: 0.9 | AL79: SABRINA ERLLEN | AM79: BA | AO79: NÃO | AP79: 121 | AQ79: 5300.12 | AS79: 46025 | AV79: Ação Monitória | AW79: Positiva | AX79: Realizado | AY79: Efeitos Negativos | BB79: NÃO | BH79: Cecília Sousa
A80: 2025 | B80: 46003 | C80: 45992 | E80: Massificado PJ | F80: RICARDO SOUZA | G80: Viana Peixoto Advogados Associados | H80: PJ | I80: EMPRESAS 1 | J80: CV | K80: 45992 | L80: 1 | M80: FRANKSUELDER DE MORAES NASCIMENTO | N80: 26056381000114 | O80: 3000 | P80: 101939.26 | Q80: 357462.23 | R80: 290035.8 | S80: PROPOSTA NEGADA | T80: 256391429 | U80: 45996 | X80: Campanha mês | Y80: EVENTO REGIONAL - UF | Z80: SIM | AA80: NÃO | AB80: CENTRO_OESTE | AC80: Multicanalidade | AG80: Negado. Negociar dentro da alçada. | AH80: 90 | AI80: 0.0112 | AJ80: 0.7226 | AK80: 0.9 | AL80: RENATO SOUSA | AM80: MT | AO80: NÃO | AP80: 51 | AQ80: 2599.54 | AS80: 46027 | AV80: Ação de cobrança | AW80: Positiva | AX80: Realizado | AY80: Positivo | BB80: NÃO | BH80: Cecília Sousa
A81: 2025 | B81: 46003 | C81: 45992 | D81: 45994 | E81: Massificado PF | F81: BRUNO MONTEIRO | G81: Viana Peixoto Advogados Associados | H81: PF | I81: PESSOA FÍSICA | J81: PR | K81: 45992 | L81: 1 | M81: GILDICELIA DUTRA LOPES CASACCHI | N81: 2690823446 | O81: 22193.94 | P81: 22193.94 | Q81: 88568.58 | R81: 79109.74 | S81: PROMESSA DE PAGAMENTO | T81: 256399680 | U81: 46013 | X81: Campanha mês | Y81: EVENTO REGIONAL - UF | Z81: SIM | AA81: NÃO | AB81: NORDESTE | AC81: Multicanalidade | AH81: 90 | AI81: 0 | AJ81: 0.7516 | AK81: 0.9 | AL81: MICHELE GUIMARAES | AM81: RN | AO81: NÃO | AP81: QUITAÇÃO | AQ81: QUITAÇÃO | AS81: QUITAÇÃO | AV81: Ação busca e apreensão. | AW81: Positiva | AX81: Não realizado | BB81: SIM | BC81: GERADOR FOTOVOLTAICO | BH81: Cecília Sousa
A82: 2025 | B82: 46003 | C82: 45992 | E82: E2 - Baixo Ticket | F82: ANDREZA SOUZA | G82: Viana Peixoto Advogados Associados | H82: PJ | I82: EMPRESAS 2 | J82: CV | K82: 45992 | L82: 1 | M82: E SOUZA MASCARENHAS LTDA | N82: 35660726000135 | O82: 5000 | P82: 284483.81 | Q82: 406405.44 | R82: 396455.03 | S82: PROPOSTA NEGADA | T82: 256046526 | U82: 45996 | X82: Campanha mês | Y82: EVENTO REGIONAL - UF | Z82: SIM | AA82: NÃO | AB82: NORDESTE | AC82: Multicanalidade | AG82: Atraso curto e pouca evolução processual. A negociação deverá obedecer ao deságio previsto na carta de alçada. Cliente liquidou a operação de FINC de Veiculos em 25/11 e há um dossiê de BA. O acordo foi homologado? Vocês desistiram da ação? Qual bem estava em garantia? Conseguimos com o acordo, indicar esse veículo à penhora? | AH82: 90 | AI82: 0.0112 | AJ82: 0.3 | AK82: 0.9 | AL82: SAMARA SOARES | AM82: BA | AO82: NÃO | AP82: 86 | AQ82: 5157.28 | AS82: 45674 | AV82: Ação de execução | AW82: Positiva | AX82: Não realizado | BB82: NÃO | BH82: Hillary Cavalcanti
A83: 2025 | B83: 46003 | C83: 45992 | D83: 45992 | E83: E2 - Baixo Ticket | F83: ANDREZA SOUZA | G83: Viana Peixoto Advogados Associados | H83: PJ | I83: EMPRESAS 2 | J83: PR | K83: 45992 | L83: 1 | M83: SAO PAULO - PIZZA DELIVERY EIRELI | N83: 6179940000176 | O83: 2000 | P83: 32604.08 | Q83: 220297.78 | R83: 77755.3 | S83: ACORDO IMPLANTADO | T83: 256414158 | U83: 46000 | X83: Campanha mês | Y83: EVENTO REGIONAL - UF | Z83: SIM | AA83: NÃO | AB83: NORDESTE | AC83: Telefone | AH83: 90 | AI83: 0.0112 | AJ83: 0.852 | AK83: 0.9 | AL83: SAMARA SOARES | AM83: BA | AO83: NÃO | AP83: 13 | AQ83: 2747.39 | AS83: 46031 | AV83: Ação Monitória | AW83: Positiva | AX83: Realizado | AY83: Efeitos Negativos | BB83: NÃO | BG83: 46000 | BH83: Cecília Sousa
A84: 2025 | B84: 46003 | C84: 45993 | E84: Massificado PJ | F84: RICARDO SOUZA | G84: Viana Peixoto Advogados Associados | H84: PJ | I84: EMPRESAS 1 | J84: PR | K84: 45993 | L84: 2 | M84: G3 AUTO STORE COMERCIALIZACAO DE VEICULO | N84: 43701023000136 | O84: 85000 | P84: 85000 | Q84: 285311.64 | R84: 219639.23 | S84: PROPOSTA NEGADA | T84: FORMULARIO | U84: 46011 | X84: Campanha mês | Y84: B-SEM CAMPANHA | Z84: SIM | AA84: NÃO | AB84: NORTE | AC84: Multicanalidade | AG84: Ele só pagou o carro porque era o melhor PRA ELE, tivemos o pagamento de apenas uma parcela do Giro. Nossa garantia vale 300k e vamos liberar por 80k? Acabamos de ajuizar o caso e já estamos falando que temos baixa probabilidade na via judicial? A contraproposta aqui é de no mínimo 180k | AH84: SEM ALÇADA | AI84: 0 | AJ84: 0.7021 | AK84: 0.9 | AL84: RENATO SOUSA | AM84: CE | AO84: NÃO | AP84: QUITAÇÃO | AQ84: QUITAÇÃO | AS84: QUITAÇÃO | AV84: Ação busca e apreensão. | AW84: Positiva | AX84: Realizado | AY84: Efeitos Negativos | BB84: SIM | BC84: VEICULO | BH84: Cecília Sousa
A85: 2025 | B85: 46003 | C85: 45993 | E85: Massificado PJ | F85: RICARDO SOUZA | G85: Viana Peixoto Advogados Associados | H85: PJ | I85: EMPRESAS 1 | J85: PR | K85: 45993 | L85: 2 | M85: W R COML DE BEB LTDA | N85: 34063894000180 | O85: 2000 | P85: 84893.71 | Q85: 282979 | R85: 85592.46 | S85: PROPOSTA NEGADA | T85: 256219794 | U85: 45995 | X85: Campanha mês | Y85: EVENTO REGIONAL - UF | Z85: SIM | AA85: NÃO | AB85: CENTRO_OESTE | AC85: Telefone | AG85: CLIENTE NÃO HONRA COM ACORDO PARCELADO. PODEMOS REAVALIAR A REATIVAÇÃO DO ACORDO ANTERIOR MEDIANTE UMA ENTRADA MINIMA DE 3 PMTS. SEGUIR COM A EXECUÇÃO E PENHORA DOS BENS EM CASO DE NEGATIVA. | AH85: 90 | AI85: 0.0112 | AJ85: 0.7 | AK85: 0.9 | AL85: MIKELYNE ALVES | AM85: DF | AO85: NÃO | AP85: 56 | AQ85: 2032.29 | AS85: 46026 | AV85: Ação de execução | AW85: Positiva | AX85: Realizado | AY85: Positivo | BB85: SIM | BC85: VEICULO | BH85: Cecília Sousa
A86: 2025 | B86: 46003 | C86: 45993 | E86: Massificado PF | F86: BRUNO MONTEIRO | G86: Viana Peixoto Advogados Associados | H86: PF | I86: PESSOA FÍSICA | J86: PR | K86: 45993 | L86: 2 | M86: CESAR PEREIRA DA SILVA FILHO | N86: 2861953560 | O86: 20014.01 | P86: 20014.01 | Q86: 579386.65 | R86: 418119.78 | S86: PROPOSTA NEGADA | T86: 256406658 | U86: 46010 | W86: Alto Impacto | X86: Campanha mês | Y86: EVENTO REGIONAL - UF | Z86: SIM | AA86: SIM | AB86: NORDESTE | AC86: Multicanalidade | AG86: CLIENTE É ADVOGADO, CERTO? PODEM SEGUIR COM O PROCESSO OU PODEMOS REAVALIAR UMA PROPOSTA JUSTA (O QUE NÃO É O CASO AQUI) NEGADO. | AH86: 90 | AI86: 0 | AJ86: 0.9655 | AK86: 0.9 | AL86: MICHELE GUIMARAES | AM86: BA | AO86: NÃO | AP86: QUITAÇÃO | AQ86: QUITAÇÃO | AS86: QUITAÇÃO | AV86: Ação Monitória | AW86: Positiva | AX86: Realizado | AY86: Efeitos Negativos | BB86: NÃO | BH86: Hillary Cavalcanti
A87: 2025 | B87: 46003 | C87: 45993 | E87: Massificado PJ | F87: RICARDO SOUZA | G87: Viana Peixoto Advogados Associados | H87: PJ | I87: EMPRESAS 1 | J87: PR | K87: 45993 | L87: 2 | M87: AMP INDUSTRIA COMERCIO E SERVICOS LTDA | N87: 44455550000170 | O87: 9000 | P87: 48523.64 | Q87: 161745.44 | R87: 127850.97 | S87: PROPOSTA NEGADA | T87: 256395350 | U87: 46013 | X87: Campanha mês | Y87: EVENTO REGIONAL - UF | Z87: SIM | AA87: NÃO | AB87: CENTRO_OESTE | AC87: Multicanalidade | AG87: Cliente tomou 103k do banco e quer devolver 48k em 12 meses? Acho que ele não entendeu o racional do credito concedido. EXPLIQUEM, RELEMBREEM O FATO AOS SÓCIOS! Se ele quer pagar em 12 parcelas, manter a parcela da origem. Alonguem essa dívida....com VP mínimo dos 103 mil e taxa de 1,12% | AH87: 90 | AI87: 0.0112 | AJ87: 0.7 | AK87: 0.9 | AL87: MIKELYNE ALVES | AM87: MS | AO87: NÃO | AP87: 13 | AQ87: 3572.31 | AS87: 46044 | AV87: Ação de execução | AW87: Positiva | AX87: Realizado | AY87: Efeitos Negativos | BB87: NÃO | BH87: Cecília Sousa
A88: 2025 | B88: 46003 | C88: 45993 | D88: 45993 | E88: Massificado PF | F88: BRUNO MONTEIRO | G88: Viana Peixoto Advogados Associados | H88: PF | I88: PESSOA FÍSICA | J88: CV | K88: 45993 | L88: 2 | M88: FRANCISCO TEMOTEO DA SILVA FILHO | N88: 11251190120 | O88: 2000 | P88: 38005.83 | Q88: 63343.05 | R88: 59508.25 | S88: PROPOSTA EXPURGADA | T88: 255965535 | U88: 45992 | V88: 46002 | X88: Campanha mês | Y88: CAMPANHA PRE APROVADO C2 | Z88: NÃO | AA88: NÃO | AB88: CENTRO_OESTE | AC88: Multicanalidade | AH88: SEM ALÇADA | AI88: 0 | AJ88: 0.4 | AK88: 0.9 | AL88: FELIPE CORREIA | AM88: GO | AO88: NÃO | AP88: 71 | AQ88: 514.37 | AS88: 46023 | BB88: NÃO | BH88: Hillary Cavalcanti
A89: 2025 | B89: 46003 | C89: 45993 | D89: 45995 | E89: Massificado PJ | F89: RICARDO SOUZA | G89: Viana Peixoto Advogados Associados | H89: PJ | I89: EMPRESAS 1 | J89: CV | K89: 45993 | L89: 2 | M89: IMPACTUS MIX LTDA | N89: 37090605000120 | O89: 7000 | P89: 143078.53 | Q89: 204397.89 | R89: 195986.92 | S89: PROPOSTA EXPURGADA | T89: 256394699 | U89: 46013 | V89: 46000 | X89: Campanha mês | Y89: EVENTO REGIONAL - UF | Z89: SIM | AA89: NÃO | AB89: NORTE | AC89: Multicanalidade | AH89: 90 | AI89: 0.0112 | AJ89: 0.3 | AK89: 0.9 | AL89: MIKELYNE ALVES | AM89: PA | AO89: NÃO | AP89: 121 | AQ89: 2084.28 | AS89: 46044 | AV89: Ação Monitória | AW89: Positiva | AX89: Realizado | AY89: Positivo | BB89: NÃO | BH89: Cecília Sousa
A90: 2025 | B90: 46003 | C90: 45993 | E90: Alto Ticket | F90: BRUNO MONTEIRO | G90: Viana Peixoto Advogados Associados | H90: PF | I90: PESSOA FÍSICA | J90: PR | K90: 45993 | L90: 2 | M90: BENITO JOAQUIM DE CASTRO FILHO | N90: 72730226400 | O90: 75000 | P90: 75000 | Q90: 1501062.9 | R90: 552190.62 | S90: PROPOSTA NEGADA | T90: FORMULARIO | U90: 46010 | W90: Alto Ticket | X90: Campanha mês | Y90: B-SEM CAMPANHA | Z90: SIM | AA90: NÃO | AB90: NORDESTE | AC90: Multicanalidade | AG90: Em que pese a defesa, para o pagamento a vista, segue uma contraproposta, dado que não temos atualização da pesquisa de bens atualizada, baixo histórico de amortização. Caso o cliente aceite as condições, solicitamos a inclusão no workflow para deliberação. Risco grupo R$ 1.299.288,53 Faixa de atraso: 2.894 dias prejuízo Histórico na origem: Contratou um total de R$ 332 mil, amortizou R$ 64 mil; Não possui histórico de acordos; Principal devido R$ 267 mil Pesquisa de bens realizada em 2022, matrícula do imóvel 63658 traz avaliação de R$ 450K e a propriedade é compartilhada entre o devedor e um terceiro, restando apenas a propriedade de 50% ao Sr Benito, a qual corresponde a R$ 225K da avaliação da matrícula. Foi solicitada renovação da matricula, para confirmar a titularidade da propriedade e a ausência de demais restritivos. Contraproposta: BENITO JOAQUIM DE CASTRO FILHO - 727.302.264-00 Saldo MZ: R$ 552.190,62 Saldo LY: R$ 1.550.097,32 Valor negociado: R$ 100,000,00 a vista no ato Desconto: 93,55% Contratos: 1592000012570 32 0155 C.P.E. PR DEVEDOR P N 204.425,80 1592000006300 00 1308 BLACKMASTE PR DEVEDOR P N 1.311.043,59 1592000059900 00 1308 BLACKMASTE PR DEVEDOR P N 34.627,93 Ressalto que se faz necessário o cadastro e envio do acordo para aprovação do CD Reestruturação, através das alçadas 92 (PJ) e 91 (PF). | AH90: FORMULARIO | AI90: 0 | AJ90: 0.95 | AK90: 0.9 | AL90: WELLINGTON SOUSA | AM90: PB | AO90: NÃO | AP90: QUITAÇÃO | AQ90: QUITAÇÃO | AS90: QUITAÇÃO | AV90: Ação de cobrança | AW90: Positiva | AX90: Realizado | AY90: Positivo | BB90: NÃO | BH90: Hillary Cavalcanti
A91: 2025 | B91: 46003 | C91: 45993 | D91: 45995 | E91: Massificado PJ | F91: RICARDO SOUZA | G91: Viana Peixoto Advogados Associados | H91: PJ | I91: EMPRESAS 1 | J91: CV | K91: 45993 | L91: 2 | M91: FLAVIO CARVALHO | N91: 5976556000131 | O91: 5000 | P91: 125744.98 | Q91: 147935.26 | R91: 145259.29 | S91: PROPOSTA EXPURGADA | T91: 256461222 | U91: 45999 | V91: 46009 | X91: Campanha mês | Y91: EVENTO REGIONAL - UF | Z91: NÃO | AA91: NÃO | AB91: NORTE | AC91: Telefone | AH91: 90 | AI91: 0.0112 | AJ91: 0.15 | AK91: 0.9 | AL91: MIKELYNE ALVES | AM91: CE | AO91: NÃO | AP91: 56 | AQ91: 2955.85 | AS91: 46030 | BB91: NÃO | BH91: Cecília Sousa
A92: 2025 | B92: 46003 | C92: 45993 | D92: 45993 | E92: Massificado PF | F92: BRUNO MONTEIRO | G92: Viana Peixoto Advogados Associados | H92: PF | I92: PESSOA FÍSICA | J92: PR | K92: 45993 | L92: 2 | M92: RAUL DE ARAUJO BARROS | N92: 5444484480 | O92: 3029.91 | P92: 3029.91 | Q92: 75739.11 | R92: 53187.58 | S92: PROMESSA DE PAGAMENTO | T92: 256400335 | U92: 46001 | X92: Campanha mês | Y92: CAMPANHA PRE APROVADO C2 | Z92: NÃO | AA92: NÃO | AB92: CENTRO_OESTE | AC92: Multicanalidade | AH92: SEM ALÇADA | AI92: 0 | AJ92: 0.96 | AK92: 0.9 | AL92: FRANCISCA JOCILANE | AM92: GO | AO92: NÃO | AP92: QUITAÇÃO | AQ92: QUITAÇÃO | AS92: QUITAÇÃO | BB92: NÃO | BH92: Hillary Cavalcanti
A93: 2025 | B93: 46003 | C93: 45993 | D93: 45993 | E93: Massificado PJ | F93: RICARDO SOUZA | G93: Viana Peixoto Advogados Associados | H93: PJ | I93: EMPRESAS 1 | J93: CV | K93: 45993 | L93: 2 | M93: L S DO NASCIMENTO SERVICOS | N93: 19424170000121 | O93: 5009.58 | P93: 103639.1 | Q93: 115316.25 | R93: 24013.36 | S93: ACORDO IMPLANTADO | T93: 256425403 | U93: 46006 | X93: Campanha mês | Y93: PRODUTOS GOVERNAMENTAIS | Z93: SIM | AA93: NÃO | AB93: NORDESTE | AC93: Telefone | AH93: FORMULARIO | AI93: 0.0049 | AJ93: 0.1013 | AK93: 0.9 | AL93: RENATO SOUSA | AM93: AL | AO93: NÃO | AP93: 71 | AQ93: 1665.63 | AS93: 46037 | BB93: NÃO | BG93: 46006 | BH93: Cecília Sousa
A94: 2025 | B94: 46003 | C94: 45993 | D94: 45993 | E94: Massificado PF | F94: BRUNO MONTEIRO | G94: Viana Peixoto Advogados Associados | H94: PF | I94: PESSOA FÍSICA | J94: CV | K94: 45993 | L94: 2 | M94: JEAN CARLO BERNARDO BORGES | N94: 3439664171 | O94: 250 | P94: 22918.59 | Q94: 24124.83 | R94: 24019.32 | S94: PROPOSTA EXPURGADA | T94: 256397155 | U94: 45994 | V94: 46006 | X94: Campanha mês | Y94: CAMPANHA PRE APROVADO C2 | Z94: NÃO | AA94: NÃO | AB94: CENTRO_OESTE | AC94: Multicanalidade | AH94: SEM ALÇADA | AI94: 0 | AJ94: 0.05 | AK94: 0.9 | AL94: FRANCISCA JOCILANE | AM94: GO | AO94: NÃO | AP94: 96 | AQ94: 245.35 | AS94: 46025 | BB94: NÃO | BH94: Hillary Cavalcanti
A95: 2025 | B95: 46003 | C95: 45993 | D95: 45993 | E95: Massificado PF | F95: BRUNO MONTEIRO | G95: Viana Peixoto Advogados Associados | H95: PF | I95: PESSOA FÍSICA | J95: CV | K95: 45993 | L95: 2 | M95: MIRIA DEISE CALDAS ALBUQUERQUE | N95: 93438729253 | O95: 1940.43 | P95: 1940.43 | Q95: 38808.75 | R95: 28449.83 | S95: ACORDO IMPLANTADO | T95: 256393483 | U95: 45994 | X95: Campanha mês | Y95: CAMPANHA PRE APROVADO C2 | Z95: NÃO | AA95: NÃO | AB95: NORTE | AC95: Multicanalidade | AH95: SEM ALÇADA | AI95: 0 | AJ95: 0.95 | AK95: 0.9 | AL95: SARAH SALES | AM95: PA | AO95: NÃO | AP95: QUITAÇÃO | AQ95: QUITAÇÃO | AS95: QUITAÇÃO | BB95: NÃO | BG95: 45992 | BH95: Hillary Cavalcanti
A96: 2025 | B96: 46003 | C96: 45993 | E96: Massificado PJ | F96: RICARDO SOUZA | G96: Viana Peixoto Advogados Associados | H96: PJ | I96: EMPRESAS 1 | J96: PR | K96: 45993 | L96: 2 | M96: JOSEAN FERREIRA DE CARVALHO | N96: 19680989000150 | O96: 15000 | P96: 21666.36 | Q96: 144442.31 | R96: 126018.79 | S96: PROPOSTA NEGADA | T96: 256395045 | U96: 46013 | X96: Campanha mês | Y96: EVENTO REGIONAL - UF | Z96: NÃO | AA96: NÃO | AB96: NORDESTE | AC96: Multicanalidade | AG96: Negado, esse valor pode ser avaliado á vista no parcelado, seguir a politica. No ultimo acordo foi em 60x, por quê reduzir prazo e aumentar desconto? Temos PP? Vamos ajuizar? | AH96: 90 | AI96: 0.0112 | AJ96: 0.85 | AK96: 0.9 | AL96: MIKELYNE ALVES | AM96: BA | AO96: NÃO | AP96: 9 | AQ96: 898.29 | AS96: 46044 | BB96: NÃO | BH96: Cecília Sousa
A97: 2025 | B97: 46003 | C97: 45993 | E97: Massificado PF | F97: BRUNO MONTEIRO | G97: Viana Peixoto Advogados Associados | H97: PF | I97: PESSOA FÍSICA | J97: PR | K97: 45993 | L97: 2 | M97: BRUNO CORREIA MONTALVAO | N97: 69813752149 | O97: 25078.66 | P97: 25078.66 | Q97: 285028.48 | R97: 174350.85 | S97: PROPOSTA NEGADA | T97: 256404698 | U97: 46001 | W97: Alto Impacto | X97: Campanha mês | Y97: EVENTO REGIONAL - UF | Z97: SIM | AA97: SIM | AB97: CENTRO_OESTE | AC97: Multicanalidade | AG97: Cliente tomou mais de 100k e não pagou nem a 1 PMT. Negado. Contra: 100k a vista. | AH97: 90 | AI97: 0 | AJ97: 0.912 | AK97: 0.9 | AL97: MICHELE GUIMARAES | AM97: GO | AO97: NÃO | AP97: QUITAÇÃO | AQ97: QUITAÇÃO | AS97: QUITAÇÃO | AV97: Ação Monitória | AW97: Positiva | AX97: Realizado | AY97: Positivo | BB97: NÃO | BH97: Cecília Sousa
A98: 2025 | B98: 46003 | C98: 45993 | D98: 45995 | E98: Massificado PF | F98: BRUNO MONTEIRO | G98: Viana Peixoto Advogados Associados | H98: PF | I98: PESSOA FÍSICA | J98: CV | K98: 45993 | L98: 2 | M98: MARIA APARECIDA DE MEDEIROS | N98: 56327730515 | O98: 16000 | P98: 16000 | Q98: 36149.9 | R98: 34768.18 | S98: PROPOSTA APROVADA | T98: FORMULARIO | U98: 46013 | X98: Campanha mês | Y98: EVENTO REGIONAL - UF | Z98: NÃO | AA98: NÃO | AB98: NORDESTE | AC98: Multicanalidade | AH98: FORMULARIO | AI98: 0 | AJ98: 0.557 | AK98: 0.9 | AL98: MICHELE GUIMARAES | AM98: RN | AO98: NÃO | AP98: QUITAÇÃO | AQ98: QUITAÇÃO | AS98: QUITAÇÃO | BB98: SIM | BC98: VEICULO | BH98: Cecília Sousa
A99: 2025 | B99: 46003 | C99: 45993 | D99: 45993 | E99: E2 - Baixo Ticket | F99: ANDREZA SOUZA | G99: Viana Peixoto Advogados Associados | H99: PJ | I99: EMPRESAS 2 | J99: CV | K99: 45993 | L99: 2 | M99: NORTE LAJES COMERCIO VAREJISTA DE MATERI | N99: 27833001000173 | O99: 44780.83 | P99: 385775.87 | Q99: 429498.66 | R99: 100430.79 | S99: PROPOSTA EXPURGADA | T99: 256425341 | U99: 45999 | V99: 46009 | X99: Campanha mês | Y99: PRODUTOS GOVERNAMENTAIS | Z99: NÃO | AA99: NÃO | AB99: NORTE | AC99: Multicanalidade | AH99: FORMULARIO | AI99: 0.011 | AJ99: 0.1018 | AK99: 0.9 | AL99: SABRINA ERLLEN | AM99: AM | AO99: NÃO | AP99: 71 | AQ99: 7003.4 | AS99: 46030 | BB99: NÃO | BH99: Cecília Sousa
A100: 2025 | B100: 46003 | C100: 45993 | D100: 45993 | E100: E2 - Baixo Ticket | F100: ANDREZA SOUZA | G100: Viana Peixoto Advogados Associados | H100: PJ | I100: EMPRESAS 2 | J100: PR | K100: 45993 | L100: 2 | M100: CLEOCIMAR AZEVEDO DA MOTA EIRELI | N100: 34208133000170 | O100: 11000 | P100: 38038.31 | Q100: 380383.03 | R100: 256191.74 | S100: PROMESSA DE PAGAMENTO | T100: 256394937 | U100: 46013 | X100: Campanha mês | Y100: EVENTO REGIONAL - UF | Z100: SIM | AA100: NÃO | AB100: NORTE | AC100: Multicanalidade | AH100: 90 | AI100: 0.0112 | AJ100: 0.9 | AK100: 0.9 | AL100: MIKELYNE ALVES | AM100: AM | AO100: NÃO | AP100: 11 | AQ100: 2916.69 | AS100: 46044 | AV100: Ação de execução | AW100: Positiva | AX100: Não realizado | BB100: NÃO | BH100: Cecília Sousa
...

Sheet PJ_E1 (2)
M1: PJ
D2: PJ
A6: GERAL | B6: CPC | C6: CPCA | D6: PROPOSTA | E6: PAGAMENTO | F6: ($) CASH | G6: ($) TKT CASH | H6: ($) CONTABIL | I6: ($) TKT CONTABIL | J6: (%) CONVERSÃO | K6: (%) CPC_A | L6: (%) EFETIVIDADE
B7: =AUX!C15 -> 70 | C7: =AUX!C16 -> 46 | D7: =AUX!C17 -> 12 | E7: =AUX!C18 -> 5 | F7: =AUX!C19 -> 75686.94 | G7: =AUX!C20 -> 6307.245 | H7: =AUX!C21 -> 976768.68 | I7: =AUX!C22 -> 81397.39 | J7: =AUX!C23 -> 0.26 | K7: =AUX!C24 -> 0.71 | L7: =AUX!C25 -> 0.6
A9: META GERAL | B9: =B7*(COUNTIFS(B14:B40,">="&1)) -> 0 | C9: =C7*(COUNTIFS(C14:C40,">="&1)) -> 0 | D9: =D7*(COUNTIFS(D14:D40,">="&1)) -> 0 | E9: =E7*(COUNTIFS(E14:E40,">="&1)) -> 0 | F9: =F7*(COUNTIFS(F14:F40,">="&1)) -> 0 | G9: =G7 -> 6307.245 | H9: =H7*(COUNTIFS(H14:H40,">="&1)) -> 0 | I9: =I7 -> 81397.39 | J9: =J7 -> 0.26 | K9: =K7 -> 0.71 | L9: =L7 -> 0.6
A10: REALIZADO | B10: =SUM(B14:B40) -> 0 | C10: =SUM(C14:C40) -> 0 | D10: =SUM(D14:D40) -> 0 | E10: =SUM(E14:E40) -> 0 | F10: =SUM(F14:F40) -> 0 | G10: =F10/E10 -> #DIV/0! | H10: =SUM(H14:H35) -> 0 | I10: =H10/E10 -> #DIV/0! | J10: =AVERAGE(J14:J35) -> #DIV/0! | K10: =AVERAGE(K14:K35) -> #DIV/0! | L10: =AVERAGE(L14:L35) -> #DIV/0!
A11: (%) META | B11: =B10/B9 -> #DIV/0! | C11: =C10/C9 -> #DIV/0! | D11: =D10/D9 -> #DIV/0! | E11: =E10/E9 -> #DIV/0! | F11: =F10/F9 -> #DIV/0! | G11: =G10/G9 -> #DIV/0! | H11: =H10/H9 -> #DIV/0! | I11: =I10/I9 -> #DIV/0! | ... L11: =L10/L9 -> #DIV/0!
A13: DATA | B13: CPC | C13: CPCA | D13: PROPOSTA | E13: PAGAMENTO | F13: ($) CASH | G13: ($) TKT CASH | H13: ($) CONTABIL | I13: ($) TKT CONTABIL | J13: (%) CONVERSÃO | K13: (%) CPC | L13: (%) EFETIVIDADE
A14: 46083 | B14: =SUMIFS('HORA HORA'!J:J,'HORA HORA'!C:C,'PJ_E1 (2)'!$M$1,'HORA HORA'!B:B,'PJ_E1 (2)'!A14) -> 0 | C14: =SUMIFS('HORA HORA'!K:K,'HORA HORA'!C:C,'PJ_E1 (2)'!$M$1,'HORA HORA'!B:B,'PJ_E1 (2)'!A14) -> 0 | D14: =SUMIFS('HORA HORA'!L:L,'HORA HORA'!C:C,'PJ_E1 (2)'!$M$1,'HORA HORA'!B:B,'PJ_E1 (2)'!A14) -> 0 | E14: =COUNTIFS(ACOMPANHAMENTO!S:S,"ACORDO IMPLANTADO",ACOMPANHAMENTO!BC:BC,A14,ACOMPANHAMENTO!H:H,'PJ_E1 (2)'!$M$1) -> 0 | F14: =SUMIFS(ACOMPANHAMENTO!O:O,ACOMPANHAMENTO!H:H,'PJ_E1 (2)'!$M$1,ACOMPANHAMENTO!BC:BC,'PJ_E1 (2)'!A14) -> 0 | G14: =F14/D14 -> #DIV/0! | H14: =SUMIFS(ACOMPANHAMENTO!R:R,ACOMPANHAMENTO!BC:BC,'PJ_E1 (2)'!A14,ACOMPANHAMENTO!H:H,'PJ_E1 (2)'!$M$1) -> 0 | I14: =H14/D14 -> #DIV/0! | J14: =IFERROR(IF(D14/B14=0,"-",D14/B14),"-") -> - | K14: =SUMIFS('HORA HORA'!$K:$K,'HORA HORA'!$B:$B,'PJ_E1 (2)'!$A14,'HORA HORA'!$C:$C,"="&"PJ",'HORA HORA'!$Y:$Y,"<>"&"EMPRESAS_2")/SUMIFS('HORA HORA'!$J:$J,'HORA HORA'!$B:$B,'PJ_E1 (2)'!$A14,'HORA HORA'!$C:$C,"="&"PJ",'HORA HORA'!$Y:$Y,"<>"&"EMPRESAS_2") -> #DIV/0! | L14: =E14/D14 -> #DIV/0!
A15: 46084 | B15: =SUMIFS('HORA HORA'!J:J,'HORA HORA'!C:C,'PJ_E1 (2)'!$M$1,'HORA HORA'!B:B,'PJ_E1 (2)'!A15) -> 0 | C15: =SUMIFS('HORA HORA'!K:K,'HORA HORA'!C:C,'PJ_E1 (2)'!$M$1,'HORA HORA'!B:B,'PJ_E1 (2)'!A15) -> 0 | D15: =SUMIFS('HORA HORA'!L:L,'HORA HORA'!C:C,'PJ_E1 (2)'!$M$1,'HORA HORA'!B:B,'PJ_E1 (2)'!A15) -> 0 | E15: =COUNTIFS(ACOMPANHAMENTO!S:S,"ACORDO IMPLANTADO",ACOMPANHAMENTO!BC:BC,A15,ACOMPANHAMENTO!H:H,'PJ_E1 (2)'!$M$1) -> 0 | F15: =SUMIFS(ACOMPANHAMENTO!O:O,ACOMPANHAMENTO!H:H,'PJ_E1 (2)'!$M$1,ACOMPANHAMENTO!BC:BC,'PJ_E1 (2)'!A15) -> 0 | G15: =F15/D15 -> #DIV/0! | H15: =SUMIFS(ACOMPANHAMENTO!R:R,ACOMPANHAMENTO!BC:BC,'PJ_E1 (2)'!A15,ACOMPANHAMENTO!H:H,'PJ_E1 (2)'!$M$1) -> 0 | I15: =H15/D15 -> #DIV/0! | J15: =IFERROR(IF(D15/B15=0,"-",D15/B15),"-") -> - | K15: =SUMIFS('HORA HORA'!$K:$K,'HORA HORA'!$B:$B,'PJ_E1 (2)'!$A15,'HORA HORA'!$C:$C,"="&"PJ",'HORA HORA'!$Y:$Y,"<>"&"EMPRESAS_2")/SUMIFS('HORA HORA'!$J:$J,'HORA HORA'!$B:$B,'PJ_E1 (2)'!$A15,'HORA HORA'!$C:$C,"="&"PJ",'HORA HORA'!$Y:$Y,"<>"&"EMPRESAS_2") -> #DIV/0! | L15: =E15/D15 -> #DIV/0!
A16: 46085 | B16: =SUMIFS('HORA HORA'!J:J,'HORA HORA'!C:C,'PJ_E1 (2)'!$M$1,'HORA HORA'!B:B,'PJ_E1 (2)'!A16) -> 0 | C16: =SUMIFS('HORA HORA'!K:K,'HORA HORA'!C:C,'PJ_E1 (2)'!$M$1,'HORA HORA'!B:B,'PJ_E1 (2)'!A16) -> 0 | D16: =SUMIFS('HORA HORA'!L:L,'HORA HORA'!C:C,'PJ_E1 (2)'!$M$1,'HORA HORA'!B:B,'PJ_E1 (2)'!A16) -> 0 | E16: =COUNTIFS(ACOMPANHAMENTO!S:S,"ACORDO IMPLANTADO",ACOMPANHAMENTO!BC:BC,A16,ACOMPANHAMENTO!H:H,'PJ_E1 (2)'!$M$1) -> 0 | F16: =SUMIFS(ACOMPANHAMENTO!O:O,ACOMPANHAMENTO!H:H,'PJ_E1 (2)'!$M$1,ACOMPANHAMENTO!BC:BC,'PJ_E1 (2)'!A16) -> 0 | G16: =F16/D16 -> #DIV/0! | H16: =SUMIFS(ACOMPANHAMENTO!R:R,ACOMPANHAMENTO!BC:BC,'PJ_E1 (2)'!A16,ACOMPANHAMENTO!H:H,'PJ_E1 (2)'!$M$1) -> 0 | I16: =H16/D16 -> #DIV/0! | J16: =IFERROR(IF(D16/B16=0,"-",D16/B16),"-") -> - | K16: =SUMIFS('HORA HORA'!$K:$K,'HORA HORA'!$B:$B,'PJ_E1 (2)'!$A16,'HORA HORA'!$C:$C,"="&"PJ",'HORA HORA'!$Y:$Y,"<>"&"EMPRESAS_2")/SUMIFS('HORA HORA'!$J:$J,'HORA HORA'!$B:$B,'PJ_E1 (2)'!$A16,'HORA HORA'!$C:$C,"="&"PJ",'HORA HORA'!$Y:$Y,"<>"&"EMPRESAS_2") -> #DIV/0! | L16: =E16/D16 -> #DIV/0!
A17: 46086 | B17: =SUMIFS('HORA HORA'!J:J,'HORA HORA'!C:C,'PJ_E1 (2)'!$M$1,'HORA HORA'!B:B,'PJ_E1 (2)'!A17) -> 0 | C17: =SUMIFS('HORA HORA'!K:K,'HORA HORA'!C:C,'PJ_E1 (2)'!$M$1,'HORA HORA'!B:B,'PJ_E1 (2)'!A17) -> 0 | D17: =SUMIFS('HORA HORA'!L:L,'HORA HORA'!C:C,'PJ_E1 (2)'!$M$1,'HORA HORA'!B:B,'PJ_E1 (2)'!A17) -> 0 | E17: =COUNTIFS(ACOMPANHAMENTO!S:S,"ACORDO IMPLANTADO",ACOMPANHAMENTO!BC:BC,A17,ACOMPANHAMENTO!H:H,'PJ_E1 (2)'!$M$1) -> 0 | F17: =SUMIFS(ACOMPANHAMENTO!O:O,ACOMPANHAMENTO!H:H,'PJ_E1 (2)'!$M$1,ACOMPANHAMENTO!BC:BC,'PJ_E1 (2)'!A17) -> 0 | G17: =F17/D17 -> #DIV/0! | H17: =SUMIFS(ACOMPANHAMENTO!R:R,ACOMPANHAMENTO!BC:BC,'PJ_E1 (2)'!A17,ACOMPANHAMENTO!H:H,'PJ_E1 (2)'!$M$1) -> 0 | I17: =H17/D17 -> #DIV/0! | J17: =IFERROR(IF(D17/B17=0,"-",D17/B17),"-") -> - | K17: =SUMIFS('HORA HORA'!$K:$K,'HORA HORA'!$B:$B,'PJ_E1 (2)'!$A17,'HORA HORA'!$C:$C,"="&"PJ",'HORA HORA'!$Y:$Y,"<>"&"EMPRESAS_2")/SUMIFS('HORA HORA'!$J:$J,'HORA HORA'!$B:$B,'PJ_E1 (2)'!$A17,'HORA HORA'!$C:$C,"="&"PJ",'HORA HORA'!$Y:$Y,"<>"&"EMPRESAS_2") -> #DIV/0! | L17: =E17/D17 -> #DIV/0!
A18: 46087 | B18: =SUMIFS('HORA HORA'!J:J,'HORA HORA'!C:C,'PJ_E1 (2)'!$M$1,'HORA HORA'!B:B,'PJ_E1 (2)'!A18) -> 0 | C18: =SUMIFS('HORA HORA'!K:K,'HORA HORA'!C:C,'PJ_E1 (2)'!$M$1,'HORA HORA'!B:B,'PJ_E1 (2)'!A18) -> 0 | D18: =SUMIFS('HORA HORA'!L:L,'HORA HORA'!C:C,'PJ_E1 (2)'!$M$1,'HORA HORA'!B:B,'PJ_E1 (2)'!A18) -> 0 | E18: =COUNTIFS(ACOMPANHAMENTO!S:S,"ACORDO IMPLANTADO",ACOMPANHAMENTO!BC:BC,A18,ACOMPANHAMENTO!H:H,'PJ_E1 (2)'!$M$1) -> 0 | F18: =SUMIFS(ACOMPANHAMENTO!O:O,ACOMPANHAMENTO!H:H,'PJ_E1 (2)'!$M$1,ACOMPANHAMENTO!BC:BC,'PJ_E1 (2)'!A18) -> 0 | G18: =F18/D18 -> #DIV/0! | H18: =SUMIFS(ACOMPANHAMENTO!R:R,ACOMPANHAMENTO!BC:BC,'PJ_E1 (2)'!A18,ACOMPANHAMENTO!H:H,'PJ_E1 (2)'!$M$1) -> 0 | I18: =H18/D18 -> #DIV/0! | J18: =IFERROR(IF(D18/B18=0,"-",D18/B18),"-") -> - | K18: =SUMIFS('HORA HORA'!$K:$K,'HORA HORA'!$B:$B,'PJ_E1 (2)'!$A18,'HORA HORA'!$C:$C,"="&"PJ",'HORA HORA'!$Y:$Y,"<>"&"EMPRESAS_2")/SUMIFS('HORA HORA'!$J:$J,'HORA HORA'!$B:$B,'PJ_E1 (2)'!$A18,'HORA HORA'!$C:$C,"="&"PJ",'HORA HORA'!$Y:$Y,"<>"&"EMPRESAS_2") -> #DIV/0! | L18: =E18/D18 -> #DIV/0!
A19: 46090 | B19: =SUMIFS('HORA HORA'!J:J,'HORA HORA'!C:C,'PJ_E1 (2)'!$M$1,'HORA HORA'!B:B,'PJ_E1 (2)'!A19) -> 0 | C19: =SUMIFS('HORA HORA'!K:K,'HORA HORA'!C:C,'PJ_E1 (2)'!$M$1,'HORA HORA'!B:B,'PJ_E1 (2)'!A19) -> 0 | D19: =SUMIFS('HORA HORA'!L:L,'HORA HORA'!C:C,'PJ_E1 (2)'!$M$1,'HORA HORA'!B:B,'PJ_E1 (2)'!A19) -> 0 | E19: =COUNTIFS(ACOMPANHAMENTO!S:S,"ACORDO IMPLANTADO",ACOMPANHAMENTO!BC:BC,A19,ACOMPANHAMENTO!H:H,'PJ_E1 (2)'!$M$1) -> 0 | F19: =SUMIFS(ACOMPANHAMENTO!O:O,ACOMPANHAMENTO!H:H,'PJ_E1 (2)'!$M$1,ACOMPANHAMENTO!BC:BC,'PJ_E1 (2)'!A19) -> 0 | G19: =F19/D19 -> #DIV/0! | H19: =SUMIFS(ACOMPANHAMENTO!R:R,ACOMPANHAMENTO!BC:BC,'PJ_E1 (2)'!A19,ACOMPANHAMENTO!H:H,'PJ_E1 (2)'!$M$1) -> 0 | I19: =H19/D19 -> #DIV/0! | J19: =IFERROR(IF(D19/B19=0,"-",D19/B19),"-") -> - | K19: =SUMIFS('HORA HORA'!$K:$K,'HORA HORA'!$B:$B,'PJ_E1 (2)'!$A19,'HORA HORA'!$C:$C,"="&"PJ",'HORA HORA'!$Y:$Y,"<>"&"EMPRESAS_2")/SUMIFS('HORA HORA'!$J:$J,'HORA HORA'!$B:$B,'PJ_E1 (2)'!$A19,'HORA HORA'!$C:$C,"="&"PJ",'HORA HORA'!$Y:$Y,"<>"&"EMPRESAS_2") -> #DIV/0! | L19: =E19/D19 -> #DIV/0!
A20: 46091 | B20: =SUMIFS('HORA HORA'!J:J,'HORA HORA'!C:C,'PJ_E1 (2)'!$M$1,'HORA HORA'!B:B,'PJ_E1 (2)'!A20) -> 0 | C20: =SUMIFS('HORA HORA'!K:K,'HORA HORA'!C:C,'PJ_E1 (2)'!$M$1,'HORA HORA'!B:B,'PJ_E1 (2)'!A20) -> 0 | D20: =SUMIFS('HORA HORA'!L:L,'HORA HORA'!C:C,'PJ_E1 (2)'!$M$1,'HORA HORA'!B:B,'PJ_E1 (2)'!A20) -> 0 | E20: =COUNTIFS(ACOMPANHAMENTO!S:S,"ACORDO IMPLANTADO",ACOMPANHAMENTO!BC:BC,A20,ACOMPANHAMENTO!H:H,'PJ_E1 (2)'!$M$1) -> 0 | F20: =SUMIFS(ACOMPANHAMENTO!O:O,ACOMPANHAMENTO!H:H,'PJ_E1 (2)'!$M$1,ACOMPANHAMENTO!BC:BC,'PJ_E1 (2)'!A20) -> 0 | G20: =F20/D20 -> #DIV/0! | H20: =SUMIFS(ACOMPANHAMENTO!R:R,ACOMPANHAMENTO!BC:BC,'PJ_E1 (2)'!A20,ACOMPANHAMENTO!H:H,'PJ_E1 (2)'!$M$1) -> 0 | I20: =H20/D20 -> #DIV/0! | J20: =IFERROR(IF(D20/B20=0,"-",D20/B20),"-") -> - | K20: =SUMIFS('HORA HORA'!$K:$K,'HORA HORA'!$B:$B,'PJ_E1 (2)'!$A20,'HORA HORA'!$C:$C,"="&"PJ",'HORA HORA'!$Y:$Y,"<>"&"EMPRESAS_2")/SUMIFS('HORA HORA'!$J:$J,'HORA HORA'!$B:$B,'PJ_E1 (2)'!$A20,'HORA HORA'!$C:$C,"="&"PJ",'HORA HORA'!$Y:$Y,"<>"&"EMPRESAS_2") -> #DIV/0! | L20: =E20/D20 -> #DIV/0!
A21: 46092 | B21: =SUMIFS('HORA HORA'!J:J,'HORA HORA'!C:C,'PJ_E1 (2)'!$M$1,'HORA HORA'!B:B,'PJ_E1 (2)'!A21) -> 0 | C21: =SUMIFS('HORA HORA'!K:K,'HORA HORA'!C:C,'PJ_E1 (2)'!$M$1,'HORA HORA'!B:B,'PJ_E1 (2)'!A21) -> 0 | D21: =SUMIFS('HORA HORA'!L:L,'HORA HORA'!C:C,'PJ_E1 (2)'!$M$1,'HORA HORA'!B:B,'PJ_E1 (2)'!A21) -> 0 | E21: =COUNTIFS(ACOMPANHAMENTO!S:S,"ACORDO IMPLANTADO",ACOMPANHAMENTO!BC:BC,A21,ACOMPANHAMENTO!H:H,'PJ_E1 (2)'!$M$1) -> 0 | F21: =SUMIFS(ACOMPANHAMENTO!O:O,ACOMPANHAMENTO!H:H,'PJ_E1 (2)'!$M$1,ACOMPANHAMENTO!BC:BC,'PJ_E1 (2)'!A21) -> 0 | G21: =F21/D21 -> #DIV/0! | H21: =SUMIFS(ACOMPANHAMENTO!R:R,ACOMPANHAMENTO!BC:BC,'PJ_E1 (2)'!A21,ACOMPANHAMENTO!H:H,'PJ_E1 (2)'!$M$1) -> 0 | I21: =H21/D21 -> #DIV/0! | J21: =IFERROR(IF(D21/B21=0,"-",D21/B21),"-") -> - | K21: =SUMIFS('HORA HORA'!$K:$K,'HORA HORA'!$B:$B,'PJ_E1 (2)'!$A21,'HORA HORA'!$C:$C,"="&"PJ",'HORA HORA'!$Y:$Y,"<>"&"EMPRESAS_2")/SUMIFS('HORA HORA'!$J:$J,'HORA HORA'!$B:$B,'PJ_E1 (2)'!$A21,'HORA HORA'!$C:$C,"="&"PJ",'HORA HORA'!$Y:$Y,"<>"&"EMPRESAS_2") -> #DIV/0! | L21: =E21/D21 -> #DIV/0!
A22: 46093 | B22: =SUMIFS('HORA HORA'!J:J,'HORA HORA'!C:C,'PJ_E1 (2)'!$M$1,'HORA HORA'!B:B,'PJ_E1 (2)'!A22) -> 0 | C22: =SUMIFS('HORA HORA'!K:K,'HORA HORA'!C:C,'PJ_E1 (2)'!$M$1,'HORA HORA'!B:B,'PJ_E1 (2)'!A22) -> 0 | D22: =SUMIFS('HORA HORA'!L:L,'HORA HORA'!C:C,'PJ_E1 (2)'!$M$1,'HORA HORA'!B:B,'PJ_E1 (2)'!A22) -> 0 | E22: =COUNTIFS(ACOMPANHAMENTO!S:S,"ACORDO IMPLANTADO",ACOMPANHAMENTO!BC:BC,A22,ACOMPANHAMENTO!H:H,'PJ_E1 (2)'!$M$1) -> 0 | F22: =SUMIFS(ACOMPANHAMENTO!O:O,ACOMPANHAMENTO!H:H,'PJ_E1 (2)'!$M$1,ACOMPANHAMENTO!BC:BC,'PJ_E1 (2)'!A22) -> 0 | G22: =F22/D22 -> #DIV/0! | H22: =SUMIFS(ACOMPANHAMENTO!R:R,ACOMPANHAMENTO!BC:BC,'PJ_E1 (2)'!A22,ACOMPANHAMENTO!H:H,'PJ_E1 (2)'!$M$1) -> 0 | I22: =H22/D22 -> #DIV/0! | J22: =IFERROR(IF(D22/B22=0,"-",D22/B22),"-") -> - | K22: =SUMIFS('HORA HORA'!$K:$K,'HORA HORA'!$B:$B,'PJ_E1 (2)'!$A22,'HORA HORA'!$C:$C,"="&"PJ",'HORA HORA'!$Y:$Y,"<>"&"EMPRESAS_2")/SUMIFS('HORA HORA'!$J:$J,'HORA HORA'!$B:$B,'PJ_E1 (2)'!$A22,'HORA HORA'!$C:$C,"="&"PJ",'HORA HORA'!$Y:$Y,"<>"&"EMPRESAS_2") -> #DIV/0! | L22: =E22/D22 -> #DIV/0!
A23: 46094 | B23: =SUMIFS('HORA HORA'!J:J,'HORA HORA'!C:C,'PJ_E1 (2)'!$M$1,'HORA HORA'!B:B,'PJ_E1 (2)'!A23) -> 0 | C23: =SUMIFS('HORA HORA'!K:K,'HORA HORA'!C:C,'PJ_E1 (2)'!$M$1,'HORA HORA'!B:B,'PJ_E1 (2)'!A23) -> 0 | D23: =SUMIFS('HORA HORA'!L:L,'HORA HORA'!C:C,'PJ_E1 (2)'!$M$1,'HORA HORA'!B:B,'PJ_E1 (2)'!A23) -> 0 | E23: =COUNTIFS(ACOMPANHAMENTO!S:S,"ACORDO IMPLANTADO",ACOMPANHAMENTO!BC:BC,A23,ACOMPANHAMENTO!H:H,'PJ_E1 (2)'!$M$1) -> 0 | F23: =SUMIFS(ACOMPANHAMENTO!O:O,ACOMPANHAMENTO!H:H,'PJ_E1 (2)'!$M$1,ACOMPANHAMENTO!BC:BC,'PJ_E1 (2)'!A23) -> 0 | G23: =F23/D23 -> #DIV/0! | H23: =SUMIFS(ACOMPANHAMENTO!R:R,ACOMPANHAMENTO!BC:BC,'PJ_E1 (2)'!A23,ACOMPANHAMENTO!H:H,'PJ_E1 (2)'!$M$1) -> 0 | I23: =H23/D23 -> #DIV/0! | J23: =IFERROR(IF(D23/B23=0,"-",D23/B23),"-") -> - | K23: =SUMIFS('HORA HORA'!$K:$K,'HORA HORA'!$B:$B,'PJ_E1 (2)'!$A23,'HORA HORA'!$C:$C,"="&"PJ",'HORA HORA'!$Y:$Y,"<>"&"EMPRESAS_2")/SUMIFS('HORA HORA'!$J:$J,'HORA HORA'!$B:$B,'PJ_E1 (2)'!$A23,'HORA HORA'!$C:$C,"="&"PJ",'HORA HORA'!$Y:$Y,"<>"&"EMPRESAS_2") -> #DIV/0! | L23: =E23/D23 -> #DIV/0!
A24: 46097 | B24: =SUMIFS('HORA HORA'!J:J,'HORA HORA'!C:C,'PJ_E1 (2)'!$M$1,'HORA HORA'!B:B,'PJ_E1 (2)'!A24) -> 0 | C24: =SUMIFS('HORA HORA'!K:K,'HORA HORA'!C:C,'PJ_E1 (2)'!$M$1,'HORA HORA'!B:B,'PJ_E1 (2)'!A24) -> 0 | D24: =SUMIFS('HORA HORA'!L:L,'HORA HORA'!C:C,'PJ_E1 (2)'!$M$1,'HORA HORA'!B:B,'PJ_E1 (2)'!A24) -> 0 | E24: =COUNTIFS(ACOMPANHAMENTO!S:S,"ACORDO IMPLANTADO",ACOMPANHAMENTO!BC:BC,A24,ACOMPANHAMENTO!H:H,'PJ_E1 (2)'!$M$1) -> 0 | F24: =SUMIFS(ACOMPANHAMENTO!O:O,ACOMPANHAMENTO!H:H,'PJ_E1 (2)'!$M$1,ACOMPANHAMENTO!BC:BC,'PJ_E1 (2)'!A24) -> 0 | G24: =F24/D24 -> #DIV/0! | H24: =SUMIFS(ACOMPANHAMENTO!R:R,ACOMPANHAMENTO!BC:BC,'PJ_E1 (2)'!A24,ACOMPANHAMENTO!H:H,'PJ_E1 (2)'!$M$1) -> 0 | I24: =H24/D24 -> #DIV/0! | J24: =IFERROR(IF(D24/B24=0,"-",D24/B24),"-") -> - | K24: =SUMIFS('HORA HORA'!$K:$K,'HORA HORA'!$B:$B,'PJ_E1 (2)'!$A24,'HORA HORA'!$C:$C,"="&"PJ",'HORA HORA'!$Y:$Y,"<>"&"EMPRESAS_2")/SUMIFS('HORA HORA'!$J:$J,'HORA HORA'!$B:$B,'PJ_E1 (2)'!$A24,'HORA HORA'!$C:$C,"="&"PJ",'HORA HORA'!$Y:$Y,"<>"&"EMPRESAS_2") -> #DIV/0! | L24: =E24/D24 -> #DIV/0!
A25: 46098 | B25: =SUMIFS('HORA HORA'!J:J,'HORA HORA'!C:C,'PJ_E1 (2)'!$M$1,'HORA HORA'!B:B,'PJ_E1 (2)'!A25) -> 0 | C25: =SUMIFS('HORA HORA'!K:K,'HORA HORA'!C:C,'PJ_E1 (2)'!$M$1,'HORA HORA'!B:B,'PJ_E1 (2)'!A25) -> 0 | D25: =SUMIFS('HORA HORA'!L:L,'HORA HORA'!C:C,'PJ_E1 (2)'!$M$1,'HORA HORA'!B:B,'PJ_E1 (2)'!A25) -> 0 | E25: =COUNTIFS(ACOMPANHAMENTO!S:S,"ACORDO IMPLANTADO",ACOMPANHAMENTO!BC:BC,A25,ACOMPANHAMENTO!H:H,'PJ_E1 (2)'!$M$1) -> 0 | F25: =SUMIFS(ACOMPANHAMENTO!O:O,ACOMPANHAMENTO!H:H,'PJ_E1 (2)'!$M$1,ACOMPANHAMENTO!BC:BC,'PJ_E1 (2)'!A25) -> 0 | G25: =F25/D25 -> #DIV/0! | H25: =SUMIFS(ACOMPANHAMENTO!R:R,ACOMPANHAMENTO!BC:BC,'PJ_E1 (2)'!A25,ACOMPANHAMENTO!H:H,'PJ_E1 (2)'!$M$1) -> 0 | I25: =H25/D25 -> #DIV/0! | J25: =IFERROR(IF(D25/B25=0,"-",D25/B25),"-") -> - | K25: =SUMIFS('HORA HORA'!$K:$K,'HORA HORA'!$B:$B,'PJ_E1 (2)'!$A25,'HORA HORA'!$C:$C,"="&"PJ",'HORA HORA'!$Y:$Y,"<>"&"EMPRESAS_2")/SUMIFS('HORA HORA'!$J:$J,'HORA HORA'!$B:$B,'PJ_E1 (2)'!$A25,'HORA HORA'!$C:$C,"="&"PJ",'HORA HORA'!$Y:$Y,"<>"&"EMPRESAS_2") -> #DIV/0! | L25: =E25/D25 -> #DIV/0!
... A35: 46112 | B35: =SUMIFS('HORA HORA'!J:J,'HORA HORA'!C:C,'PJ_E1 (2)'!$M$1,'HORA HORA'!B:B,'PJ_E1 (2)'!A35) -> 0 | C35: =SUMIFS('HORA HORA'!K:K,'HORA HORA'!C:C,'PJ_E1 (2)'!$M$1,'HORA HORA'!B:B,'PJ_E1 (2)'!A35) -> 0 | D35: =SUMIFS('HORA HORA'!L:L,'HORA HORA'!C:C,'PJ_E1 (2)'!$M$1,'HORA HORA'!B:B,'PJ_E1 (2)'!A35) -> 0 | E35: =COUNTIFS(ACOMPANHAMENTO!S:S,"ACORDO IMPLANTADO",ACOMPANHAMENTO!BC:BC,A35,ACOMPANHAMENTO!H:H,'PJ_E1 (2)'!$M$1) -> 0 | F35: =SUMIFS(ACOMPANHAMENTO!O:O,ACOMPANHAMENTO!H:H,'PJ_E1 (2)'!$M$1,ACOMPANHAMENTO!BC:BC,'PJ_E1 (2)'!A35) -> 0 | G35: =F35/D35 -> #DIV/0! | H35: =SUMIFS(ACOMPANHAMENTO!R:R,ACOMPANHAMENTO!BC:BC,'PJ_E1 (2)'!A35,ACOMPANHAMENTO!H:H,'PJ_E1 (2)'!$M$1) -> 0 | I35: =H35/D35 -> #DIV/0! | J35: =IFERROR(IF(D35/B35=0,"-",D35/B35),"-") -> - | K35: =SUMIFS('HORA HORA'!$K:$K,'HORA HORA'!$B:$B,'PJ_E1 (2)'!$A35,'HORA HORA'!$C:$C,"="&"PJ",'HORA HORA'!$Y:$Y,"<>"&"EMPRESAS_2")/SUMIFS('HORA HORA'!$J:$J,'HORA HORA'!$B:$B,'PJ_E1 (2)'!$A35,'HORA HORA'!$C:$C,"="&"PJ",'HORA HORA'!$Y:$Y,"<>"&"EMPRESAS_2") -> #DIV/0! | L35: =E35/D35 -> #DIV/0!

Sheet BD DISCADOR
A1: Data | B1: HORA OK | C1: Campanha | D1: Status_Telefonia | E1: ACIONADO | F1: ATENDIDO | G1: ALÔ | H1: CPC | I1: CPC-A | J1: PROPOSTA | K1: % CPC
A2: 46268 | B2: 11 | C2: SANTANDER_E1_PJ_04 | D2: DNA | E2: 216 | F2: 0 | G2: 0 | H2: 0 | I2: 0 | J2: 0
A3: 46267 | B3: 11 | C3: SANTANDER_E1_PJ_03 | D3: DVC | E3: 42 | F3: 0 | G3: 0 | H3: 0 | I3: 0 | J3: 0
A4: 46274 | B4: 9 | C4: SANTANDER_E1_PJ_05 | D4: DAC | E4: 4 | F4: 4 | G4: 0 | H4: 0 | I4: 0 | J4: 0
A5: 46276 | B5: 16 | C5: SANTANDER_PF_01 | D5: NR | E5: 0 | F5: 0 | G5: 0 | H5: 0 | I5: 0 | J5: 0
A6: 46269 | B6: 14 | C6: SANTANDER_PF_03 | D6: NVD | E6: 120 | F6: 0 | G6: 0 | H6: 0 | I6: 0 | J6: 0
A7: 46267 | B7: 13 | C7: SANTANDER_E1_PJ_06 | D7: RR | E7: 0 | F7: 0 | G7: 0 | H7: 0 | I7: 0 | J7: 0
A8: 46275 | B8: 14 | C8: SANTANDER_E2_PJ_02 | D8: NVD | E8: 42 | F8: 0 | G8: 0 | H8: 0 | I8: 0 | J8: 0
A9: 46268 | B9: 15 | C9: SANTANDER_E2_PJ_02 | D9: DVC | E9: 25 | F9: 0 | G9: 0 | H9: 0 | I9: 0 | J9: 0
A10: 46275 | B10: 14 | C10: BRADESCO_02 | D10: SW_DBS | E10: 7 | F10: 0 | G10: 0 | H10: 0 | I10: 0 | J10: 0
A11: 46276 | B11: 10 | C11: BRADESCO_01 | D11: DVC | E11: 117 | F11: 0 | G11: 0 | H11: 0 | I11: 0 | J11: 0
A12: 46266 | B12: 8 | C12: SANTANDER_PF_01 | D12: RR | E12: 0 | F12: 0 | G12: 0 | H12: 0 | I12: 0 | J12: 0
A13: 46273 | B13: 10 | C13: SANTANDER_E1_PJ_06 | D13: DCB | E13: 1 | F13: 0 | G13: 0 | H13: 0 | I13: 0 | J13: 0
... A530: 46269 | B530: 16 | C530: SANTANDER_E2_PJ_02 | D530: SW_DBS | E530: 125 | F530: 0 | G530: 0 | H530: 0 | I530: 0 | J530: 0
A531: 46267 | B531: 8 | C531: BRADESCO_02 | D531: RR | E531: 0 | F531: 0 | G531: 0 | H531: 0 | I531: 0 | J531: 0 | K531: =IFERROR(AVERAGE(H531/F531),"")
A532: 46269 | B532: 15 | C532: BRADESCO_02 | D532: DAM | E532: 4 | F532: 0 | G532: 0 | H532: 0 | I532: 0 | J532: 0 | K532: =IFERROR(AVERAGE(H532/F532),"")
A533: 46273 | B533: 11 | C533: SANTANDER_E2_PJ_02 | D533: TZ | E533: 0 | F533: 0 | G533: 0 | H533: 0 | I533: 0 | J533: 0 | K533: =IFERROR(AVERAGE(H533/F533),"")
A534: 46268 | B534: 15 | C534: SANTANDER_PF_01 | D534: DNR | E534: 8 | F534: 0 | G534: 0 | H534: 0 | I534: 0 | J534: 0 | K534: =IFERROR(AVERAGE(H534/F534),"")
A535: 46266 | B535: 14 | C535: SANTANDER_PF_02 | D535: NR | E535: 0 | F535: 0 | G535: 0 | H535: 0 | I535: 0 | J535: 0 | K535: =IFERROR(AVERAGE(H535/F535),"")
A536: 46268 | B536: 15 | C536: SANTANDER_E1_PJ_03 | D536: NVD | E536: 62 | F536: 0 | G536: 0 | H536: 0 | I536: 0 | J536: 0 | K536: =IFERROR(AVERAGE(H536/F536),"")
A537: 46273 | B537: 12 | C537: SANTANDER_PF_03 | D537: DAM | E537: 271 | F537: 0 | G537: 0 | H537: 0 | I537: 0 | J537: 0 | K537: =IFERROR(AVERAGE(H537/F537),"")
A538: 46275 | B538: 15 | C538: SANTANDER_E1_PJ_05 | D538: DNR | E538: 4 | F538: 0 | G538: 0 | H538: 0 | I538: 0 | J538: 0 | K538: =IFERROR(AVERAGE(H538/F538),"")
A539: 46268 | B539: 11 | C539: SANTANDER_E2_PJ_02 | D539: DNR | E539: 10 | F539: 0 | G539: 0 | H539: 0 | I539: 0 | J539: 0 | K539: =IFERROR(AVERAGE(H539/F539),"")
A540: 46267 | B540: 8 | C540: SANTANDER_E2_PJ_02 | D540: DNC | E540: 1 | F540: 0 | G540: 0 | H540: 0 | I540: 0 | J540: 0 | K540: =IFERROR(AVERAGE(H540/F540),"")
A541: 46273 | B541: 15 | C541: SANTANDER_PF_03 | D541: DRO | E541: 23 | F541: 0 | G541: 0 | H541: 0 | I541: 0 | J541: 0 | K541: =IFERROR(AVERAGE(H541/F541),"")
A542: 46274 | B542: 9 | C542: SANTANDER_E1_PJ_04 | D542: DBU | E542: 1 | F542: 0 | G542: 0 | H542: 0 | I542: 0 | J542: 0 | K542: =IFERROR(AVERAGE(H542/F542),"")
... A620: 46269 | B620: 14 | C620: BRADESCO_01 | D620: ATENDIDO | E620: 14 | F620: 14 | G620: 0 | H620: 14 | I620: 0 | J620: 0 | K620: =IFERROR(AVERAGE(H620/F620),"") -> 1
A621: 46276 | B621: 16 | C621: SANTANDER_E1_PJ_01 | D621: DCB | E621: 1 | F621: 0 | G621: 0 | H621: 0 | I621: 0 | J621: 0
A622: 46269 | B622: 11 | C622: SANTANDER_E1_PJ_03 | D622: DAM | E622: 278 | F622: 0 | G622: 0 | H622: 0 | I622: 0 | J622: 0
A623: 46274 | B623: 10 | C623: BRADESCO_02 | D623: DNC | E623: 1 | F623: 0 | G623: 0 | H623: 0 | I623: 0 | J623: 0
A624: 46268 | B624: 11 | C624: SANTANDER_E1_PJ_02 | D624: DAC | E624: 2 | F624: 2 | G624: 0 | H624: 0 | I624: 0 | J624: 0
A625: 46275 | B625: 13 | C625: SANTANDER_E1_PJ_04 | D625: DAM | E625: 180 | F625: 0 | G625: 0 | H625: 0 | I625: 0 | J625: 0
A626: 46267 | B626: 15 | C626: SANTANDER_PF_01 | D626: DRO | E626: 61 | F626: 0 | G626: 0 | H626: 0 | I626: 0 | J626: 0
A627: 46267 | B627: 11 | C627: SANTANDER_E1_PJ_04 | D627: NAN | E627: 107 | F627: 0 | G627: 0 | H627: 0 | I627: 0 | J627: 0
A628: 46275 | B628: 12 | C628: SANTANDER_E1_PJ_01 | D628: ATENDIDO | E628: 1 | F628: 1 | G628: 1 | H628: 0 | I628: 0 | J628: 0
A629: 46273 | B629: 10 | C629: SANTANDER_E1_PJ_04 | D629: SW_DBS | E629: 801 | F629: 0 | G629: 0 | H629: 0 | I629: 0 | J629: 0
A630: 46267 | B630: 9 | C630: SANTANDER_PF_01 | D630: DVC | E630: 214 | F630: 0 | G630: 0 | H630: 0 | I630: 0 | J630: 0
A631: 46266 | B631: 10 | C631: SANTANDER_E2_PJ_03 | D631: CC_NRT | E631: 2 | F631: 0 | G631: 0 | H631: 0 | I631: 0 | J631: 0
A632: 46275 | B632: 10 | C632: SANTANDER_E1_PJ_01 | D632: CC_NRT | E632: 2 | F632: 0 | G632: 0 | H632: 0 | I632: 0 | J632: 0
... A11944: 46267 | B11944: 10 | C11944: COOPERFORTE_02 | D11944: NR | E11944: 0 | F11944: 0 | G11944: 0 | H11944: 0 | I11944: 0 | J11944: 0

Sheet TEMPOS
G1: 1 | U1: 1 | Y1: =A1*1 -> 0 | Z1: =B1&"."&Y1 -> .0 | AA1: =SUMIFS([1]!Consulta1[CONTADOR],[1]!Consulta1[CONCATENADO],[1]BD!Z1) -> #REF! | AB1: =IF(B1="RSTASPECTAGENT","NÃO","SIM") -> SIM | AC1: =VLOOKUP(A1*1,[1]AUX!B:D,3,0) -> #N/A | AD1: =VLOOKUP(C1,[1]AUX!J:K,2,0) -> #N/A | AE1: =SUM(AH1:AK1) -> 1 | AF1: =E1*1-D1*1 -> 0 | AG1: =IF(IF(AE1>AF1,0,AF1-AE1)<0,0,IF(AE1>AF1,0,AF1-AE1)) -> 0 | AH1: =J1*1 -> 0 | AI1: =L1*1 -> 0 | AJ1: =I1*1 -> 0 | AK1: =SUM(M1*1,N1*1,O1*1,P1*1,Q1*1,R1*1,S1*1,T1*1,U1*1,V1*1,W1*1) -> 1 | AL1: =SUM(AH1:AJ1) -> 0 | AM1: =SUM(S1*1,T1*1,U1*1) -> 1 | AN1: =AK1-AM1 -> 0
A2: DATA | B2: LOGIN_AGENTE | C2: WORKGROUP_NAME | D2: LOGIN | E2: LOGOUT | F2: LOGADO | G2: QTD | H2: DESLOGADO | I2: OCIOSO | J2: EM ATENDIMENTO | K2: QTD. ATENDIMENTO | L2: POS ATENDIMENTO | M2: ADM - FEEDBACK | N2: ADM - GINASTICA LABORAL | O2: ADM - PESSOAL | P2: ADM - TREINAMENTO | Q2: BANHEIRO | R2: ESTACIONAR | S2: NR17 - ALMOCO | T2: NR17 - DESCANSO 1 | U2: NR17 - DESCANSO 2 | V2: REUNIAO | W2: BOLETO | X2: SEGMENTO | Y2: DATA AJUSTADA | Z2: CONCATENADO | AA2: FOLLOW | AB2: VALIDADOR | AC2: DIA UTIL | AD2: CARTEIRA | AE2: TEMPO LOGADO | AF2: TEMPO NA EMPRESA | AG2: FORA DISCADOR | AH2: FALADO | AI2: PÓS | AJ2: IDLE | AK2: PAUSA | AL2: DISPONIVEL | AM2: NR17 | AN2: OUTRAS PAUSA | AO2: SEGMENTO
A3: 2026-09-04 | B3: FELIPEFERREIRA | C3: VP_STD_PF_MANUAL | D3: 0.356863 | E3: 0.695961 | F3: 0.339097 | G3: 1 | H3: 2.3e-05 | I3: 0.058623 | J3: 0.011285 | K3: 48 | L3: 0.010336 | M3: 0 | N3: 0 | O3: 0 | P3: 0 | Q3: 0.002685 | R3: 0.179873 | S3: 0.042523 | T3: 0.007731 | U3: 0.00794 | V3: 0.018079 | W3: 0 | X3: PF | Y3: =A3*1 -> 46269 | Z3: =B3&"."&Y3 -> FELIPEFERREIRA.46269 | AA3: =SUMIFS([2]!Consulta1[CONTADOR],[2]!Consulta1[CONCATENADO],[2]BD!Z3) -> 48 | AB3: =IF(B3="RSTASPECTAGENT","NÃO","SIM") -> SIM | AC3: =VLOOKUP(A3*1,[2]AUX!B:D,3,0) -> 4 | AD3: =VLOOKUP(C3,[2]AUX!J:K,2,0) -> SANTANDER | AE3: =SUM(AH3:AK3) -> 0.339075 | AF3: =E3*1-D3*1 -> 0.339098 | AG3: =IF(IF(AE3>AF3,0,AF3-AE3)<0,0,IF(AE3>AF3,0,AF3-AE3)) -> 2.3e-05 | AH3: =J3*1 -> 0.011285 | AI3: =L3*1 -> 0.010336 | AJ3: =I3*1 -> 0.058623 | AK3: =SUM(M3*1,N3*1,O3*1,P3*1,Q3*1,R3*1,S3*1,T3*1,U3*1,V3*1,W3*1) -> 0.258831 | AL3: =SUM(AH3:AJ3) -> 0.080244 | AM3: =SUM(S3*1,T3*1,U3*1) -> 0.058194 | AN3: =AK3-AM3 -> 0.200637
A4: 2026-09-01 | B4: SABRINAERLLEN | C4: VP_STD_PJ_MANUAL | D4: 0.363264 | E4: 0.695613 | F4: 0.331516 | G4: 2 | H4: 0.000868 | I4: 0.018738 | J4: 0.022106 | K4: 43 | L4: 0.009387 | M4: 0 | N4: 0 | O4: 0 | P4: 0.006875 | Q4: 0.014468 | R4: 0.203333 | S4: 0.041701 | T4: 0.007361 | U4: 0.007512 | V4: 0 | W4: 0 | X4: B1 | Y4: =A4*1 -> 46266 | Z4: =B4&"."&Y4 -> SABRINAERLLEN.46266 | AA4: =SUMIFS([2]!Consulta1[CONTADOR],[2]!Consulta1[CONCATENADO],[2]BD!Z4) -> 43 | AB4: =IF(B4="RSTASPECTAGENT","NÃO","SIM") -> SIM | AC4: =VLOOKUP(A4*1,[2]AUX!B:D,3,0) -> 1 | AD4: =VLOOKUP(C4,[2]AUX!J:K,2,0) -> SANTANDER | AE4: =SUM(AH4:AK4) -> 0.331481 | AF4: =E4*1-D4*1 -> 0.332349 | AG4: =IF(IF(AE4>AF4,0,AF4-AE4)<0,0,IF(AE4>AF4,0,AF4-AE4)) -> 0.000868 | AH4: =J4*1 -> 0.022106 | AI4: =L4*1 -> 0.009387 | AJ4: =I4*1 -> 0.018738 | AK4: =SUM(M4*1,N4*1,O4*1,P4*1,Q4*1,R4*1,S4*1,T4*1,U4*1,V4*1,W4*1) -> 0.28125 | AL4: =SUM(AH4:AJ4) -> 0.050231 | AM4: =SUM(S4*1,T4*1,U4*1) -> 0.056574 | AN4: =AK4-AM4 -> 0.224676 | AO4: PF
A5: 2026-09-04 | B5: CLAUDIABARREIRA | C5: VP_BRAD_01 | D5: 0.341794 | E5: 0.711157 | F5: 0.351181 | G5: 4 | H5: 0.035093 | I5: 0.015475 | J5: 0.000625 | K5: 35 | L5: 0.004248 | M5: 0 | N5: 0 | O5: 0 | P5: 0 | Q5: 0 | R5: 0.257882 | S5: 0.042106 | T5: 0.007199 | U5: 0.006736 | V5: 0 | W5: 0 | Y5: =A5*1 -> 46269 | Z5: =B5&"."&Y5 -> CLAUDIABARREIRA.46269 | AA5: =SUMIFS([2]!Consulta1[CONTADOR],[2]!Consulta1[CONCATENADO],[2]BD!Z5) -> 35 | AB5: =IF(B5="RSTASPECTAGENT","NÃO","SIM") -> SIM | AC5: =VLOOKUP(A5*1,[2]AUX!B:D,3,0) -> 4 | AD5: =VLOOKUP(C5,[2]AUX!J:K,2,0) -> BRADESCO | AE5: =SUM(AH5:AK5) -> 0.334271 | AF5: =E5*1-D5*1 -> 0.369363 | AG5: =IF(IF(AE5>AF5,0,AF5-AE5)<0,0,IF(AE5>AF5,0,AF5-AE5)) -> 0.035092 | AH5: =J5*1 -> 0.000625 | AI5: =L5*1 -> 0.004248 | AJ5: =I5*1 -> 0.015475 | AK5: =SUM(M5*1,N5*1,O5*1,P5*1,Q5*1,R5*1,S5*1,T5*1,U5*1,V5*1,W5*1) -> 0.313923 | AL5: =SUM(AH5:AJ5) -> 0.020348 | AM5: =SUM(S5*1,T5*1,U5*1) -> 0.056041 | AN5: =AK5-AM5 -> 0.257882
A6: 2026-09-02 | B6: BEATRIZPARENTE | C6: VP_STD_PJ_DISCADOR | D6: 0.363808 | E6: 0.695891 | F6: 0.332083 | G6: 1 | H6: 0.000255 | I6: 0.147141 | J6: 0.04397 | K6: 128 | L6: 0.023264 | M6: 0.011644 | N6: 0.007975 | O6: 0 | P6: 0 | Q6: 0.024063 | R6: 0 | S6: 0.04265 | T6: 0.008461 | U6: 0.007269 | V6: 0.005185 | W6: 0.010208 | X6: B1 | Y6: =A6*1 -> 46267 | Z6: =B6&"."&Y6 -> BEATRIZPARENTE.46267 | AA6: =SUMIFS([2]!Consulta1[CONTADOR],[2]!Consulta1[CONCATENADO],[2]BD!Z6) -> 0 | AB6: =IF(B6="RSTASPECTAGENT","NÃO","SIM") -> SIM | AC6: =VLOOKUP(A6*1,[2]AUX!B:D,3,0) -> 2 | AD6: =VLOOKUP(C6,[2]AUX!J:K,2,0) -> SANTANDER | AE6: =SUM(AH6:AK6) -> 0.33183 | AF6: =E6*1-D6*1 -> 0.332083 | AG6: =IF(IF(AE6>AF6,0,AF6-AE6)<0,0,IF(AE6>AF6,0,AF6-AE6)) -> 0.000253 | AH6: =J6*1 -> 0.04397 | AI6: =L6*1 -> 0.023264 | AJ6: =I6*1 -> 0.147141 | AK6: =SUM(M6*1,N6*1,O6*1,P6*1,Q6*1,R6*1,S6*1,T6*1,U6*1,V6*1,W6*1) -> 0.117455 | AL6: =SUM(AH6:AJ6) -> 0.214375 | AM6: =SUM(S6*1,T6*1,U6*1) -> 0.05838 | AN6: =AK6-AM6 -> 0.059075
A7: 2026-09-08 | B7: MAIARACOSTA | C7: VP_STD_PF_DISCADOR | D7: 0.351759 | E7: 0.695613 | F7: 0.343854 | G7: 1 | H7: 0 | I7: 0.219097 | J7: 0.024977 | K7: 94 | L7: 0.017535 | M7: 0 | N7: 0 | O7: 0 | P7: 0 | Q7: 0.020903 | R7: 0 | S7: 0.042338 | T7: 0.007465 | U7: 0.007373 | V7: 0.00434 | W7: 0 | X7: PF | Y7: =A7*1 -> 46273 | Z7: =B7&"."&Y7 -> MAIARACOSTA.46273 | AA7: =SUMIFS([2]!Consulta1[CONTADOR],[2]!Consulta1[CONCATENADO],[2]BD!Z7) -> 0 | AB7: =IF(B7="RSTASPECTAGENT","NÃO","SIM") -> SIM | AC7: =VLOOKUP(A7*1,[2]AUX!B:D,3,0) -> 5 | AD7: =VLOOKUP(C7,[2]AUX!J:K,2,0) -> SANTANDER | AE7: =SUM(AH7:AK7) -> 0.344028 | AF7: =E7*1-D7*1 -> 0.343854 | AG7: =IF(IF(AE7>AF7,0,AF7-AE7)<0,0,IF(AE7>AF7,0,AF7-AE7)) -> 0 | AH7: =J7*1 -> 0.024977 | AI7: =L7*1 -> 0.017535 | AJ7: =I7*1 -> 0.219097 | AK7: =SUM(M7*1,N7*1,O7*1,P7*1,Q7*1,R7*1,S7*1,T7*1,U7*1,V7*1,W7*1) -> 0.082419 | AL7: =SUM(AH7:AJ7) -> 0.261609 | AM7: =SUM(S7*1,T7*1,U7*1) -> 0.057176 | AN7: =AK7-AM7 -> 0.025243 | AO7: PF
A8: 2026-09-08 | B8: KATIAMORAIS | C8: VP_BRAD_01 | D8: 0.35162 | E8: 0.697928 | F8: 0.346308 | G8: 1 | H8: 5.8e-05 | I8: 0.041944 | J8: 0.012859 | K8: 74 | L8: 0.002627 | M8: 0 | N8: 0 | O8: 0 | P8: 0 | Q8: 0.001516 | R8: 0.229479 | S8: 0.043183 | T8: 0.007697 | U8: 0.006944 | V8: 0 | W8: 0 | Y8: =A8*1 -> 46273 | Z8: =B8&"."&Y8 -> KATIAMORAIS.46273 | AA8: =SUMIFS([2]!Consulta1[CONTADOR],[2]!Consulta1[CONCATENADO],[2]BD!Z8) -> 74 | AB8: =IF(B8="RSTASPECTAGENT","NÃO","SIM") -> SIM | AC8: =VLOOKUP(A8*1,[2]AUX!B:D,3,0) -> 5 | AD8: =VLOOKUP(C8,[2]AUX!J:K,2,0) -> BRADESCO | AE8: =SUM(AH8:AK8) -> 0.346249 | AF8: =E8*1-D8*1 -> 0.346308 | AG8: =IF(IF(AE8>AF8,0,AF8-AE8)<0,0,IF(AE8>AF8,0,AF8-AE8)) -> 5.9e-05 | AH8: =J8*1 -> 0.012859 | AI8: =L8*1 -> 0.002627 | AJ8: =I8*1 -> 0.041944 | AK8: =SUM(M8*1,N8*1,O8*1,P8*1,Q8*1,R8*1,S8*1,T8*1,U8*1,V8*1,W8*1) -> 0.288819 | AL8: =SUM(AH8:AJ8) -> 0.05743 | AM8: =SUM(S8*1,T8*1,U8*1) -> 0.057824 | AN8: =AK8-AM8 -> 0.230995
A9: 2026-09-10 | B9: ADAILTONBERNARDO | C9: VP_STD_PJ_MANUAL | D9: 0.594236 | E9: 0.695694 | F9: 0.101458 | G9: 1 | H9: 1.2e-05 | I9: 0.005382 | J9: 0.000521 | K9: 26 | L9: 0.001852 | M9: 0 | N9: 0 | O9: 0 | P9: 0 | Q9: 0.001944 | R9: 0.082384 | S9: 0 | T9: 0 | U9: 0.009363 | V9: 0 | W9: 0 | X9: B2 | Y9: =A9*1 -> 46275 | Z9: =B9&"."&Y9 -> ADAILTONBERNARDO.46275 | AA9: =SUMIFS([2]!Consulta1[CONTADOR],[2]!Consulta1[CONCATENADO],[2]BD!Z9) -> 26 | AB9: =IF(B9="RSTASPECTAGENT","NÃO","SIM") -> SIM | AC9: =VLOOKUP(A9*1,[2]AUX!B:D,3,0) -> 7 | AD9: =VLOOKUP(C9,[2]AUX!J:K,2,0) -> SANTANDER | AE9: =SUM(AH9:AK9) -> 0.101446 | AF9: =E9*1-D9*1 -> 0.101458 | AG9: =IF(IF(AE9>AF9,0,AF9-AE9)<0,0,IF(AE9>AF9,0,AF9-AE9)) -> 1.2e-05 | AH9: =J9*1 -> 0.000521 | AI9: =L9*1 -> 0.001852 | AJ9: =I9*1 -> 0.005382 | AK9: =SUM(M9*1,N9*1,O9*1,P9*1,Q9*1,R9*1,S9*1,T9*1,U9*1,V9*1,W9*1) -> 0.093691 | AL9: =SUM(AH9:AJ9) -> 0.007755 | AM9: =SUM(S9*1,T9*1,U9*1) -> 0.009363 | AN9: =AK9-AM9 -> 0.084328 | AO9: B2
A10: 2026-09-02 | B10: SAMIAAGOSTINHO | C10: VP_BRAD_01 | D10: 0.359201 | E10: 0.695694 | F10: 0.336493 | G10: 1 | H10: 1.2e-05 | I10: 0.025243 | J10: 0.003935 | K10: 46 | L10: 0.004086 | M10: 0 | N10: 0 | O10: 0 | P10: 0 | Q10: 0 | R10: 0.245174 | S10: 0.042894 | T10: 0.008229 | U10: 0.006921 | V10: 0 | W10: 0 | Y10: =A10*1 -> 46267 | Z10: =B10&"."&Y10 -> SAMIAAGOSTINHO.46267 | AA10: =SUMIFS([2]!Consulta1[CONTADOR],[2]!Consulta1[CONCATENADO],[2]BD!Z10) -> 46 | AB10: =IF(B10="RSTASPECTAGENT","NÃO","SIM") -> SIM | AC10: =VLOOKUP(A10*1,[2]AUX!B:D,3,0) -> 2 | AD10: =VLOOKUP(C10,[2]AUX!J:K,2,0) -> BRADESCO | AE10: =SUM(AH10:AK10) -> 0.336482 | AF10: =E10*1-D10*1 -> 0.336493 | AG10: =IF(IF(AE10>AF10,0,AF10-AE10)<0,0,IF(AE10>AF10,0,AF10-AE10)) -> 1.1e-05 | AH10: =J10*1 -> 0.003935 | AI10: =L10*1 -> 0.004086 | AJ10: =I10*1 -> 0.025243 | AK10: =SUM(M10*1,N10*1,O10*1,P10*1,Q10*1,R10*1,S10*1,T10*1,U10*1,V10*1,W10*1) -> 0.303218 | AL10: =SUM(AH10:AJ10) -> 0.033264 | AM10: =SUM(S10*1,T10*1,U10*1) -> 0.058044 | AN10: =AK10-AM10 -> 0.245174 | AO10: B2
A11: 2026-09-02 | B11: SAMIANASCIMENTO | C11: VP_COOPER_01 | D11: 0.354387 | E11: 0.695752 | F11: 0.341366 | G11: 1 | H11: 0 | I11: 0.066794 | J11: 0.012778 | K11: 59 | L11: 0.014734 | M11: 0 | N11: 0 | O11: 0 | P11: 0 | Q11: 0.008345 | R11: 0.185602 | S11: 0.044444 | T11: 0.008738 | U11: 0 | V11: 0 | W11: 0 | Y11: =A11*1 -> 46267 | Z11: =B11&"."&Y11 -> SAMIANASCIMENTO.46267 | AA11: =SUMIFS([2]!Consulta1[CONTADOR],[2]!Consulta1[CONCATENADO],[2]BD!Z11) -> 59 | AB11: =IF(B11="RSTASPECTAGENT","NÃO","SIM") -> SIM | AC11: =VLOOKUP(A11*1,[2]AUX!B:D,3,0) -> 2 | AD11: =VLOOKUP(C11,[2]AUX!J:K,2,0) -> COOPERFORTE | AE11: =SUM(AH11:AK11) -> 0.341435 | AF11: =E11*1-D11*1 -> 0.341365 | AG11: =IF(IF(AE11>AF11,0,AF11-AE11)<0,0,IF(AE11>AF11,0,AF11-AE11)) -> 0 | AH11: =J11*1 -> 0.012778 | AI11: =L11*1 -> 0.014734 | AJ11: =I11*1 -> 0.066794 | AK11: =SUM(M11*1,N11*1,O11*1,P11*1,Q11*1,R11*1,S11*1,T11*1,U11*1,V11*1,W11*1) -> 0.247129 | AL11: =SUM(AH11:AJ11) -> 0.094306 | AM11: =SUM(S11*1,T11*1,U11*1) -> 0.053182 | AN11: =AK11-AM11 -> 0.193947
A12: 2026-09-01 | B12: GABRIELACRUZ | C12: VP_STD_PF_DISCADOR | D12: 0.355394 | E12: 0.698669 | F12: 0.335764 | G12: 5 | H12: 0.007593 | I12: 0.159109 | J12: 0.033623 | K12: 78 | L12: 0.022685 | M12: 0.011146 | N12: 0 | O12: 0 | P12: 0.006424 | Q12: 0.01919 | R12: 0 | S12: 0.041574 | T12: 0.007025 | U12: 0.007743 | V12: 0.027164 | W12: 0 | X12: PF | Y12: =A12*1 -> 46266 | Z12: =B12&"."&Y12 -> GABRIELACRUZ.46266 | AA12: =SUMIFS([2]!Consulta1[CONTADOR],[2]!Consulta1[CONCATENADO],[2]BD!Z12) -> 0 | AB12: =IF(B12="RSTASPECTAGENT","NÃO","SIM") -> SIM | AC12: =VLOOKUP(A12*1,[2]AUX!B:D,3,0) -> 1 | AD12: =VLOOKUP(C12,[2]AUX!J:K,2,0) -> SANTANDER | AE12: =SUM(AH12:AK12) -> 0.335683 | AF12: =E12*1-D12*1 -> 0.343275 | AG12: =IF(IF(AE12>AF12,0,AF12-AE12)<0,0,IF(AE12>AF12,0,AF12-AE12)) -> 0.007592 | AH12: =J12*1 -> 0.033623 | AI12: =L12*1 -> 0.022685 | AJ12: =I12*1 -> 0.159109 | AK12: =SUM(M12*1,N12*1,O12*1,P12*1,Q12*1,R12*1,S12*1,T12*1,U12*1,V12*1,W12*1) -> 0.120266 | AL12: =SUM(AH12:AJ12) -> 0.215417 | AM12: =SUM(S12*1,T12*1,U12*1) -> 0.056342 | AN12: =AK12-AM12 -> 0.063924 | AO12: B2
A13: 2026-09-04 | B13: MARLEYALVES | C13: VP_BRAD_01 | D13: 0.364641 | E13: 0.699213 | F13: 0.333032 | G13: 4 | H13: 0.004815 | I13: 0.059282 | J13: 0.00522 | K13: 40 | L13: 0.010938 | M13: 0 | N13: 0 | O13: 0 | P13: 0 | Q13: 0.014792 | R13: 0.181933 | S13: 0.042153 | T13: 0.007674 | U13: 0.007766 | V13: 0 | W13: 0 | Y13: =A13*1 -> 46269 | Z13: =B13&"."&Y13 -> MARLEYALVES.46269 | AA13: =SUMIFS([2]!Consulta1[CONTADOR],[2]!Consulta1[CONCATENADO],[2]BD!Z13) -> 40 | AB13: =IF(B13="RSTASPECTAGENT","NÃO","SIM") -> SIM | AC13: =VLOOKUP(A13*1,[2]AUX!B:D,3,0) -> 4 | AD13: =VLOOKUP(C13,[2]AUX!J:K,2,0) -> BRADESCO | AE13: =SUM(AH13:AK13) -> 0.329758 | AF13: =E13*1-D13*1 -> 0.334572 | AG13: =IF(IF(AE13>AF13,0,AF13-AE13)<0,0,IF(AE13>AF13,0,AF13-AE13)) -> 0.004814 | AH13: =J13*1 -> 0.00522 | AI13: =L13*1 -> 0.010938 | AJ13: =I13*1 -> 0.059282 | AK13: =SUM(M13*1,N13*1,O13*1,P13*1,Q13*1,R13*1,S13*1,T13*1,U13*1,V13*1,W13*1) -> 0.254318 | AL13: =SUM(AH13:AJ13) -> 0.07544 | AM13: =SUM(S13*1,T13*1,U13*1) -> 0.057593 | AN13: =AK13-AM13 -> 0.196725 | AO13: B1
A14: 2026-09-02 | B14: CLAUDIAVALERO | C14: VP_BRAD_01 | D14: 0.334144 | E14: 0.695567 | F14: 0.341019 | G14: 3 | H14: 0.020463 | I14: 0.041435 | J14: 0.012292 | K14: 58 | L14: 0.009572 | M14: 0 | N14: 0 | O14: 0 | P14: 0 | Q14: 0 | R14: 0.220278 | S14: 0.041505 | T14: 0.009387 | U14: 0.006493 | V14: 0 | W14: 0 | Y14: =A14*1 -> 46267 | Z14: =B14&"."&Y14 -> CLAUDIAVALERO.46267 | AA14: =SUMIFS([2]!Consulta1[CONTADOR],[2]!Consulta1[CONCATENADO],[2]BD!Z14) -> 58 | AB14: =IF(B14="RSTASPECTAGENT","NÃO","SIM") -> SIM | AC14: =VLOOKUP(A14*1,[2]AUX!B:D,3,0) -> 2 | AD14: =VLOOKUP(C14,[2]AUX!J:K,2,0) -> BRADESCO | AE14: =SUM(AH14:AK14) -> 0.340962 | AF14: =E14*1-D14*1 -> 0.361423 | AG14: =IF(IF(AE14>AF14,0,AF14-AE14)<0,0,IF(AE14>AF14,0,AF14-AE14)) -> 0.020461 | AH14: =J14*1 -> 0.012292 | AI14: =L14*1 -> 0.009572 | AJ14: =I14*1 -> 0.041435 | AK14: =SUM(M14*1,N14*1,O14*1,P14*1,Q14*1,R14*1,S14*1,T14*1,U14*1,V14*1,W14*1) -> 0.277663 | AL14: =SUM(AH14:AJ14) -> 0.063299 | AM14: =SUM(S14*1,T14*1,U14*1) -> 0.057385 | AN14: =AK14-AM14 -> 0.220278
A15: 2026-09-01 | B15: BRUNOBEZERRA | C15: VP_STD_PF_DISCADOR | D15: 0.352836 | E15: 0.695926 | F15: 0.34309 | G15: 1 | H15: 8.1e-05 | I15: 0.172188 | J15: 0.05037 | K15: 96 | L15: 0.024688 | M15: 0.002662 | N15: 0 | O15: 0 | P15: 0.006076 | Q15: 0.005926 | R15: 0 | S15: 0.042928 | T15: 0.007014 | U15: 0.007199 | V15: 0.023958 | W15: 0 | X15: PF | Y15: =A15*1 -> 46266 | Z15: =B15&"."&Y15 -> BRUNOBEZERRA.46266 | AA15: =SUMIFS([2]!Consulta1[CONTADOR],[2]!Consulta1[CONCATENADO],[2]BD!Z15) -> 0 | AB15: =IF(B15="RSTASPECTAGENT","NÃO","SIM") -> SIM | AC15: =VLOOKUP(A15*1,[2]AUX!B:D,3,0) -> 1 | AD15: =VLOOKUP(C15,[2]AUX!J:K,2,0) -> SANTANDER | AE15: =SUM(AH15:AK15) -> 0.343009 | AF15: =E15*1-D15*1 -> 0.34309 | AG15: =IF(IF(AE15>AF15,0,AF15-AE15)<0,0,IF(AE15>AF15,0,AF15-AE15)) -> 8.1e-05 | AH15: =J15*1 -> 0.05037 | AI15: =L15*1 -> 0.024688 | AJ15: =I15*1 -> 0.172188 | AK15: =SUM(M15*1,N15*1,O15*1,P15*1,Q15*1,R15*1,S15*1,T15*1,U15*1,V15*1,W15*1) -> 0.095763 | AL15: =SUM(AH15:AJ15) -> 0.247246 | AM15: =SUM(S15*1,T15*1,U15*1) -> 0.057141 | AN15: =AK15-AM15 -> 0.038622
A16: 2026-09-10 | B16: KATIAMORAIS | C16: VP_BRAD_01 | D16: 0.352616 | E16: 0.696262 | F16: 0.343646 | G16: 1 | H16: 0 | I16: 0.028681 | J16: 0.011609 | K16: 39 | L16: 0.002951 | M16: 0 | N16: 0 | O16: 0 | P16: 0 | Q16: 0 | R16: 0.242002 | S16: 0.044595 | T16: 0.006956 | U16: 0.006863 | V16: 0 | W16: 0 | Y16: =A16*1 -> 46275 | Z16: =B16&"."&Y16 -> KATIAMORAIS.46275 | AA16: =SUMIFS([2]!Consulta1[CONTADOR],[2]!Consulta1[CONCATENADO],[2]BD!Z16) -> 39 | AB16: =IF(B16="RSTASPECTAGENT","NÃO","SIM") -> SIM | AC16: =VLOOKUP(A16*1,[2]AUX!B:D,3,0) -> 7 | AD16: =VLOOKUP(C16,[2]AUX!J:K,2,0) -> BRADESCO | AE16: =SUM(AH16:AK16) -> 0.343657 | AF16: =E16*1-D16*1 -> 0.343646 | AG16: =IF(IF(AE16>AF16,0,AF16-AE16)<0,0,IF(AE16>AF16,0,AF16-AE16)) -> 0 | AH16: =J16*1 -> 0.011609 | AI16: =L16*1 -> 0.002951 | AJ16: =I16*1 -> 0.028681 | AK16: =SUM(M16*1,N16*1,O16*1,P16*1,Q16*1,R16*1,S16*1,T16*1,U16*1,V16*1,W16*1) -> 0.300416 | AL16: =SUM(AH16:AJ16) -> 0.043241 | AM16: =SUM(S16*1,T16*1,U16*1) -> 0.058414 | AN16: =AK16-AM16 -> 0.242002 | AO16: B2
A17: 2026-09-01 | B17: NARIELEGUEDES | C17: VP_COLCHAO | D17: 0.350602 | E17: 0.696435 | F17: 0.345833 | G17: 1 | H17: 1.2e-05 | I17: 0.000162 | J17: 0 | K17: 47 | L17: 0 | M17: 0 | N17: 0 | O17: 0 | P17: 0 | Q17: 0 | R17: 0.290266 | S17: 0.041806 | T17: 0.006505 | U17: 0.007083 | V17: 0 | W17: 0 | Y17: =A17*1 -> 46266 | Z17: =B17&"."&Y17 -> NARIELEGUEDES.46266 | AA17: =SUMIFS([2]!Consulta1[CONTADOR],[2]!Consulta1[CONCATENADO],[2]BD!Z17) -> 47 | AB17: =IF(B17="RSTASPECTAGENT","NÃO","SIM") -> SIM | AC17: =VLOOKUP(A17*1,[2]AUX!B:D,3,0) -> 1 | AD17: =VLOOKUP(C17,[2]AUX!J:K,2,0) -> COLCHÃO | AE17: =SUM(AH17:AK17) -> 0.345822 | AF17: =E17*1-D17*1 -> 0.345833 | AG17: =IF(IF(AE17>AF17,0,AF17-AE17)<0,0,IF(AE17>AF17,0,AF17-AE17)) -> 1.1e-05 | AH17: =J17*1 -> 0 | AI17: =L17*1 -> 0 | AJ17: =I17*1 -> 0.000162 | AK17: =SUM(M17*1,N17*1,O17*1,P17*1,Q17*1,R17*1,S17*1,T17*1,U17*1,V17*1,W17*1) -> 0.34566 | AL17: =SUM(AH17:AJ17) -> 0.000162 | AM17: =SUM(S17*1,T17*1,U17*1) -> 0.055394 | AN17: =AK17-AM17 -> 0.290266
A18: 2026-09-09 | B18: SAMARAPAIXAO | C18: VP_STD_PJ_MANUAL | D18: 0.356169 | E18: 0.69706 | F18: 0.338704 | G18: 3 | H18: 0.002245 | I18: 0.071042 | J18: 0.02316 | K18: 80 | L18: 0.030567 | M18: 0 | N18: 0 | O18: 0 | P18: 0 | Q18: 0 | R18: 0.163646 | S18: 0.042025 | T18: 0.008206 | U18: 0 | V18: 0 | W18: 0 | X18: B2 | Y18: =A18*1 -> 46274 | Z18: =B18&"."&Y18 -> SAMARAPAIXAO.46274 | AA18: =SUMIFS([2]!Consulta1[CONTADOR],[2]!Consulta1[CONCATENADO],[2]BD!Z18) -> 80 | AB18: =IF(B18="RSTASPECTAGENT","NÃO","SIM") -> SIM | AC18: =VLOOKUP(A18*1,[2]AUX!B:D,3,0) -> 6 | AD18: =VLOOKUP(C18,[2]AUX!J:K,2,0) -> SANTANDER | AE18: =SUM(AH18:AK18) -> 0.338646 | AF18: =E18*1-D18*1 -> 0.340891 | AG18: =IF(IF(AE18>AF18,0,AF18-AE18)<0,0,IF(AE18>AF18,0,AF18-AE18)) -> 0.002245 | AH18: =J18*1 -> 0.02316 | AI18: =L18*1 -> 0.030567 | AJ18: =I18*1 -> 0.071042 | AK18: =SUM(M18*1,N18*1,O18*1,P18*1,Q18*1,R18*1,S18*1,T18*1,U18*1,V18*1,W18*1) -> 0.213877 | AL18: =SUM(AH18:AJ18) -> 0.124769 | AM18: =SUM(S18*1,T18*1,U18*1) -> 0.050231 | AN18: =AK18-AM18 -> 0.163646 | AO18: B1
A19: 2026-09-01 | B19: RENATOOLIVEIRA | C19: VP_STD_PJ_MANUAL | D19: 0.352824 | E19: 0.695764 | F19: 0.34294 | G19: 1 | H19: 5.8e-05 | I19: 0.03647 | J19: 0.027373 | K19: 91 | L19: 0.011319 | M19: 0 | N19: 0 | O19: 0 | P19: 0 | Q19: 0.011782 | R19: 0.194606 | S19: 0.041412 | T19: 0.007627 | U19: 0.008252 | V19: 0.004039 | W19: 0 | X19: B1 | Y19: =A19*1 -> 46266 | Z19: =B19&"."&Y19 -> RENATOOLIVEIRA.46266 | AA19: =SUMIFS([2]!Consulta1[CONTADOR],[2]!Consulta1[CONCATENADO],[2]BD!Z19) -> 91 | AB19: =IF(B19="RSTASPECTAGENT","NÃO","SIM") -> SIM | AC19: =VLOOKUP(A19*1,[2]AUX!B:D,3,0) -> 1 | AD19: =VLOOKUP(C19,[2]AUX!J:K,2,0) -> SANTANDER | AE19: =SUM(AH19:AK19) -> 0.34288 | AF19: =E19*1-D19*1 -> 0.34294 | AG19: =IF(IF(AE19>AF19,0,AF19-AE19)<0,0,IF(AE19>AF19,0,AF19-AE19)) -> 6e-05 | AH19: =J19*1 -> 0.027373 | AI19: =L19*1 -> 0.011319 | AJ19: =I19*1 -> 0.03647 | AK19: =SUM(M19*1,N19*1,O19*1,P19*1,Q19*1,R19*1,S19*1,T19*1,U19*1,V19*1,W19*1) -> 0.267718 | AL19: =SUM(AH19:AJ19) -> 0.075162 | AM19: =SUM(S19*1,T19*1,U19*1) -> 0.057291 | AN19: =AK19-AM19 -> 0.210427
A20: 2026-09-04 | B20: KAUANEGOMES | C20: VP_BRAD_01 | D20: 0.354595 | E20: 0.696539 | F20: 0.341944 | G20: 1 | H20: 5.8e-05 | I20: 0.048843 | J20: 0.017847 | K20: 106 | L20: 0.006794 | M20: 0 | N20: 0 | O20: 0 | P20: 0 | Q20: 0.00397 | R20: 0.206667 | S20: 0.043819 | T20: 0.007002 | U20: 0.006944 | V20: 0 | W20: 0 | Y20: =A20*1 -> 46269 | Z20: =B20&"."&Y20 -> KAUANEGOMES.46269 | AA20: =SUMIFS([2]!Consulta1[CONTADOR],[2]!Consulta1[CONCATENADO],[2]BD!Z20) -> 0 | AB20: =IF(B20="RSTASPECTAGENT","NÃO","SIM") -> SIM | AC20: =VLOOKUP(A20*1,[2]AUX!B:D,3,0) -> 4 | AD20: =VLOOKUP(C20,[2]AUX!J:K,2,0) -> BRADESCO | AE20: =SUM(AH20:AK20) -> 0.341886 | AF20: =E20*1-D20*1 -> 0.341944 | AG20: =IF(IF(AE20>AF20,0,AF20-AE20)<0,0,IF(AE20>AF20,0,AF20-AE20)) -> 5.8e-05 | AH20: =J20*1 -> 0.017847 | AI20: =L20*1 -> 0.006794 | AJ20: =I20*1 -> 0.048843 | AK20: =SUM(M20*1,N20*1,O20*1,P20*1,Q20*1,R20*1,S20*1,T20*1,U20*1,V20*1,W20*1) -> 0.268402 | AL20: =SUM(AH20:AJ20) -> 0.073484 | AM20: =SUM(S20*1,T20*1,U20*1) -> 0.057765 | AN20: =AK20-AM20 -> 0.210637
A21: 2026-09-01 | B21: SAMIANASCIMENTO | C21: VP_COOPER_01 | D21: 0.338275 | E21: 0.676204 | F21: 0.337928 | G21: 1 | H21: 1.2e-05 | I21: 0.012095 | J21: 0.008704 | K21: 52 | L21: 0.003854 | M21: 0 | N21: 0 | O21: 0 | P21: 0 | Q21: 0.00456 | R21: 0.255428 | S21: 0.043634 | T21: 0.009641 | U21: 0 | V21: 0 | W21: 0 | Y21: =A21*1 -> 46266 | Z21: =B21&"."&Y21 -> SAMIANASCIMENTO.46266 | AA21: =SUMIFS([2]!Consulta1[CONTADOR],[2]!Consulta1[CONCATENADO],[2]BD!Z21) -> 52 | AB21: =IF(B21="RSTASPECTAGENT","NÃO","SIM") -> SIM | AC21: =VLOOKUP(A21*1,[2]AUX!B:D,3,0) -> 1 | AD21: =VLOOKUP(C21,[2]AUX!J:K,2,0) -> COOPERFORTE | AE21: =SUM(AH21:AK21) -> 0.337916 | AF21: =E21*1-D21*1 -> 0.337929 | AG21: =IF(IF(AE21>AF21,0,AF21-AE21)<0,0,IF(AE21>AF21,0,AF21-AE21)) -> 1.3e-05 | AH21: =J21*1 -> 0.008704 | AI21: =L21*1 -> 0.003854 | AJ21: =I21*1 -> 0.012095 | AK21: =SUM(M21*1,N21*1,O21*1,P21*1,Q21*1,R21*1,S21*1,T21*1,U21*1,V21*1,W21*1) -> 0.313263 | AL21: =SUM(AH21:AJ21) -> 0.024653 | AM21: =SUM(S21*1,T21*1,U21*1) -> 0.053275 | AN21: =AK21-AM21 -> 0.259988 | AO21: B2
A22: 2026-09-03 | B22: CLAUDIAVALERO | C22: VP_BRAD_01 | D22: 0.334653 | E22: 0.695926 | F22: 0.361273 | G22: 1 | H22: 0.02897 | I22: 0.033044 | J22: 0.009757 | K22: 60 | L22: 0.011713 | M22: 0 | N22: 0 | O22: 0 | P22: 0 | Q22: 0 | R22: 0.199942 | S22: 0.043333 | T22: 0.008935 | U22: 0.007859 | V22: 0.01772 | W22: 0 | Y22: =A22*1 -> 46268 | Z22: =B22&"."&Y22 -> CLAUDIAVALERO.46268 | AA22: =SUMIFS([2]!Consulta1[CONTADOR],[2]!Consulta1[CONCATENADO],[2]BD!Z22) -> 60 | AB22: =IF(B22="RSTASPECTAGENT","NÃO","SIM") -> SIM | AC22: =VLOOKUP(A22*1,[2]AUX!B:D,3,0) -> 3 | AD22: =VLOOKUP(C22,[2]AUX!J:K,2,0) -> BRADESCO | AE22: =SUM(AH22:AK22) -> 0.332303 | AF22: =E22*1-D22*1 -> 0.361273 | AG22: =IF(IF(AE22>AF22,0,AF22-AE22)<0,0,IF(AE22>AF22,0,AF22-AE22)) -> 0.02897 | AH22: =J22*1 -> 0.009757 | AI22: =L22*1 -> 0.011713 | AJ22: =I22*1 -> 0.033044 | AK22: =SUM(M22*1,N22*1,O22*1,P22*1,Q22*1,R22*1,S22*1,T22*1,U22*1,V22*1,W22*1) -> 0.277789 | AL22: =SUM(AH22:AJ22) -> 0.054514 | AM22: =SUM(S22*1,T22*1,U22*1) -> 0.060127 | AN22: =AK22-AM22 -> 0.217662
A23: 2026-09-01 | B23: LUCASPEDRACA | C23: VP_STD_PJ_DISCADOR | D23: 0.356678 | E23: 0.695718 | F23: 0.33787 | G23: 3 | H23: 0.001146 | I23: 0.101655 | J23: 0.033519 | K23: 101 | L23: 0.031447 | M23: 0.033935 | N23: 0 | O23: 0 | P23: 0 | Q23: 0.020104 | R23: 0 | S23: 0.043762 | T23: 0.007141 | U23: 0.006991 | V23: 0.009965 | W23: 0.049375 | X23: B1 | Y23: =A23*1 -> 46266 | Z23: =B23&"."&Y23 -> LUCASPEDRACA.46266 | AA23: =SUMIFS([2]!Consulta1[CONTADOR],[2]!Consulta1[CONCATENADO],[2]BD!Z23) -> 101 | AB23: =IF(B23="RSTASPECTAGENT","NÃO","SIM") -> SIM | AC23: =VLOOKUP(A23*1,[2]AUX!B:D,3,0) -> 1 | AD23: =VLOOKUP(C23,[2]AUX!J:K,2,0) -> SANTANDER | AE23: =SUM(AH23:AK23) -> 0.337894 | AF23: =E23*1-D23*1 -> 0.33904 | AG23: =IF(IF(AE23>AF23,0,AF23-AE23)<0,0,IF(AE23>AF23,0,AF23-AE23)) -> 0.001146 | AH23: =J23*1 -> 0.033519 | AI23: =L23*1 -> 0.031447 | AJ23: =I23*1 -> 0.101655 | AK23: =SUM(M23*1,N23*1,O23*1,P23*1,Q23*1,R23*1,S23*1,T23*1,U23*1,V23*1,W23*1) -> 0.171273 | AL23: =SUM(AH23:AJ23) -> 0.166621 | AM23: =SUM(S23*1,T23*1,U23*1) -> 0.057894 | AN23: =AK23-AM23 -> 0.113379
A24: 2026-09-08 | B24: LUCASPEDRACA | C24: VP_STD_PJ_DISCADOR | D24: 0.337361 | E24: 0.695544 | F24: 0.350185 | G24: 2 | H24: 0.007975 | I24: 0.152014 | J24: 0.047407 | K24: 128 | L24: 0.033241 | M24: 0.015162 | N24: 0 | O24: 0 | P24: 0 | Q24: 0.021065 | R24: 0 | S24: 0.041308 | T24: 0.006944 | U24: 0.006435 | V24: 0.004097 | W24: 0.022535 | X24: B1 | Y24: =A24*1 -> 46273 | Z24: =B24&"."&Y24 -> LUCASPEDRACA.46273 | AA24: =SUMIFS([2]!Consulta1[CONTADOR],[2]!Consulta1[CONCATENADO],[2]BD!Z24) -> 128 | AB24: =IF(B24="RSTASPECTAGENT","NÃO","SIM") -> SIM | AC24: =VLOOKUP(A24*1,[2]AUX!B:D,3,0) -> 5 | AD24: =VLOOKUP(C24,[2]AUX!J:K,2,0) -> SANTANDER | AE24: =SUM(AH24:AK24) -> 0.350208 | AF24: =E24*1-D24*1 -> 0.358183 | AG24: =IF(IF(AE24>AF24,0,AF24-AE24)<0,0,IF(AE24>AF24,0,AF24-AE24)) -> 0.007975 | AH24: =J24*1 -> 0.047407 | AI24: =L24*1 -> 0.033241 | AJ24: =I24*1 -> 0.152014 | AK24: =SUM(M24*1,N24*1,O24*1,P24*1,Q24*1,R24*1,S24*1,T24*1,U24*1,V24*1,W24*1) -> 0.117546 | AL24: =SUM(AH24:AJ24) -> 0.232662 | AM24: =SUM(S24*1,T24*1,U24*1) -> 0.054687 | AN24: =AK24-AM24 -> 0.062859
A25: 2026-09-08 | B25: ANTONIARENATA | C25: VP_STD_PJ_MANUAL | D25: 0.342384 | E25: 0.696319 | F25: 0.353935 | G25: 1 | H25: 0 | I25: 0.000185 | J25: 0 | K25: 52 | L25: 0 | M25: 0 | N25: 0 | O25: 0 | P25: 0 | Q25: 0.017153 | R25: 0.280104 | S25: 0.041262 | T25: 0.007685 | U25: 0.007569 | V25: 0 | W25: 0 | X25: PREV | Y25: =A25*1 -> 46273 | Z25: =B25&"."&Y25 -> ANTONIARENATA.46273 | AA25: =SUMIFS([2]!Consulta1[CONTADOR],[2]!Consulta1[CONCATENADO],[2]BD!Z25) -> 52 | AB25: =IF(B25="RSTASPECTAGENT","NÃO","SIM") -> SIM | AC25: =VLOOKUP(A25*1,[2]AUX!B:D,3,0) -> 5 | AD25: =VLOOKUP(C25,[2]AUX!J:K,2,0) -> SANTANDER | AE25: =SUM(AH25:AK25) -> 0.353958 | AF25: =E25*1-D25*1 -> 0.353935 | AG25: =IF(IF(AE25>AF25,0,AF25-AE25)<0,0,IF(AE25>AF25,0,AF25-AE25)) -> 0 | AH25: =J25*1 -> 0 | AI25: =L25*1 -> 0 | AJ25: =I25*1 -> 0.000185 | AK25: =SUM(M25*1,N25*1,O25*1,P25*1,Q25*1,R25*1,S25*1,T25*1,U25*1,V25*1,W25*1) -> 0.353773 | AL25: =SUM(AH25:AJ25) -> 0.000185 | AM25: =SUM(S25*1,T25*1,U25*1) -> 0.056516 | AN25: =AK25-AM25 -> 0.297257
